Workbook

Sheet Read_me
A1: HOW TO USE
A2: 1. Edit only blue cells on Assumptions. Yellow fill = assumption that most needs a real number.
A3: 2. Three scenarios run side by side (Model_Cons / Model_Base / Model_Aggr). Summary, Unit_Economics and Sensitivity update automatically.
A4: 3. Months are counted from launch. Calendar mapping uses 'Calendar month of launch' for seasonality only.
A6: STRUCTURE
A7: Funnel -> cohort survivors -> AUM (deposits, exits, partial withdrawals) -> revenue -> bonus cost -> costs -> net contribution.
A8: Counterfactual rows re-run AUM without Pause & Reflect to size AUM retained.
A10: SIMPLIFICATIONS (be honest about them)
A11: - Constant monthly churn; one average balance for all users; no discounting; no compounding of bonus interest.
A12: - Bonus interest is paid on all Habitlock savings balances, but only 'incrementality' of revenue is counted as new.
A13: - Badge levels follow deck unlock rules by tenure; Lv5 and Lv6 depend on auto-invest adoption after AI launch.
A14: - All take rates, CAC, retention and balances are illustrative. Replace with Infina data before using any output.
A16: COLOUR CODE: blue input, black formula, green link to another sheet, yellow fill = key assumption.

Sheet Summary
A1: Habitlock financial model: summary
A2: 18 months from launch. VND. Every input is illustrative unless the Assumptions tab says 'Deck'. This is a reasoning tool, not a forecast.
A4: Metric | B4: Unit | C4: Conservative | D4: Base | E4: Aggressive
A5: Scale
A6: Users acquired, cumulative M18 | B6: users | C6: =Model_Cons!U13 -> 150000 | D6: =Model_Base!U13 -> 300000 | E6: =Model_Aggr!U13 -> 600000
A7: Activated users (first deposit), cumulative | B7: users | C7: =Model_Cons!C10 -> 75000 | D7: =Model_Base!C10 -> 180000 | E7: =Model_Aggr!C10 -> 420000
A8: Active users, M18 | B8: users | C8: =Model_Cons!U11 -> 30693.461 | D8: =Model_Base!U11 -> 96828.953 | E8: =Model_Aggr!U11 -> 281987.78
A9: AUM, M18 | B9: VND bn | C9: =Model_Cons!U21/1000 -> 48.707519 | D9: =Model_Base!U21/1000 -> 298.58156 | E9: =Model_Aggr!U21/1000 -> 1584.7798
A10: Average balance per active user, M18 | B10: VND mn | C10: =Model_Cons!U21/Model_Cons!U11 -> 1.5869022 | D10: =Model_Base!U21/Model_Base!U11 -> 3.083598 | E10: =Model_Aggr!U21/Model_Aggr!U11 -> 5.6200303
A11: AUM retained thanks to Pause & Reflect, M18 | B11: VND bn | C11: =Model_Cons!U31/1000 -> 0.69851615 | D11: =Model_Base!U31/1000 -> 7.8733198 | E11: =Model_Aggr!U31/1000 -> 62.809597
A12: P&L, 18 months, VND mn
A13: Incremental revenue | B13: VND mn | C13: =Model_Cons!C36 -> 56.309089 | D13: =Model_Base!C36 -> 721.2107 | E13: =Model_Aggr!C36 -> 6330.0942
A14: Bonus interest cost | B14: VND mn | C14: =Model_Cons!C38 -> 32.438328 | D14: =Model_Base!C38 -> 233.83508 | E14: =Model_Aggr!C38 -> 1315.3696
A15: Bonus cost as % of incremental revenue | B15: % | C15: =IF(C13>0,C14/C13,0) -> 0.57607624 | D15: =IF(D13>0,D14/D13,0) -> 0.32422575 | E15: =IF(E13>0,E14/E13,0) -> 0.20779621
A16: Acquisition spend | B16: VND mn | C16: =Model_Cons!C39 -> 15000 | D16: =Model_Base!C39 -> 21600 | E16: =Model_Aggr!C39 -> 33600
A17: Build + run cost | B17: VND mn | C17: =Model_Cons!C40+Model_Cons!C41 -> 3660 | D17: =Model_Base!C40+Model_Base!C41 -> 3660 | E17: =Model_Aggr!C40+Model_Aggr!C41 -> 3660
A18: Cumulative net contribution, M18 | B18: VND mn | C18: =Model_Cons!U43 -> -18636.129 | D18: =Model_Base!U43 -> -24772.624 | E18: =Model_Aggr!U43 -> -32245.275
A19: First month cumulative net >= 0 | B19: month | C19: =IFERROR(MATCH(1,Model_Cons!D44:U44,0),"Not within 18M") -> Not within 18M | D19: =IFERROR(MATCH(1,Model_Base!D44:U44,0),"Not within 18M") -> Not within 18M | E19: =IFERROR(MATCH(1,Model_Aggr!D44:U44,0),"Not within 18M") -> Not within 18M
A20: First month monthly net >= 0 | B20: month | C20: =IFERROR(MATCH(1,Model_Cons!D45:U45,0),"Not within 18M") -> Not within 18M | D20: =IFERROR(MATCH(1,Model_Base!D45:U45,0),"Not within 18M") -> Not within 18M | E20: =IFERROR(MATCH(1,Model_Aggr!D45:U45,0),"Not within 18M") -> Not within 18M
A21: Cross-checks against the deck
A22: Required P&R effectiveness to hit deck Dec adherence target | B22: % | C22: =(Assumptions!$C$44-Assumptions!$C$43)/(1-Assumptions!$C$43) -> 0.47368421 | D22: =(Assumptions!$D$44-Assumptions!$D$43)/(1-Assumptions!$D$43) -> 0.47368421 | E22: =(Assumptions!$E$44-Assumptions!$E$43)/(1-Assumptions!$E$43) -> 0.47368421
A23: P&R effectiveness assumed in this scenario | B23: % | C23: =Assumptions!$C$22 -> 0.1 | D23: =Assumptions!$D$22 -> 0.2 | E23: =Assumptions!$E$22 -> 0.35
A24: Earliest month any user can reach Lv4 (badge launch + 3) | B24: month | C24: =Assumptions!$C$32+3 -> 7 | D24: =Assumptions!$D$32+3 -> 7 | E24: =Assumptions!$E$32+3 -> 7
A25: Deck Phase 3 (needs Lv4 users) ends in month | B25: month | C25: =Assumptions!$C$34 -> 6 | D25: =Assumptions!$D$34 -> 6 | E25: =Assumptions!$E$34 -> 6
A26: Timeline check | C26: =IF(C24>C25,"CONFLICT: Lv4 arrives after Phase 3","OK") -> CONFLICT: Lv4 arrives after Phase 3 | D26: =IF(D24>D25,"CONFLICT: Lv4 arrives after Phase 3","OK") -> CONFLICT: Lv4 arrives after Phase 3 | E26: =IF(E24>E25,"CONFLICT: Lv4 arrives after Phase 3","OK") -> CONFLICT: Lv4 arrives after Phase 3
A27: Share of 'ready' pool reached by M18 (deck claims 20-30%) | B27: % | C27: =Assumptions!$C$14 -> 0.05 | D27: =Assumptions!$D$14 -> 0.1 | E27: =Assumptions!$E$14 -> 0.2
A28: Model integrity checks
A29: Activated users = reach x pool x activation | B29: check | C29: =IF(ABS(Model_Cons!C10-Assumptions!$C$14*Assumptions!$C$12*Assumptions!$C$15)<1,"OK","ERROR") -> OK | D29: =IF(ABS(Model_Base!C10-Assumptions!$D$14*Assumptions!$D$12*Assumptions!$D$15)<1,"OK","ERROR") -> OK | E29: =IF(ABS(Model_Aggr!C10-Assumptions!$E$14*Assumptions!$E$12*Assumptions!$E$15)<1,"OK","ERROR") -> OK
A30: AUM never negative | B30: check | C30: =IF(MIN(Model_Cons!D21:U21)>=0,"OK","ERROR") -> OK | D30: =IF(MIN(Model_Base!D21:U21)>=0,"OK","ERROR") -> OK | E30: =IF(MIN(Model_Aggr!D21:U21)>=0,"OK","ERROR") -> OK
A31: Signup weights sum to 100% | B31: check | C31: =IF(ABS(SUM(Model_Cons!D7:U7)-1)<0.0001,"OK","ERROR") -> OK | D31: =IF(ABS(SUM(Model_Base!D7:U7)-1)<0.0001,"OK","ERROR") -> OK | E31: =IF(ABS(SUM(Model_Aggr!D7:U7)-1)<0.0001,"OK","ERROR") -> OK

Sheet Unit_Economics
A1: Unit economics per active user at M18
A2: Steady-state view using M18 mix. Undiscounted LTV. Take rates and CAC are placeholders: read the ratios as sensitivity, not as a forecast.
A4: Metric | B4: Unit | C4: Conservative | D4: Base | E4: Aggressive
A5: Average balance per active user | B5: VND mn | C5: =Model_Cons!U21/Model_Cons!U11 -> 1.5869022 | D5: =Model_Base!U21/Model_Base!U11 -> 3.083598 | E5: =Model_Aggr!U21/Model_Aggr!U11 -> 5.6200303
A6: Fund share of AUM | B6: % | C6: =Model_Cons!U22 -> 0.05 | D6: =Model_Base!U22 -> 0.1 | E6: =Model_Aggr!U22 -> 0.2
A7: Blended gross take rate | B7: %/yr | C7: =(1-C6)*Assumptions!$C$24+C6*Assumptions!$C$25 -> 0.0031 | D7: =(1-D6)*Assumptions!$D$24+D6*Assumptions!$D$25 -> 0.0053 | E7: =(1-E6)*Assumptions!$E$24+E6*Assumptions!$E$25 -> 0.0076
A8: Incrementality | B8: % | C8: =Assumptions!$C$26 -> 0.5 | D8: =Assumptions!$D$26 -> 0.7 | E8: =Assumptions!$E$26 -> 0.9
A9: Incremental revenue per user per year | B9: VND '000 | C9: =C5*C7*C8*Assumptions!$C$7/Assumptions!$C$8 -> 2.4596983 | D9: =D5*D7*D8*Assumptions!$D$7/Assumptions!$D$8 -> 11.440148 | E9: =E5*E7*E8*Assumptions!$E$7/Assumptions!$E$8 -> 38.441007
A10: Weighted bonus rate on savings | B10: %/yr | C10: =Model_Cons!U37 -> 0.0010670685 | D10: =Model_Base!U37 -> 0.001508751 | E10: =Model_Aggr!U37 -> 0.0019923606
A11: Bonus cost per user per year | B11: VND '000 | C11: =C5*(1-C6)*C10*Assumptions!$C$7/Assumptions!$C$8 -> 1.6086667 | D11: =D5*(1-D6)*D10*Assumptions!$D$7/Assumptions!$D$8 -> 4.1871432 | E11: =E5*(1-E6)*E10*Assumptions!$E$7/Assumptions!$E$8 -> 8.9577014
A12: Net margin per user per year | B12: VND '000 | C12: =C9-C11 -> 0.85103168 | D12: =D9-D11 -> 7.2530052 | E12: =E9-E11 -> 29.483306
A13: Net margin per user per month | B13: VND '000 | C13: =C12/12 -> 0.070919307 | D13: =D12/12 -> 0.6044171 | E13: =E12/12 -> 2.4569421
A14: Expected lifetime (1 / monthly churn) | B14: months | C14: =1/Assumptions!$C$18 -> 8.3333333 | D14: =1/Assumptions!$D$18 -> 12.5 | E14: =1/Assumptions!$E$18 -> 20
A15: LTV (undiscounted) | B15: VND '000 | C15: =C13*C14 -> 0.59099422 | D15: =D13*D14 -> 7.5552138 | E15: =E13*E14 -> 49.138843
A16: CAC per activated user | B16: VND '000 | C16: =Assumptions!$C$16/Assumptions!$C$8 -> 200 | D16: =Assumptions!$D$16/Assumptions!$D$8 -> 120 | E16: =Assumptions!$E$16/Assumptions!$E$8 -> 80
A17: LTV / CAC | B17: x | C17: =IF(C16>0,C15/C16,0) -> 0.0029549711 | D17: =IF(D16>0,D15/D16,0) -> 0.062960115 | E17: =IF(E16>0,E15/E16,0) -> 0.61423553
A18: CAC payback | B18: months | C18: =IF(C13>0,C16/C13,"Never") -> 2820.1065 | D18: =IF(D13>0,D16/D13,"Never") -> 198.53839 | E18: =IF(E13>0,E16/E13,"Never") -> 32.560799
A19: Max sustainable bonus rate (net margin = 0) | B19: %/yr | C19: =IF(C6<1,C7*C8/(1-C6),0) -> 0.0016315789 | D19: =IF(D6<1,D7*D8/(1-D6),0) -> 0.0041222222 | E19: =IF(E6<1,E7*E8/(1-E6),0) -> 0.00855
A20: Headroom: max minus actual bonus rate | B20: %/yr | C20: =C19-C10 -> 0.00056451043 | D20: =D19-D10 -> 0.0026134713 | E20: =E19-E10 -> 0.0065576394
A22: What must be true for the economics to close
A23: Net margin per VND of average AUM (take x incr minus bonus on savings) | B23: %/yr | C23: =C7*C8-(1-C6)*C10 -> 0.00053628491 | D23: =D7*D8-(1-D6)*D10 -> 0.0023521241 | E23: =E7*E8-(1-E6)*E10 -> 0.0052461115
A24: AUM needed just to cover monthly run cost | B24: VND bn | C24: =IF(C23>0,Assumptions!$C$41*12/Assumptions!$C$7/C23/1000,"Never") -> 2685.1399 | D24: =IF(D23>0,Assumptions!$D$41*12/Assumptions!$D$7/D23/1000,"Never") -> 612.21259 | E24: =IF(E23>0,Assumptions!$E$41*12/Assumptions!$E$7/E23/1000,"Never") -> 274.48902
A25: AUM actually reached at M18 | B25: VND bn | C25: =Model_Cons!U21/1000 -> 48.707519 | D25: =Model_Base!U21/1000 -> 298.58156 | E25: =Model_Aggr!U21/1000 -> 1584.7798
A26: M18 AUM as multiple of break-even AUM | B26: x | C26: =IF(ISNUMBER(C24),C25/C24,0) -> 0.018139658 | D26: =IF(ISNUMBER(D24),D25/D24,0) -> 0.48770896 | E26: =IF(ISNUMBER(E24),E25/E24,0) -> 5.7735637
A27: Max CAC for LTV / CAC = 3 | B27: VND '000 | C27: =C15/3 -> 0.19699807 | D27: =D15/3 -> 2.5184046 | E27: =E15/3 -> 16.379614
A28: Avg balance per user needed for LTV / CAC = 3 (current CAC, take rate, churn) | B28: VND mn | C28: =IF(C23>0,3*C16*12/C14/(C23*Assumptions!$C$7/Assumptions!$C$8),"Never") -> 1611.0839 | D28: =IF(D23>0,3*D16*12/D14/(D23*Assumptions!$D$7/Assumptions!$D$8),"Never") -> 146.93102 | E28: =IF(E23>0,3*E16*12/E14/(E23*Assumptions!$E$7/Assumptions!$E$8),"Never") -> 27.448902
A30: Reading guide: if M18 AUM is below break-even AUM, the product does not cover even its own run cost, regardless of CAC. If LTV / CAC < 3, paid acquisition destroys value; the case then depends on organic or partner-funded growth.

Sheet Sensitivity
A1: Sensitivity: does the bonus interest pay for itself?
A2: Table 1 compares each badge's bonus with the net take rate Infina keeps. Table 2 flexes the two biggest unknowns on the Base scenario.
A4: Table 1: spread per VND of savings balance after bonus (incremental take rate minus bonus), annual
A5: Badge | B5: Bonus (annual) | C5: Conservative | D5: Base | E5: Aggressive
A6: =Assumptions!A48&" "&Assumptions!B48 -> Lv1 Saving Rookie | B6: =Assumptions!C48 -> 0.0005 | C6: =Assumptions!$C$24*Assumptions!$C$26-$B6 -> 0.001 | D6: =Assumptions!$D$24*Assumptions!$D$26-$B6 -> 0.003 | E6: =Assumptions!$E$24*Assumptions!$E$26-$B6 -> 0.0058
A7: =Assumptions!A49&" "&Assumptions!B49 -> Lv2 Steady Cash Flow | B7: =Assumptions!C49 -> 0.001 | C7: =Assumptions!$C$24*Assumptions!$C$26-$B7 -> 0.0005 | D7: =Assumptions!$D$24*Assumptions!$D$26-$B7 -> 0.0025 | E7: =Assumptions!$E$24*Assumptions!$E$26-$B7 -> 0.0053
A8: =Assumptions!A50&" "&Assumptions!B50 -> Lv3 Motivation Builder | B8: =Assumptions!C50 -> 0.0015 | C8: =Assumptions!$C$24*Assumptions!$C$26-$B8 -> 0 | D8: =Assumptions!$D$24*Assumptions!$D$26-$B8 -> 0.002 | E8: =Assumptions!$E$24*Assumptions!$E$26-$B8 -> 0.0048
A9: =Assumptions!A51&" "&Assumptions!B51 -> Lv4 Accumulation Master | B9: =Assumptions!C51 -> 0.0025 | C9: =Assumptions!$C$24*Assumptions!$C$26-$B9 -> -0.001 | D9: =Assumptions!$D$24*Assumptions!$D$26-$B9 -> 0.001 | E9: =Assumptions!$E$24*Assumptions!$E$26-$B9 -> 0.0038
A10: =Assumptions!A52&" "&Assumptions!B52 -> Lv5 Habit Investor | B10: =Assumptions!C52 -> 0.003 | C10: =Assumptions!$C$24*Assumptions!$C$26-$B10 -> -0.0015 | D10: =Assumptions!$D$24*Assumptions!$D$26-$B10 -> 0.0005 | E10: =Assumptions!$E$24*Assumptions!$E$26-$B10 -> 0.0033
A11: =Assumptions!A53&" "&Assumptions!B53 -> Lv6 Growth Seeker | B11: =Assumptions!C53 -> 0.004 | C11: =Assumptions!$C$24*Assumptions!$C$26-$B11 -> -0.0025 | D11: =Assumptions!$D$24*Assumptions!$D$26-$B11 -> -0.0005 | E11: =Assumptions!$E$24*Assumptions!$E$26-$B11 -> 0.0023
A12: Negative (red) = a user at that level costs Infina more in bonus than they earn, before CAC and run costs. Bonus is paid on all balances; only the take rate is scaled by incrementality.
A14: Table 2: Base scenario, M18 run-rate annualised net contribution before acquisition spend (VND mn)
A15: Rows: multiplier on take rates. Columns: multiplier on bonus rates.
A16: Take-rate multiplier \ Bonus multiplier | B16: 0.5 | C16: 1 | D16: 1.5 | E16: 2 | F16: 3
A17: 0.5 | B17: =12*(Model_Base!U36*$A17-Model_Base!U38*B$16-Model_Base!U41) -> -1094.8259 | C17: =12*(Model_Base!U36*$A17-Model_Base!U38*C$16-Model_Base!U41) -> -1294.0941 | D17: =12*(Model_Base!U36*$A17-Model_Base!U38*D$16-Model_Base!U41) -> -1493.3623 | E17: =12*(Model_Base!U36*$A17-Model_Base!U38*E$16-Model_Base!U41) -> -1692.6306 | F17: =12*(Model_Base!U36*$A17-Model_Base!U38*F$16-Model_Base!U41) -> -2091.167
A18: 0.75 | B18: =12*(Model_Base!U36*$A18-Model_Base!U38*B$16-Model_Base!U41) -> -822.60471 | C18: =12*(Model_Base!U36*$A18-Model_Base!U38*C$16-Model_Base!U41) -> -1021.8729 | D18: =12*(Model_Base!U36*$A18-Model_Base!U38*D$16-Model_Base!U41) -> -1221.1412 | E18: =12*(Model_Base!U36*$A18-Model_Base!U38*E$16-Model_Base!U41) -> -1420.4094 | F18: =12*(Model_Base!U36*$A18-Model_Base!U38*F$16-Model_Base!U41) -> -1818.9458
A19: 1 | B19: =12*(Model_Base!U36*$A19-Model_Base!U38*B$16-Model_Base!U41) -> -550.38354 | C19: =12*(Model_Base!U36*$A19-Model_Base!U38*C$16-Model_Base!U41) -> -749.65176 | D19: =12*(Model_Base!U36*$A19-Model_Base!U38*D$16-Model_Base!U41) -> -948.91999 | E19: =12*(Model_Base!U36*$A19-Model_Base!U38*E$16-Model_Base!U41) -> -1148.1882 | F19: =12*(Model_Base!U36*$A19-Model_Base!U38*F$16-Model_Base!U41) -> -1546.7247
A20: 1.25 | B20: =12*(Model_Base!U36*$A20-Model_Base!U38*B$16-Model_Base!U41) -> -278.16237 | C20: =12*(Model_Base!U36*$A20-Model_Base!U38*C$16-Model_Base!U41) -> -477.43059 | D20: =12*(Model_Base!U36*$A20-Model_Base!U38*D$16-Model_Base!U41) -> -676.69882 | E20: =12*(Model_Base!U36*$A20-Model_Base!U38*E$16-Model_Base!U41) -> -875.96704 | F20: =12*(Model_Base!U36*$A20-Model_Base!U38*F$16-Model_Base!U41) -> -1274.5035
A21: 1.5 | B21: =12*(Model_Base!U36*$A21-Model_Base!U38*B$16-Model_Base!U41) -> -5.9411938 | C21: =12*(Model_Base!U36*$A21-Model_Base!U38*C$16-Model_Base!U41) -> -205.20942 | D21: =12*(Model_Base!U36*$A21-Model_Base!U38*D$16-Model_Base!U41) -> -404.47764 | E21: =12*(Model_Base!U36*$A21-Model_Base!U38*E$16-Model_Base!U41) -> -603.74587 | F21: =12*(Model_Base!U36*$A21-Model_Base!U38*F$16-Model_Base!U41) -> -1002.2823
A24: Table 3: Base scenario LTV / CAC by CAC (rows) and average balance multiplier (columns)
A25: CAC per activated user in VND thousand. 0 = purely organic. Balance multiplier scales the M18 average balance.
A26: CAC (VND '000) \ Balance multiplier | B26: 1 | C26: 2 | D26: 3 | E26: 4 | F26: 5
A27: 0 | B27: =IF($A27>0,Unit_Economics!$D$15*B$26/$A27,"organic") -> organic | C27: =IF($A27>0,Unit_Economics!$D$15*C$26/$A27,"organic") -> organic | D27: =IF($A27>0,Unit_Economics!$D$15*D$26/$A27,"organic") -> organic | E27: =IF($A27>0,Unit_Economics!$D$15*E$26/$A27,"organic") -> organic | F27: =IF($A27>0,Unit_Economics!$D$15*F$26/$A27,"organic") -> organic
A28: 30 | B28: =IF($A28>0,Unit_Economics!$D$15*B$26/$A28,"organic") -> 0.25184046 | C28: =IF($A28>0,Unit_Economics!$D$15*C$26/$A28,"organic") -> 0.50368092 | D28: =IF($A28>0,Unit_Economics!$D$15*D$26/$A28,"organic") -> 0.75552138 | E28: =IF($A28>0,Unit_Economics!$D$15*E$26/$A28,"organic") -> 1.0073618 | F28: =IF($A28>0,Unit_Economics!$D$15*F$26/$A28,"organic") -> 1.2592023
A29: 60 | B29: =IF($A29>0,Unit_Economics!$D$15*B$26/$A29,"organic") -> 0.12592023 | C29: =IF($A29>0,Unit_Economics!$D$15*C$26/$A29,"organic") -> 0.25184046 | D29: =IF($A29>0,Unit_Economics!$D$15*D$26/$A29,"organic") -> 0.37776069 | E29: =IF($A29>0,Unit_Economics!$D$15*E$26/$A29,"organic") -> 0.50368092 | F29: =IF($A29>0,Unit_Economics!$D$15*F$26/$A29,"organic") -> 0.62960115
A30: 120 | B30: =IF($A30>0,Unit_Economics!$D$15*B$26/$A30,"organic") -> 0.062960115 | C30: =IF($A30>0,Unit_Economics!$D$15*C$26/$A30,"organic") -> 0.12592023 | D30: =IF($A30>0,Unit_Economics!$D$15*D$26/$A30,"organic") -> 0.18888034 | E30: =IF($A30>0,Unit_Economics!$D$15*E$26/$A30,"organic") -> 0.25184046 | F30: =IF($A30>0,Unit_Economics!$D$15*F$26/$A30,"organic") -> 0.31480057
A31: 200 | B31: =IF($A31>0,Unit_Economics!$D$15*B$26/$A31,"organic") -> 0.037776069 | C31: =IF($A31>0,Unit_Economics!$D$15*C$26/$A31,"organic") -> 0.075552138 | D31: =IF($A31>0,Unit_Economics!$D$15*D$26/$A31,"organic") -> 0.11332821 | E31: =IF($A31>0,Unit_Economics!$D$15*E$26/$A31,"organic") -> 0.15110428 | F31: =IF($A31>0,Unit_Economics!$D$15*F$26/$A31,"organic") -> 0.18888034
A32: Red = below the common 3x LTV / CAC threshold.

Sheet Assumptions
A1: Habitlock financial model: assumptions
A2: Blue = input (edit these). Black = formula. Yellow fill = key assumption that must be validated with Infina. All VND. Nothing here is Infina data unless Source says 'Deck'.
A3: Source key: Deck = taken from the Habitlock proposal; Illustrative = my placeholder, not evidence; Confirm = needs Infina / real data before anyone relies on it.
A5: Parameter | B5: Unit | C5: Conservative | D5: Base | E5: Aggressive | F5: Source | G5: Note
A6: Units
A7: VND per VND million | B7: VND | C7: =D7 -> 1000000 | D7: 1000000 | E7: =D7 -> 1000000 | F7: Constant
A8: VND per VND thousand | B8: VND | C8: =D8 -> 1000 | D8: 1000 | E8: =D8 -> 1000 | F8: Constant
A9: Market funnel (Deck sizing)
A10: Population aged 18-25 | B10: people | C10: =D10 -> 17000000 | D10: 17000000 | E10: =D10 -> 17000000 | F10: Deck | G10: Top-down estimate, no source in deck
A11: Interested in personal finance | B11: people | C11: =D11 -> 7000000 | D11: 7000000 | E11: =D11 -> 7000000 | F11: Deck
A12: Ready to save with the right tool | B12: people | C12: =D12 -> 3000000 | D12: 3000000 | E12: =D12 -> 3000000 | F12: Deck
A13: Acquisition and activation
A14: Cumulative users acquired by M18, % of 'ready' pool | B14: % | C14: 0.05 | D14: 0.1 | E14: 0.2 | F14: Illustrative | G14: Deck claims 20-30% (600-900K users). Aggressive = deck low end. Base is half of it.
A15: Acquired users who make a first deposit | B15: % | C15: 0.5 | D15: 0.6 | E15: 0.7 | F15: Illustrative
A16: CAC per activated user | B16: VND | C16: 200000 | D16: 120000 | E16: 80000 | F16: Illustrative | G16: Confirm with Infina's blended CAC
A17: Retention and balances
A18: Monthly churn of activated users (full exit) | B18: %/month | C18: 0.12 | D18: 0.08 | E18: 0.05 | F18: Illustrative | G18: Constant hazard for simplicity
A19: Deposit per active user per month | B19: VND | C19: 300000 | D19: 500000 | E19: 800000 | F19: Illustrative | G19: Badge Lv1/Lv2 floor is 100K/month (Deck)
A20: Partial withdrawals, % of AUM per month (before Pause & Reflect) | B20: %/month | C20: 0.06 | D20: 0.05 | E20: 0.04 | F20: Illustrative
A21: Share of partial withdrawals that are impulsive | B21: % | C21: =D21 -> 0.6 | D21: 0.6 | E21: =D21 -> 0.6 | F21: Illustrative | G21: Deck: >70% SAY impulsive spending is the main barrier. Self-report is not withdrawal data.
A22: Pause & Reflect: share of impulsive withdrawals cancelled | B22: % | C22: 0.1 | D22: 0.2 | E22: 0.35 | F22: Illustrative | G22: Core product hypothesis. Test it, do not assume it.
A23: Revenue to Infina (annual, % of AUM)
A24: Net take rate on savings AUM | B24: %/yr | C24: 0.003 | D24: 0.005 | E24: 0.007 | F24: Confirm | G24: Spread or commission Infina keeps. Biggest unknown in the model.
A25: Net take rate on fund AUM | B25: %/yr | C25: 0.005 | D25: 0.008 | E25: 0.01 | F25: Confirm | G25: Distribution fee share
A26: Incrementality: share of Habitlock AUM revenue that is truly new | B26: % | C26: 0.5 | D26: 0.7 | E26: 0.9 | F26: Illustrative | G26: Some users would have saved in Infina anyway. Bonus cost is NOT scaled by this.
A27: Fund share of AUM once AI / auto-invest is mature | B27: % | C27: 0.05 | D27: 0.1 | E27: 0.2 | F27: Illustrative | G27: Deck: auto-invest moves only 10-20% of savings, so this is capped by design
A28: Months to reach mature fund share after AI launch | B28: months | C28: =D28 -> 6 | D28: 6 | E28: =D28 -> 6 | F28: Illustrative
A29: Product timeline (months since launch; Deck roadmap assumes Jul start)
A30: Calendar month of launch (1=Jan) | B30: month | C30: =D30 -> 7 | D30: 7 | E30: =D30 -> 7 | F30: Deck | G30: Jul 2025 start
A31: Pause & Reflect live from month | B31: month | C31: =D31 -> 3 | D31: 3 | E31: =D31 -> 3 | F31: Deck | G31: Sep on the roadmap
A32: Streaks and badges live from month | B32: month | C32: =D32 -> 4 | D32: 4 | E32: =D32 -> 4 | F32: Deck | G32: Oct on the roadmap
A33: AI suggestions and auto-invest live from month | B33: month | C33: =D33 -> 5 | D33: 5 | E33: =D33 -> 5 | F33: Deck | G33: Nov on the roadmap
A34: Last month of deck Phase 3 (Nov-Dec) | B34: month | C34: =D34 -> 6 | D34: 6 | E34: =D34 -> 6 | F34: Deck
A35: Badges
A36: Active users who meet badge conditions | B36: % | C36: 0.5 | D36: 0.65 | E36: 0.8 | F36: Illustrative | G36: Streaks are hard. Not everyone qualifies.
A37: Eligible users (Lv5+) who adopt auto-invest | B37: % | C37: 0.1 | D37: 0.2 | E37: 0.3 | F37: Illustrative
A38: Costs
A39: One-off build, QA and compliance cost | B39: VND | C39: =D39 -> 1500000000 | D39: 1500000000 | E39: =D39 -> 1500000000 | F39: Illustrative | G39: Confirm: engineering + legal + design
A40: Months over which build cost is spent | B40: months | C40: =D40 -> 3 | D40: 3 | E40: =D40 -> 3 | F40: Illustrative
A41: Monthly run cost (PM, CS, ops, data) | B41: VND | C41: =D41 -> 120000000 | D41: 120000000 | E41: =D41 -> 120000000 | F41: Illustrative
A42: Deck KPI targets (used for cross-checks only)
A43: Adherence Rate, Jul 2025 target | B43: % | C43: =D43 -> 0.05 | D43: 0.05 | E43: =D43 -> 0.05 | F43: Deck
A44: Adherence Rate, Dec 2025 target | B44: % | C44: =D44 -> 0.5 | D44: 0.5 | E44: =D44 -> 0.5 | F44: Deck
A46: Badge bonus interest by level (Deck, annual, added on top of base rate)
A47: Level | B47: Name | C47: Bonus (annual)
A48: Lv1 | B48: Saving Rookie | C48: 0.0005 | F48: Deck
A49: Lv2 | B49: Steady Cash Flow | C49: 0.001 | F49: Deck
A50: Lv3 | B50: Motivation Builder | C50: 0.0015 | F50: Deck
A51: Lv4 | B51: Accumulation Master | C51: 0.0025 | F51: Deck
A52: Lv5 | B52: Habit Investor | C52: 0.003 | F52: Deck
A53: Lv6 | B53: Growth Seeker | C53: 0.004 | F53: Deck
A55: Withdrawal seasonality multiplier by calendar month (Tet and year-end)
C56: Jan | D56: Feb | E56: Mar | F56: Apr | G56: May | H56: Jun | I56: Jul | J56: Aug | K56: Sep | L56: Oct | M56: Nov | N56: Dec
A57: Multiplier | B57: x | C57: 1.4 | D57: 1.2 | E57: 1 | F57: 1 | G57: 1 | H57: 1 | I57: 1 | J57: 1 | K57: 1 | L57: 1 | M57: 1 | N57: 1.3 | O57: Illustrative. Deck itself expects year-end withdrawals.
A59: Signup ramp: relative weight by month since launch (normalised in model)
C60: M1 | D60: M2 | E60: M3 | F60: M4 | G60: M5 | H60: M6 | I60: M7 | J60: M8 | K60: M9 | L60: M10 | M60: M11 | N60: M12 | O60: M13 | P60: M14 | Q60: M15 | R60: M16 | S60: M17 | T60: M18
A61: Weight | B61: index | C61: 2 | D61: 3 | E61: 4 | F61: 5 | G61: 6 | H61: 7 | I61: 7 | J61: 7 | K61: 7 | L61: 7 | M61: 6 | N61: 6 | O61: 6 | P61: 5 | Q61: 5 | R61: 5 | S61: 4 | T61: 4

Sheet Model_Cons
A1: Habitlock model, Conservative scenario
A2: All money in VND million unless stated. Months are counted from launch. Flows are monthly; stocks are end of month.
A3: Line item | B3: Unit | C3: 18M total | D3: M1 | E3: M2 | F3: M3 | G3: M4 | H3: M5 | I3: M6 | J3: M7 | K3: M8 | L3: M9 | M3: M10 | N3: M11 | O3: M12 | P3: M13 | Q3: M14 | R3: M15 | S3: M16 | T3: M17 | U3: M18
A4: Month since launch | B4: # | D4: 1 | E4: 2 | F4: 3 | G4: 4 | H4: 5 | I4: 6 | J4: 7 | K4: 8 | L4: 9 | M4: 10 | N4: 11 | O4: 12 | P4: 13 | Q4: 14 | R4: 15 | S4: 16 | T4: 17 | U4: 18
A5: Calendar month | B5: 1-12 | D5: =MOD(Assumptions!$C$30-1+D4-1,12)+1 -> 7 | E5: =MOD(Assumptions!$C$30-1+E4-1,12)+1 -> 8 | F5: =MOD(Assumptions!$C$30-1+F4-1,12)+1 -> 9 | G5: =MOD(Assumptions!$C$30-1+G4-1,12)+1 -> 10 | H5: =MOD(Assumptions!$C$30-1+H4-1,12)+1 -> 11 | I5: =MOD(Assumptions!$C$30-1+I4-1,12)+1 -> 12 | J5: =MOD(Assumptions!$C$30-1+J4-1,12)+1 -> 1 | K5: =MOD(Assumptions!$C$30-1+K4-1,12)+1 -> 2 | ... U5: =MOD(Assumptions!$C$30-1+U4-1,12)+1 -> 12
A6: Withdrawal seasonality | B6: x | D6: =INDEX(Assumptions!$C$57:$N$57,D5) -> 1 | E6: =INDEX(Assumptions!$C$57:$N$57,E5) -> 1 | F6: =INDEX(Assumptions!$C$57:$N$57,F5) -> 1 | G6: =INDEX(Assumptions!$C$57:$N$57,G5) -> 1 | H6: =INDEX(Assumptions!$C$57:$N$57,H5) -> 1 | I6: =INDEX(Assumptions!$C$57:$N$57,I5) -> 1.3 | J6: =INDEX(Assumptions!$C$57:$N$57,J5) -> 1.4 | K6: =INDEX(Assumptions!$C$57:$N$57,K5) -> 1.2 | ... U6: =INDEX(Assumptions!$C$57:$N$57,U5) -> 1.3
A7: Signup weight (normalised) | B7: % | D7: =INDEX(Assumptions!$C$61:$T$61,D4)/SUM(Assumptions!$C$61:$T$61) -> 0.020833333 | E7: =INDEX(Assumptions!$C$61:$T$61,E4)/SUM(Assumptions!$C$61:$T$61) -> 0.03125 | F7: =INDEX(Assumptions!$C$61:$T$61,F4)/SUM(Assumptions!$C$61:$T$61) -> 0.041666667 | G7: =INDEX(Assumptions!$C$61:$T$61,G4)/SUM(Assumptions!$C$61:$T$61) -> 0.052083333 | H7: =INDEX(Assumptions!$C$61:$T$61,H4)/SUM(Assumptions!$C$61:$T$61) -> 0.0625 | I7: =INDEX(Assumptions!$C$61:$T$61,I4)/SUM(Assumptions!$C$61:$T$61) -> 0.072916667 | J7: =INDEX(Assumptions!$C$61:$T$61,J4)/SUM(Assumptions!$C$61:$T$61) -> 0.072916667 | K7: =INDEX(Assumptions!$C$61:$T$61,K4)/SUM(Assumptions!$C$61:$T$61) -> 0.072916667 | ... U7: =INDEX(Assumptions!$C$61:$T$61,U4)/SUM(Assumptions!$C$61:$T$61) -> 0.041666667
A8: Funnel
A9: New users acquired | B9: users | C9: =SUM(D9:U9) -> 150000 | D9: =Assumptions!$C$14*Assumptions!$C$12*D7 -> 3125 | E9: =Assumptions!$C$14*Assumptions!$C$12*E7 -> 4687.5 | F9: =Assumptions!$C$14*Assumptions!$C$12*F7 -> 6250 | G9: =Assumptions!$C$14*Assumptions!$C$12*G7 -> 7812.5 | H9: =Assumptions!$C$14*Assumptions!$C$12*H7 -> 9375 | I9: =Assumptions!$C$14*Assumptions!$C$12*I7 -> 10937.5 | J9: =Assumptions!$C$14*Assumptions!$C$12*J7 -> 10937.5 | K9: =Assumptions!$C$14*Assumptions!$C$12*K7 -> 10937.5 | ... U9: =Assumptions!$C$14*Assumptions!$C$12*U7 -> 6250
A10: New activated users (first deposit) | B10: users | C10: =SUM(D10:U10) -> 75000 | D10: =D9*Assumptions!$C$15 -> 1562.5 | E10: =E9*Assumptions!$C$15 -> 2343.75 | F10: =F9*Assumptions!$C$15 -> 3125 | G10: =G9*Assumptions!$C$15 -> 3906.25 | H10: =H9*Assumptions!$C$15 -> 4687.5 | I10: =I9*Assumptions!$C$15 -> 5468.75 | J10: =J9*Assumptions!$C$15 -> 5468.75 | K10: =K9*Assumptions!$C$15 -> 5468.75 | ... U10: =U9*Assumptions!$C$15 -> 3125
A11: Active users, end of month | B11: users | D11: =SUM(D49:D66) -> 1562.5 | E11: =SUM(E49:E66) -> 3718.75 | F11: =SUM(F49:F66) -> 6397.5 | G11: =SUM(G49:G66) -> 9536.05 | H11: =SUM(H49:H66) -> 13079.224 | I11: =SUM(I49:I66) -> 16978.467 | J11: =SUM(J49:J66) -> 20409.801 | K11: =SUM(K49:K66) -> 23429.375 | ... U11: =SUM(U49:U66) -> 30693.461
A12: Users who exit in month | B12: users | C12: =SUM(D12:U12) -> 44306.539 | D12: =0 -> 0 | E12: =D11*Assumptions!$C$18 -> 187.5 | F12: =E11*Assumptions!$C$18 -> 446.25 | G12: =F11*Assumptions!$C$18 -> 767.7 | H12: =G11*Assumptions!$C$18 -> 1144.326 | I12: =H11*Assumptions!$C$18 -> 1569.5069 | J12: =I11*Assumptions!$C$18 -> 2037.4161 | K12: =J11*Assumptions!$C$18 -> 2449.1761 | L12: =K11*Assumptions!$C$18 -> 2811.525 | ... U12: =T11*Assumptions!$C$18 -> 3759.3355
A13: Cumulative users acquired | B13: users | D13: =D9 -> 3125 | E13: =D13+E9 -> 7812.5 | F13: =E13+F9 -> 14062.5 | G13: =F13+G9 -> 21875 | H13: =G13+H9 -> 31250 | I13: =H13+I9 -> 42187.5 | J13: =I13+J9 -> 53125 | K13: =J13+K9 -> 64062.5 | L13: =K13+L9 -> 75000 | ... U13: =T13+U9 -> 150000
A14: AUM
A15: Average balance per active user, start of month | B15: VND mn/user | D15: =IF(0>0,0/0,0) -> 0 | E15: =IF(D11>0,D21/D11,0) -> 0.3 | F15: =IF(E11>0,E21/E11,0) -> 0.40426891 | G15: =IF(F11>0,F21/F11,0) -> 0.49513161 | H15: =IF(G11>0,G21/G11,0) -> 0.57582462 | I15: =IF(H11>0,H21/H11,0) -> 0.64861605 | J15: =IF(I11>0,I21/I11,0) -> 0.70745875 | K15: =IF(J11>0,J21/J11,0) -> 0.77700397 | L15: =IF(K11>0,K21/K11,0) -> 0.85532725 | ... U15: =IF(T11>0,T21/T11,0) -> 1.5461409
A16: Gross deposits | B16: VND mn | C16: =SUM(D16:U16) -> 119974.39 | D16: =D11*Assumptions!$C$19/Assumptions!$C$7 -> 468.75 | E16: =E11*Assumptions!$C$19/Assumptions!$C$7 -> 1115.625 | F16: =F11*Assumptions!$C$19/Assumptions!$C$7 -> 1919.25 | G16: =G11*Assumptions!$C$19/Assumptions!$C$7 -> 2860.815 | H16: =H11*Assumptions!$C$19/Assumptions!$C$7 -> 3923.7672 | I16: =I11*Assumptions!$C$19/Assumptions!$C$7 -> 5093.5401 | J16: =J11*Assumptions!$C$19/Assumptions!$C$7 -> 6122.9403 | K16: =K11*Assumptions!$C$19/Assumptions!$C$7 -> 7028.8125 | ... U16: =U11*Assumptions!$C$19/Assumptions!$C$7 -> 9208.0382
A17: Exit withdrawals (churned users take full balance) | B17: VND mn | C17: =SUM(D17:U17) -> 49534.506 | D17: =D12*D15 -> 0 | E17: =E12*E15 -> 56.25 | F17: =F12*F15 -> 180.405 | G17: =G12*G15 -> 380.11254 | H17: =H12*H15 -> 658.93109 | I17: =I12*I15 -> 1018.0074 | J17: =J12*J15 -> 1441.3878 | K17: =K12*K15 -> 1903.0196 | ... U17: =U12*U15 -> 5812.4626
A18: Pause & Reflect live (1/0) | B18: flag | D18: =IF(D4>=Assumptions!$C$31,1,0) -> 0 | E18: =IF(E4>=Assumptions!$C$31,1,0) -> 0 | F18: =IF(F4>=Assumptions!$C$31,1,0) -> 1 | G18: =IF(G4>=Assumptions!$C$31,1,0) -> 1 | H18: =IF(H4>=Assumptions!$C$31,1,0) -> 1 | I18: =IF(I4>=Assumptions!$C$31,1,0) -> 1 | J18: =IF(J4>=Assumptions!$C$31,1,0) -> 1 | K18: =IF(K4>=Assumptions!$C$31,1,0) -> 1 | ... U18: =IF(U4>=Assumptions!$C$31,1,0) -> 1
A19: Partial withdrawal rate after Pause & Reflect | B19: %/month | D19: =Assumptions!$C$20*D6*(1-Assumptions!$C$21*Assumptions!$C$22*D18) -> 0.06 | E19: =Assumptions!$C$20*E6*(1-Assumptions!$C$21*Assumptions!$C$22*E18) -> 0.06 | F19: =Assumptions!$C$20*F6*(1-Assumptions!$C$21*Assumptions!$C$22*F18) -> 0.0564 | G19: =Assumptions!$C$20*G6*(1-Assumptions!$C$21*Assumptions!$C$22*G18) -> 0.0564 | H19: =Assumptions!$C$20*H6*(1-Assumptions!$C$21*Assumptions!$C$22*H18) -> 0.0564 | I19: =Assumptions!$C$20*I6*(1-Assumptions!$C$21*Assumptions!$C$22*I18) -> 0.07332 | J19: =Assumptions!$C$20*J6*(1-Assumptions!$C$21*Assumptions!$C$22*J18) -> 0.07896 | K19: =Assumptions!$C$20*K6*(1-Assumptions!$C$21*Assumptions!$C$22*K18) -> 0.06768 | ... U19: =Assumptions!$C$20*U6*(1-Assumptions!$C$21*Assumptions!$C$22*U18) -> 0.07332
A20: Partial withdrawals | B20: VND mn | C20: =SUM(D20:U20) -> 21732.362 | D20: =(0-D17)*D19 -> 0 | E20: =(D21-E17)*E19 -> 24.75 | F20: =(E21-F17)*F19 -> 74.615508 | G20: =(F21-G17)*G19 -> 157.21455 | H20: =(G21-H17)*H19 -> 272.5339 | I20: =(H21-I17)*I19 -> 547.36219 | J20: =(I21-J17)*J19 -> 834.62121 | K20: =(J21-K17)*K19 -> 944.50668 | L20: =(K21-L17)*L19 -> 994.6145 | ... U20: =(T21-U17)*U19 -> 3125.2449
A21: AUM, end of month | B21: VND mn | D21: =0+D16-D17-D20 -> 468.75 | E21: =D21+E16-E17-E20 -> 1503.375 | F21: =E21+F16-F17-F20 -> 3167.6045 | G21: =F21+G16-G17-G20 -> 5491.0924 | H21: =G21+H16-H17-H20 -> 8483.3946 | I21: =H21+I16-I17-I20 -> 12011.565 | J21: =I21+J16-J17-J20 -> 15858.496 | K21: =J21+K16-K17-K20 -> 20039.783 | L21: =K21+L16-L17-L20 -> 24466.374 | ... U21: =T21+U16-U17-U20 -> 48707.519
A22: Fund share of AUM | B22: % | D22: =IF(D4<Assumptions!$C$33,0,MIN(1,(D4-Assumptions!$C$33+1)/Assumptions!$C$28))*Assumptions!$C$27 -> 0 | E22: =IF(E4<Assumptions!$C$33,0,MIN(1,(E4-Assumptions!$C$33+1)/Assumptions!$C$28))*Assumptions!$C$27 -> 0 | F22: =IF(F4<Assumptions!$C$33,0,MIN(1,(F4-Assumptions!$C$33+1)/Assumptions!$C$28))*Assumptions!$C$27 -> 0 | G22: =IF(G4<Assumptions!$C$33,0,MIN(1,(G4-Assumptions!$C$33+1)/Assumptions!$C$28))*Assumptions!$C$27 -> 0 | H22: =IF(H4<Assumptions!$C$33,0,MIN(1,(H4-Assumptions!$C$33+1)/Assumptions!$C$28))*Assumptions!$C$27 -> 0.0083333333 | I22: =IF(I4<Assumptions!$C$33,0,MIN(1,(I4-Assumptions!$C$33+1)/Assumptions!$C$28))*Assumptions!$C$27 -> 0.016666667 | J22: =IF(J4<Assumptions!$C$33,0,MIN(1,(J4-Assumptions!$C$33+1)/Assumptions!$C$28))*Assumptions!$C$27 -> 0.025 | K22: =IF(K4<Assumptions!$C$33,0,MIN(1,(K4-Assumptions!$C$33+1)/Assumptions!$C$28))*Assumptions!$C$27 -> 0.033333333 | ... U22: =IF(U4<Assumptions!$C$33,0,MIN(1,(U4-Assumptions!$C$33+1)/Assumptions!$C$28))*Assumptions!$C$27 -> 0.05
A23: AUM in funds | B23: VND mn | D23: =D21*D22 -> 0 | E23: =E21*E22 -> 0 | F23: =F21*F22 -> 0 | G23: =G21*G22 -> 0 | H23: =H21*H22 -> 70.694955 | I23: =I21*I22 -> 200.19275 | J23: =J21*J22 -> 396.46241 | K23: =K21*K22 -> 667.99276 | ... U23: =U21*U22 -> 2435.3759
A24: AUM in savings | B24: VND mn | D24: =D21-D23 -> 468.75 | E24: =E21-E23 -> 1503.375 | F24: =F21-F23 -> 3167.6045 | G24: =G21-G23 -> 5491.0924 | H24: =H21-H23 -> 8412.6997 | I24: =I21-I23 -> 11811.372 | J24: =J21-J23 -> 15462.034 | K24: =K21-K23 -> 19371.79 | ... U24: =U21-U23 -> 46272.143
A25: Average AUM in month | B25: VND mn | D25: =(0+D21)/2 -> 234.375 | E25: =(D21+E21)/2 -> 986.0625 | F25: =(E21+F21)/2 -> 2335.4897 | G25: =(F21+G21)/2 -> 4329.3484 | H25: =(G21+H21)/2 -> 6987.2435 | I25: =(H21+I21)/2 -> 10247.48 | J25: =(I21+J21)/2 -> 13935.031 | K25: =(J21+K21)/2 -> 17949.14 | L25: =(K21+L21)/2 -> 22253.079 | ... U25: =(T21+U21)/2 -> 48572.354
A26: Counterfactual: same cohort without Pause & Reflect
A27: Avg balance per active user, no P&R | B27: VND mn/user | D27: =IF(0>0,0/0,0) -> 0 | E27: =IF(D11>0,D30/D11,0) -> 0.3 | F27: =IF(E11>0,E30/E11,0) -> 0.40426891 | G27: =IF(F11>0,F30/F11,0) -> 0.49438715 | H27: =IF(G11>0,G30/G11,0) -> 0.57435917 | I27: =IF(H11>0,H30/H11,0) -> 0.64640219 | J27: =IF(I11>0,I30/I11,0) -> 0.70401725 | K27: =IF(J11>0,J30/J11,0) -> 0.77208603 | L27: =IF(K11>0,K30/K11,0) -> 0.8492555 | ... U27: =IF(T11>0,T30/T11,0) -> 1.526508
A28: Exit withdrawals, no P&R | B28: VND mn | C28: =SUM(D28:U28) -> 49066.047 | D28: =D12*D27 -> 0 | E28: =E12*E27 -> 56.25 | F28: =F12*F27 -> 180.405 | G28: =G12*G27 -> 379.54102 | H28: =H12*H27 -> 657.25413 | I28: =I12*I27 -> 1014.5327 | J28: =J12*J27 -> 1434.3761 | K28: =K12*K27 -> 1890.9747 | ... U28: =U12*U27 -> 5738.6558
A29: Partial withdrawals, no P&R | B29: VND mn | C29: =SUM(D29:U29) -> 22899.337 | D29: =(0-D28)*Assumptions!$C$20*D6 -> 0 | E29: =(D30-E28)*Assumptions!$C$20*E6 -> 24.75 | F29: =(E30-F28)*Assumptions!$C$20*F6 -> 79.3782 | G29: =(F30-G28)*Assumptions!$C$20*G6 -> 166.99805 | H29: =(G30-H28)*Assumptions!$C$20*H6 -> 289.19182 | I29: =(H30-I28)*Assumptions!$C$20*I6 -> 580.31269 | J29: =(I30-J28)*Assumptions!$C$20*J6 -> 883.57565 | K29: =(J30-K28)*Assumptions!$C$20*K6 -> 998.43463 | L29: =(K30-L28)*Assumptions!$C$20*L6 -> 1050.5893 | ... U29: =(T30-U28)*Assumptions!$C$20*U6 -> 3282.5111
A30: AUM, no P&R | B30: VND mn | D30: =0+D16-D28-D29 -> 468.75 | E30: =D30+E16-E28-E29 -> 1503.375 | F30: =E30+F16-F28-F29 -> 3162.8418 | G30: =F30+G16-G28-G29 -> 5477.1177 | H30: =G30+H16-H28-H29 -> 8454.439 | I30: =H30+I16-I28-I29 -> 11953.134 | J30: =I30+J16-J28-J29 -> 15758.122 | K30: =J30+K16-K28-K29 -> 19897.526 | L30: =K30+L16-L28-L29 -> 24285.213 | ... U30: =T30+U16-U28-U29 -> 48009.003
A31: AUM retained thanks to Pause & Reflect | B31: VND mn | D31: =D21-D30 -> 0 | E31: =E21-E30 -> 0 | F31: =F21-F30 -> 4.762692 | G31: =G21-G30 -> 13.97467 | H31: =H21-H30 -> 28.955628 | I31: =I21-I30 -> 58.43145 | J31: =J21-J30 -> 100.37412 | K31: =K21-K30 -> 142.25718 | ... U31: =U21-U30 -> 698.51615
A32: P&L to Infina (incremental)
A33: Revenue on savings AUM | B33: VND mn | C33: =SUM(D33:U33) -> 104.28605 | D33: =D25*(1-D22)*Assumptions!$C$24/12 -> 0.05859375 | E33: =E25*(1-E22)*Assumptions!$C$24/12 -> 0.24651562 | F33: =F25*(1-F22)*Assumptions!$C$24/12 -> 0.58387244 | G33: =G25*(1-G22)*Assumptions!$C$24/12 -> 1.0823371 | H33: =H25*(1-H22)*Assumptions!$C$24/12 -> 1.7322541 | I33: =I25*(1-I22)*Assumptions!$C$24/12 -> 2.5191721 | J33: =J25*(1-J22)*Assumptions!$C$24/12 -> 3.3966638 | K33: =K25*(1-K22)*Assumptions!$C$24/12 -> 4.3377087 | ... U33: =U25*(1-U22)*Assumptions!$C$24/12 -> 11.535934
A34: Revenue on fund AUM | B34: VND mn | C34: =SUM(D34:U34) -> 8.3321305 | D34: =D25*D22*Assumptions!$C$25/12 -> 0 | E34: =E25*E22*Assumptions!$C$25/12 -> 0 | F34: =F25*F22*Assumptions!$C$25/12 -> 0 | G34: =G25*G22*Assumptions!$C$25/12 -> 0 | H34: =H25*H22*Assumptions!$C$25/12 -> 0.024261262 | I34: =I25*I22*Assumptions!$C$25/12 -> 0.071163055 | J34: =J25*J22*Assumptions!$C$25/12 -> 0.14515657 | K34: =K25*K22*Assumptions!$C$25/12 -> 0.24929361 | ... U34: =U25*U22*Assumptions!$C$25/12 -> 1.011924
A35: Gross revenue on Habitlock AUM | B35: VND mn | C35: =SUM(D35:U35) -> 112.61818 | D35: =D33+D34 -> 0.05859375 | E35: =E33+E34 -> 0.24651562 | F35: =F33+F34 -> 0.58387244 | G35: =G33+G34 -> 1.0823371 | H35: =H33+H34 -> 1.7565154 | I35: =I33+I34 -> 2.5903352 | J35: =J33+J34 -> 3.5418203 | K35: =K33+K34 -> 4.5870023 | ... U35: =U33+U34 -> 12.547858
A36: Incremental revenue (after incrementality) | B36: VND mn | C36: =SUM(D36:U36) -> 56.309089 | D36: =D35*Assumptions!$C$26 -> 0.029296875 | E36: =E35*Assumptions!$C$26 -> 0.12325781 | F36: =F35*Assumptions!$C$26 -> 0.29193622 | G36: =G35*Assumptions!$C$26 -> 0.54116856 | H36: =H35*Assumptions!$C$26 -> 0.87825769 | I36: =I35*Assumptions!$C$26 -> 1.2951676 | J36: =J35*Assumptions!$C$26 -> 1.7709102 | K36: =K35*Assumptions!$C$26 -> 2.2935012 | ... U36: =U35*Assumptions!$C$26 -> 6.273929
A37: Weighted average bonus rate (annual, savings AUM) | B37: %/yr | D37: =IF(D11>0,SUM(D71:D88)/D11,0) -> 0 | E37: =IF(E11>0,SUM(E71:E88)/E11,0) -> 0 | F37: =IF(F11>0,SUM(F71:F88)/F11,0) -> 0 | G37: =IF(G11>0,SUM(G71:G88)/G11,0) -> 0.00025 | H37: =IF(H11>0,SUM(H71:H88)/H11,0) -> 0.00041040179 | I37: =IF(I11>0,SUM(I71:I88)/I11,0) -> 0.00052821172 | J37: =IF(J11>0,SUM(J71:J88)/J11,0) -> 0.00071627971 | K37: =IF(K11>0,SUM(K71:K88)/K11,0) -> 0.00077825643 | ... U37: =IF(U11>0,SUM(U71:U88)/U11,0) -> 0.0010670685
A38: Bonus interest cost (paid on ALL Habitlock savings AUM) | B38: VND mn | C38: =SUM(D38:U38) -> 32.438328 | D38: =D25*(1-D22)*D37/12 -> 0 | E38: =E25*(1-E22)*E37/12 -> 0 | F38: =F25*(1-F22)*F37/12 -> 0 | G38: =G25*(1-G22)*G37/12 -> 0.090194759 | H38: =H25*(1-H22)*H37/12 -> 0.2369734 | I38: =I25*(1-I22)*I37/12 -> 0.44355208 | J38: =J25*(1-J22)*J37/12 -> 0.81098711 | K38: =K25*(1-K22)*K37/12 -> 1.1252832 | ... U38: =U25*(1-U22)*U37/12 -> 4.1032106
A39: Acquisition spend | B39: VND mn | C39: =SUM(D39:U39) -> 15000 | D39: =D10*Assumptions!$C$16/Assumptions!$C$7 -> 312.5 | E39: =E10*Assumptions!$C$16/Assumptions!$C$7 -> 468.75 | F39: =F10*Assumptions!$C$16/Assumptions!$C$7 -> 625 | G39: =G10*Assumptions!$C$16/Assumptions!$C$7 -> 781.25 | H39: =H10*Assumptions!$C$16/Assumptions!$C$7 -> 937.5 | I39: =I10*Assumptions!$C$16/Assumptions!$C$7 -> 1093.75 | J39: =J10*Assumptions!$C$16/Assumptions!$C$7 -> 1093.75 | K39: =K10*Assumptions!$C$16/Assumptions!$C$7 -> 1093.75 | ... U39: =U10*Assumptions!$C$16/Assumptions!$C$7 -> 625
A40: Build cost | B40: VND mn | C40: =SUM(D40:U40) -> 1500 | D40: =IF(D4<=Assumptions!$C$40,Assumptions!$C$39/Assumptions!$C$40/Assumptions!$C$7,0) -> 500 | E40: =IF(E4<=Assumptions!$C$40,Assumptions!$C$39/Assumptions!$C$40/Assumptions!$C$7,0) -> 500 | F40: =IF(F4<=Assumptions!$C$40,Assumptions!$C$39/Assumptions!$C$40/Assumptions!$C$7,0) -> 500 | G40: =IF(G4<=Assumptions!$C$40,Assumptions!$C$39/Assumptions!$C$40/Assumptions!$C$7,0) -> 0 | H40: =IF(H4<=Assumptions!$C$40,Assumptions!$C$39/Assumptions!$C$40/Assumptions!$C$7,0) -> 0 | I40: =IF(I4<=Assumptions!$C$40,Assumptions!$C$39/Assumptions!$C$40/Assumptions!$C$7,0) -> 0 | J40: =IF(J4<=Assumptions!$C$40,Assumptions!$C$39/Assumptions!$C$40/Assumptions!$C$7,0) -> 0 | K40: =IF(K4<=Assumptions!$C$40,Assumptions!$C$39/Assumptions!$C$40/Assumptions!$C$7,0) -> 0 | ... U40: =IF(U4<=Assumptions!$C$40,Assumptions!$C$39/Assumptions!$C$40/Assumptions!$C$7,0) -> 0
A41: Run cost | B41: VND mn | C41: =SUM(D41:U41) -> 2160 | D41: =Assumptions!$C$41/Assumptions!$C$7 -> 120 | E41: =Assumptions!$C$41/Assumptions!$C$7 -> 120 | F41: =Assumptions!$C$41/Assumptions!$C$7 -> 120 | G41: =Assumptions!$C$41/Assumptions!$C$7 -> 120 | H41: =Assumptions!$C$41/Assumptions!$C$7 -> 120 | I41: =Assumptions!$C$41/Assumptions!$C$7 -> 120 | J41: =Assumptions!$C$41/Assumptions!$C$7 -> 120 | K41: =Assumptions!$C$41/Assumptions!$C$7 -> 120 | ... U41: =Assumptions!$C$41/Assumptions!$C$7 -> 120
A42: Net contribution | B42: VND mn | C42: =SUM(D42:U42) -> -18636.129 | D42: =D36-D38-D39-D40-D41 -> -932.4707 | E42: =E36-E38-E39-E40-E41 -> -1088.6267 | F42: =F36-F38-F39-F40-F41 -> -1244.7081 | G42: =G36-G38-G39-G40-G41 -> -900.79903 | H42: =H36-H38-H39-H40-H41 -> -1056.8587 | I42: =I36-I38-I39-I40-I41 -> -1212.8984 | J42: =J36-J38-J39-J40-J41 -> -1212.7901 | K42: =K36-K38-K39-K40-K41 -> -1212.5818 | ... U42: =U36-U38-U39-U40-U41 -> -742.82928
A43: Cumulative net contribution | B43: VND mn | D43: =D42 -> -932.4707 | E43: =D43+E42 -> -2021.0974 | F43: =E43+F42 -> -3265.8055 | G43: =F43+G42 -> -4166.6045 | H43: =G43+H42 -> -5223.4633 | I43: =H43+I42 -> -6436.3616 | J43: =I43+J42 -> -7649.1517 | K43: =J43+K42 -> -8861.7335 | L43: =K43+L42 -> -10074.097 | ... U43: =T43+U42 -> -18636.129
A44: Flag: cumulative net >= 0 | B44: flag | D44: =IF(D43>=0,1,0) -> 0 | E44: =IF(E43>=0,1,0) -> 0 | F44: =IF(F43>=0,1,0) -> 0 | G44: =IF(G43>=0,1,0) -> 0 | H44: =IF(H43>=0,1,0) -> 0 | I44: =IF(I43>=0,1,0) -> 0 | J44: =IF(J43>=0,1,0) -> 0 | K44: =IF(K43>=0,1,0) -> 0 | ... U44: =IF(U43>=0,1,0) -> 0
A45: Flag: monthly net >= 0 | B45: flag | D45: =IF(D42>=0,1,0) -> 0 | E45: =IF(E42>=0,1,0) -> 0 | F45: =IF(F42>=0,1,0) -> 0 | G45: =IF(G42>=0,1,0) -> 0 | H45: =IF(H42>=0,1,0) -> 0 | I45: =IF(I42>=0,1,0) -> 0 | J45: =IF(J42>=0,1,0) -> 0 | K45: =IF(K42>=0,1,0) -> 0 | ... U45: =IF(U42>=0,1,0) -> 0
A47: Cohort matrix: active users by acquisition cohort (rows) and month (columns)
A48: Cohort | B48: Cohort # | D48: M1 | E48: M2 | F48: M3 | G48: M4 | H48: M5 | I48: M6 | J48: M7 | K48: M8 | L48: M9 | M48: M10 | N48: M11 | O48: M12 | P48: M13 | Q48: M14 | R48: M15 | S48: M16 | T48: M17 | U48: M18
A49: Cohort M1 | B49: 1 | D49: =IF(D$4<$B49,0,INDEX($D$10:$U$10,$B49)*(1-Assumptions!$C$18)^(D$4-$B49)) -> 1562.5 | E49: =IF(E$4<$B49,0,INDEX($D$10:$U$10,$B49)*(1-Assumptions!$C$18)^(E$4-$B49)) -> 1375 | F49: =IF(F$4<$B49,0,INDEX($D$10:$U$10,$B49)*(1-Assumptions!$C$18)^(F$4-$B49)) -> 1210 | G49: =IF(G$4<$B49,0,INDEX($D$10:$U$10,$B49)*(1-Assumptions!$C$18)^(G$4-$B49)) -> 1064.8 | H49: =IF(H$4<$B49,0,INDEX($D$10:$U$10,$B49)*(1-Assumptions!$C$18)^(H$4-$B49)) -> 937.024 | I49: =IF(I$4<$B49,0,INDEX($D$10:$U$10,$B49)*(1-Assumptions!$C$18)^(I$4-$B49)) -> 824.58112 | J49: =IF(J$4<$B49,0,INDEX($D$10:$U$10,$B49)*(1-Assumptions!$C$18)^(J$4-$B49)) -> 725.63139 | K49: =IF(K$4<$B49,0,INDEX($D$10:$U$10,$B49)*(1-Assumptions!$C$18)^(K$4-$B49)) -> 638.55562 | ... U49: =IF(U$4<$B49,0,INDEX($D$10:$U$10,$B49)*(1-Assumptions!$C$18)^(U$4-$B49)) -> 177.83836
A50: Cohort M2 | B50: 2 | D50: =IF(D$4<$B50,0,INDEX($D$10:$U$10,$B50)*(1-Assumptions!$C$18)^(D$4-$B50)) -> 0 | E50: =IF(E$4<$B50,0,INDEX($D$10:$U$10,$B50)*(1-Assumptions!$C$18)^(E$4-$B50)) -> 2343.75 | F50: =IF(F$4<$B50,0,INDEX($D$10:$U$10,$B50)*(1-Assumptions!$C$18)^(F$4-$B50)) -> 2062.5 | G50: =IF(G$4<$B50,0,INDEX($D$10:$U$10,$B50)*(1-Assumptions!$C$18)^(G$4-$B50)) -> 1815 | H50: =IF(H$4<$B50,0,INDEX($D$10:$U$10,$B50)*(1-Assumptions!$C$18)^(H$4-$B50)) -> 1597.2 | I50: =IF(I$4<$B50,0,INDEX($D$10:$U$10,$B50)*(1-Assumptions!$C$18)^(I$4-$B50)) -> 1405.536 | J50: =IF(J$4<$B50,0,INDEX($D$10:$U$10,$B50)*(1-Assumptions!$C$18)^(J$4-$B50)) -> 1236.8717 | K50: =IF(K$4<$B50,0,INDEX($D$10:$U$10,$B50)*(1-Assumptions!$C$18)^(K$4-$B50)) -> 1088.4471 | ... U50: =IF(U$4<$B50,0,INDEX($D$10:$U$10,$B50)*(1-Assumptions!$C$18)^(U$4-$B50)) -> 303.13357
A51: Cohort M3 | B51: 3 | D51: =IF(D$4<$B51,0,INDEX($D$10:$U$10,$B51)*(1-Assumptions!$C$18)^(D$4-$B51)) -> 0 | E51: =IF(E$4<$B51,0,INDEX($D$10:$U$10,$B51)*(1-Assumptions!$C$18)^(E$4-$B51)) -> 0 | F51: =IF(F$4<$B51,0,INDEX($D$10:$U$10,$B51)*(1-Assumptions!$C$18)^(F$4-$B51)) -> 3125 | G51: =IF(G$4<$B51,0,INDEX($D$10:$U$10,$B51)*(1-Assumptions!$C$18)^(G$4-$B51)) -> 2750 | H51: =IF(H$4<$B51,0,INDEX($D$10:$U$10,$B51)*(1-Assumptions!$C$18)^(H$4-$B51)) -> 2420 | I51: =IF(I$4<$B51,0,INDEX($D$10:$U$10,$B51)*(1-Assumptions!$C$18)^(I$4-$B51)) -> 2129.6 | J51: =IF(J$4<$B51,0,INDEX($D$10:$U$10,$B51)*(1-Assumptions!$C$18)^(J$4-$B51)) -> 1874.048 | K51: =IF(K$4<$B51,0,INDEX($D$10:$U$10,$B51)*(1-Assumptions!$C$18)^(K$4-$B51)) -> 1649.1622 | ... U51: =IF(U$4<$B51,0,INDEX($D$10:$U$10,$B51)*(1-Assumptions!$C$18)^(U$4-$B51)) -> 459.29329
A52: Cohort M4 | B52: 4 | D52: =IF(D$4<$B52,0,INDEX($D$10:$U$10,$B52)*(1-Assumptions!$C$18)^(D$4-$B52)) -> 0 | E52: =IF(E$4<$B52,0,INDEX($D$10:$U$10,$B52)*(1-Assumptions!$C$18)^(E$4-$B52)) -> 0 | F52: =IF(F$4<$B52,0,INDEX($D$10:$U$10,$B52)*(1-Assumptions!$C$18)^(F$4-$B52)) -> 0 | G52: =IF(G$4<$B52,0,INDEX($D$10:$U$10,$B52)*(1-Assumptions!$C$18)^(G$4-$B52)) -> 3906.25 | H52: =IF(H$4<$B52,0,INDEX($D$10:$U$10,$B52)*(1-Assumptions!$C$18)^(H$4-$B52)) -> 3437.5 | I52: =IF(I$4<$B52,0,INDEX($D$10:$U$10,$B52)*(1-Assumptions!$C$18)^(I$4-$B52)) -> 3025 | J52: =IF(J$4<$B52,0,INDEX($D$10:$U$10,$B52)*(1-Assumptions!$C$18)^(J$4-$B52)) -> 2662 | K52: =IF(K$4<$B52,0,INDEX($D$10:$U$10,$B52)*(1-Assumptions!$C$18)^(K$4-$B52)) -> 2342.56 | ... U52: =IF(U$4<$B52,0,INDEX($D$10:$U$10,$B52)*(1-Assumptions!$C$18)^(U$4-$B52)) -> 652.40525
A53: Cohort M5 | B53: 5 | D53: =IF(D$4<$B53,0,INDEX($D$10:$U$10,$B53)*(1-Assumptions!$C$18)^(D$4-$B53)) -> 0 | E53: =IF(E$4<$B53,0,INDEX($D$10:$U$10,$B53)*(1-Assumptions!$C$18)^(E$4-$B53)) -> 0 | F53: =IF(F$4<$B53,0,INDEX($D$10:$U$10,$B53)*(1-Assumptions!$C$18)^(F$4-$B53)) -> 0 | G53: =IF(G$4<$B53,0,INDEX($D$10:$U$10,$B53)*(1-Assumptions!$C$18)^(G$4-$B53)) -> 0 | H53: =IF(H$4<$B53,0,INDEX($D$10:$U$10,$B53)*(1-Assumptions!$C$18)^(H$4-$B53)) -> 4687.5 | I53: =IF(I$4<$B53,0,INDEX($D$10:$U$10,$B53)*(1-Assumptions!$C$18)^(I$4-$B53)) -> 4125 | J53: =IF(J$4<$B53,0,INDEX($D$10:$U$10,$B53)*(1-Assumptions!$C$18)^(J$4-$B53)) -> 3630 | K53: =IF(K$4<$B53,0,INDEX($D$10:$U$10,$B53)*(1-Assumptions!$C$18)^(K$4-$B53)) -> 3194.4 | ... U53: =IF(U$4<$B53,0,INDEX($D$10:$U$10,$B53)*(1-Assumptions!$C$18)^(U$4-$B53)) -> 889.64352
A54: Cohort M6 | B54: 6 | D54: =IF(D$4<$B54,0,INDEX($D$10:$U$10,$B54)*(1-Assumptions!$C$18)^(D$4-$B54)) -> 0 | E54: =IF(E$4<$B54,0,INDEX($D$10:$U$10,$B54)*(1-Assumptions!$C$18)^(E$4-$B54)) -> 0 | F54: =IF(F$4<$B54,0,INDEX($D$10:$U$10,$B54)*(1-Assumptions!$C$18)^(F$4-$B54)) -> 0 | G54: =IF(G$4<$B54,0,INDEX($D$10:$U$10,$B54)*(1-Assumptions!$C$18)^(G$4-$B54)) -> 0 | H54: =IF(H$4<$B54,0,INDEX($D$10:$U$10,$B54)*(1-Assumptions!$C$18)^(H$4-$B54)) -> 0 | I54: =IF(I$4<$B54,0,INDEX($D$10:$U$10,$B54)*(1-Assumptions!$C$18)^(I$4-$B54)) -> 5468.75 | J54: =IF(J$4<$B54,0,INDEX($D$10:$U$10,$B54)*(1-Assumptions!$C$18)^(J$4-$B54)) -> 4812.5 | K54: =IF(K$4<$B54,0,INDEX($D$10:$U$10,$B54)*(1-Assumptions!$C$18)^(K$4-$B54)) -> 4235 | ... U54: =IF(U$4<$B54,0,INDEX($D$10:$U$10,$B54)*(1-Assumptions!$C$18)^(U$4-$B54)) -> 1179.4516
A55: Cohort M7 | B55: 7 | D55: =IF(D$4<$B55,0,INDEX($D$10:$U$10,$B55)*(1-Assumptions!$C$18)^(D$4-$B55)) -> 0 | E55: =IF(E$4<$B55,0,INDEX($D$10:$U$10,$B55)*(1-Assumptions!$C$18)^(E$4-$B55)) -> 0 | F55: =IF(F$4<$B55,0,INDEX($D$10:$U$10,$B55)*(1-Assumptions!$C$18)^(F$4-$B55)) -> 0 | G55: =IF(G$4<$B55,0,INDEX($D$10:$U$10,$B55)*(1-Assumptions!$C$18)^(G$4-$B55)) -> 0 | H55: =IF(H$4<$B55,0,INDEX($D$10:$U$10,$B55)*(1-Assumptions!$C$18)^(H$4-$B55)) -> 0 | I55: =IF(I$4<$B55,0,INDEX($D$10:$U$10,$B55)*(1-Assumptions!$C$18)^(I$4-$B55)) -> 0 | J55: =IF(J$4<$B55,0,INDEX($D$10:$U$10,$B55)*(1-Assumptions!$C$18)^(J$4-$B55)) -> 5468.75 | K55: =IF(K$4<$B55,0,INDEX($D$10:$U$10,$B55)*(1-Assumptions!$C$18)^(K$4-$B55)) -> 4812.5 | ... U55: =IF(U$4<$B55,0,INDEX($D$10:$U$10,$B55)*(1-Assumptions!$C$18)^(U$4-$B55)) -> 1340.2859
A56: Cohort M8 | B56: 8 | D56: =IF(D$4<$B56,0,INDEX($D$10:$U$10,$B56)*(1-Assumptions!$C$18)^(D$4-$B56)) -> 0 | E56: =IF(E$4<$B56,0,INDEX($D$10:$U$10,$B56)*(1-Assumptions!$C$18)^(E$4-$B56)) -> 0 | F56: =IF(F$4<$B56,0,INDEX($D$10:$U$10,$B56)*(1-Assumptions!$C$18)^(F$4-$B56)) -> 0 | G56: =IF(G$4<$B56,0,INDEX($D$10:$U$10,$B56)*(1-Assumptions!$C$18)^(G$4-$B56)) -> 0 | H56: =IF(H$4<$B56,0,INDEX($D$10:$U$10,$B56)*(1-Assumptions!$C$18)^(H$4-$B56)) -> 0 | I56: =IF(I$4<$B56,0,INDEX($D$10:$U$10,$B56)*(1-Assumptions!$C$18)^(I$4-$B56)) -> 0 | J56: =IF(J$4<$B56,0,INDEX($D$10:$U$10,$B56)*(1-Assumptions!$C$18)^(J$4-$B56)) -> 0 | K56: =IF(K$4<$B56,0,INDEX($D$10:$U$10,$B56)*(1-Assumptions!$C$18)^(K$4-$B56)) -> 5468.75 | ... U56: =IF(U$4<$B56,0,INDEX($D$10:$U$10,$B56)*(1-Assumptions!$C$18)^(U$4-$B56)) -> 1523.0522
A57: Cohort M9 | B57: 9 | D57: =IF(D$4<$B57,0,INDEX($D$10:$U$10,$B57)*(1-Assumptions!$C$18)^(D$4-$B57)) -> 0 | E57: =IF(E$4<$B57,0,INDEX($D$10:$U$10,$B57)*(1-Assumptions!$C$18)^(E$4-$B57)) -> 0 | F57: =IF(F$4<$B57,0,INDEX($D$10:$U$10,$B57)*(1-Assumptions!$C$18)^(F$4-$B57)) -> 0 | G57: =IF(G$4<$B57,0,INDEX($D$10:$U$10,$B57)*(1-Assumptions!$C$18)^(G$4-$B57)) -> 0 | H57: =IF(H$4<$B57,0,INDEX($D$10:$U$10,$B57)*(1-Assumptions!$C$18)^(H$4-$B57)) -> 0 | I57: =IF(I$4<$B57,0,INDEX($D$10:$U$10,$B57)*(1-Assumptions!$C$18)^(I$4-$B57)) -> 0 | J57: =IF(J$4<$B57,0,INDEX($D$10:$U$10,$B57)*(1-Assumptions!$C$18)^(J$4-$B57)) -> 0 | K57: =IF(K$4<$B57,0,INDEX($D$10:$U$10,$B57)*(1-Assumptions!$C$18)^(K$4-$B57)) -> 0 | ... U57: =IF(U$4<$B57,0,INDEX($D$10:$U$10,$B57)*(1-Assumptions!$C$18)^(U$4-$B57)) -> 1730.7412
A58: Cohort M10 | B58: 10 | D58: =IF(D$4<$B58,0,INDEX($D$10:$U$10,$B58)*(1-Assumptions!$C$18)^(D$4-$B58)) -> 0 | E58: =IF(E$4<$B58,0,INDEX($D$10:$U$10,$B58)*(1-Assumptions!$C$18)^(E$4-$B58)) -> 0 | F58: =IF(F$4<$B58,0,INDEX($D$10:$U$10,$B58)*(1-Assumptions!$C$18)^(F$4-$B58)) -> 0 | G58: =IF(G$4<$B58,0,INDEX($D$10:$U$10,$B58)*(1-Assumptions!$C$18)^(G$4-$B58)) -> 0 | H58: =IF(H$4<$B58,0,INDEX($D$10:$U$10,$B58)*(1-Assumptions!$C$18)^(H$4-$B58)) -> 0 | I58: =IF(I$4<$B58,0,INDEX($D$10:$U$10,$B58)*(1-Assumptions!$C$18)^(I$4-$B58)) -> 0 | J58: =IF(J$4<$B58,0,INDEX($D$10:$U$10,$B58)*(1-Assumptions!$C$18)^(J$4-$B58)) -> 0 | K58: =IF(K$4<$B58,0,INDEX($D$10:$U$10,$B58)*(1-Assumptions!$C$18)^(K$4-$B58)) -> 0 | ... U58: =IF(U$4<$B58,0,INDEX($D$10:$U$10,$B58)*(1-Assumptions!$C$18)^(U$4-$B58)) -> 1966.7513
A59: Cohort M11 | B59: 11 | D59: =IF(D$4<$B59,0,INDEX($D$10:$U$10,$B59)*(1-Assumptions!$C$18)^(D$4-$B59)) -> 0 | E59: =IF(E$4<$B59,0,INDEX($D$10:$U$10,$B59)*(1-Assumptions!$C$18)^(E$4-$B59)) -> 0 | F59: =IF(F$4<$B59,0,INDEX($D$10:$U$10,$B59)*(1-Assumptions!$C$18)^(F$4-$B59)) -> 0 | G59: =IF(G$4<$B59,0,INDEX($D$10:$U$10,$B59)*(1-Assumptions!$C$18)^(G$4-$B59)) -> 0 | H59: =IF(H$4<$B59,0,INDEX($D$10:$U$10,$B59)*(1-Assumptions!$C$18)^(H$4-$B59)) -> 0 | I59: =IF(I$4<$B59,0,INDEX($D$10:$U$10,$B59)*(1-Assumptions!$C$18)^(I$4-$B59)) -> 0 | J59: =IF(J$4<$B59,0,INDEX($D$10:$U$10,$B59)*(1-Assumptions!$C$18)^(J$4-$B59)) -> 0 | K59: =IF(K$4<$B59,0,INDEX($D$10:$U$10,$B59)*(1-Assumptions!$C$18)^(K$4-$B59)) -> 0 | ... U59: =IF(U$4<$B59,0,INDEX($D$10:$U$10,$B59)*(1-Assumptions!$C$18)^(U$4-$B59)) -> 1915.6669
A60: Cohort M12 | B60: 12 | D60: =IF(D$4<$B60,0,INDEX($D$10:$U$10,$B60)*(1-Assumptions!$C$18)^(D$4-$B60)) -> 0 | E60: =IF(E$4<$B60,0,INDEX($D$10:$U$10,$B60)*(1-Assumptions!$C$18)^(E$4-$B60)) -> 0 | F60: =IF(F$4<$B60,0,INDEX($D$10:$U$10,$B60)*(1-Assumptions!$C$18)^(F$4-$B60)) -> 0 | G60: =IF(G$4<$B60,0,INDEX($D$10:$U$10,$B60)*(1-Assumptions!$C$18)^(G$4-$B60)) -> 0 | H60: =IF(H$4<$B60,0,INDEX($D$10:$U$10,$B60)*(1-Assumptions!$C$18)^(H$4-$B60)) -> 0 | I60: =IF(I$4<$B60,0,INDEX($D$10:$U$10,$B60)*(1-Assumptions!$C$18)^(I$4-$B60)) -> 0 | J60: =IF(J$4<$B60,0,INDEX($D$10:$U$10,$B60)*(1-Assumptions!$C$18)^(J$4-$B60)) -> 0 | K60: =IF(K$4<$B60,0,INDEX($D$10:$U$10,$B60)*(1-Assumptions!$C$18)^(K$4-$B60)) -> 0 | ... U60: =IF(U$4<$B60,0,INDEX($D$10:$U$10,$B60)*(1-Assumptions!$C$18)^(U$4-$B60)) -> 2176.8942
... A66: Cohort M18 | B66: 18 | D66: =IF(D$4<$B66,0,INDEX($D$10:$U$10,$B66)*(1-Assumptions!$C$18)^(D$4-$B66)) -> 0 | E66: =IF(E$4<$B66,0,INDEX($D$10:$U$10,$B66)*(1-Assumptions!$C$18)^(E$4-$B66)) -> 0 | F66: =IF(F$4<$B66,0,INDEX($D$10:$U$10,$B66)*(1-Assumptions!$C$18)^(F$4-$B66)) -> 0 | G66: =IF(G$4<$B66,0,INDEX($D$10:$U$10,$B66)*(1-Assumptions!$C$18)^(G$4-$B66)) -> 0 | H66: =IF(H$4<$B66,0,INDEX($D$10:$U$10,$B66)*(1-Assumptions!$C$18)^(H$4-$B66)) -> 0 | I66: =IF(I$4<$B66,0,INDEX($D$10:$U$10,$B66)*(1-Assumptions!$C$18)^(I$4-$B66)) -> 0 | J66: =IF(J$4<$B66,0,INDEX($D$10:$U$10,$B66)*(1-Assumptions!$C$18)^(J$4-$B66)) -> 0 | K66: =IF(K$4<$B66,0,INDEX($D$10:$U$10,$B66)*(1-Assumptions!$C$18)^(K$4-$B66)) -> 0 | ... U66: =IF(U$4<$B66,0,INDEX($D$10:$U$10,$B66)*(1-Assumptions!$C$18)^(U$4-$B66)) -> 3125
A69: Cohort matrix: active users x bonus rate (feeds weighted average bonus rate)
A70: Cohort | B70: Cohort # | D70: M1 | E70: M2 | F70: M3 | G70: M4 | H70: M5 | I70: M6 | J70: M7 | K70: M8 | L70: M9 | M70: M10 | N70: M11 | O70: M12 | P70: M13 | Q70: M14 | R70: M15 | S70: M16 | T70: M17 | U70: M18
A71: Cohort M1 | B71: 1 | D71: =IF(OR(D$4<Assumptions!$C$32,D$4<$B71),0,D49*IF(D$4>=Assumptions!$C$33,INDEX($D$94:$D$111,D$4-MAX($B71,Assumptions!$C$32)+1),INDEX($C$94:$C$111,D$4-MAX($B71,Assumptions!$C$32)+1))) -> 0 | E71: =IF(OR(E$4<Assumptions!$C$32,E$4<$B71),0,E49*IF(E$4>=Assumptions!$C$33,INDEX($D$94:$D$111,E$4-MAX($B71,Assumptions!$C$32)+1),INDEX($C$94:$C$111,E$4-MAX($B71,Assumptions!$C$32)+1))) -> 0 | F71: =IF(OR(F$4<Assumptions!$C$32,F$4<$B71),0,F49*IF(F$4>=Assumptions!$C$33,INDEX($D$94:$D$111,F$4-MAX($B71,Assumptions!$C$32)+1),INDEX($C$94:$C$111,F$4-MAX($B71,Assumptions!$C$32)+1))) -> 0 | G71: =IF(OR(G$4<Assumptions!$C$32,G$4<$B71),0,G49*IF(G$4>=Assumptions!$C$33,INDEX($D$94:$D$111,G$4-MAX($B71,Assumptions!$C$32)+1),INDEX($C$94:$C$111,G$4-MAX($B71,Assumptions!$C$32)+1))) -> 0.2662 | H71: =IF(OR(H$4<Assumptions!$C$32,H$4<$B71),0,H49*IF(H$4>=Assumptions!$C$33,INDEX($D$94:$D$111,H$4-MAX($B71,Assumptions!$C$32)+1),INDEX($C$94:$C$111,H$4-MAX($B71,Assumptions!$C$32)+1))) -> 0.468512 | I71: =IF(OR(I$4<Assumptions!$C$32,I$4<$B71),0,I49*IF(I$4>=Assumptions!$C$33,INDEX($D$94:$D$111,I$4-MAX($B71,Assumptions!$C$32)+1),INDEX($C$94:$C$111,I$4-MAX($B71,Assumptions!$C$32)+1))) -> 0.61843584 | J71: =IF(OR(J$4<Assumptions!$C$32,J$4<$B71),0,J49*IF(J$4>=Assumptions!$C$33,INDEX($D$94:$D$111,J$4-MAX($B71,Assumptions!$C$32)+1),INDEX($C$94:$C$111,J$4-MAX($B71,Assumptions!$C$32)+1))) -> 0.90703923 | K71: =IF(OR(K$4<Assumptions!$C$32,K$4<$B71),0,K49*IF(K$4>=Assumptions!$C$33,INDEX($D$94:$D$111,K$4-MAX($B71,Assumptions!$C$32)+1),INDEX($C$94:$C$111,K$4-MAX($B71,Assumptions!$C$32)+1))) -> 0.81415841 | ... U71: =IF(OR(U$4<Assumptions!$C$32,U$4<$B71),0,U49*IF(U$4>=Assumptions!$C$33,INDEX($D$94:$D$111,U$4-MAX($B71,Assumptions!$C$32)+1),INDEX($C$94:$C$111,U$4-MAX($B71,Assumptions!$C$32)+1))) -> 0.23563583
A72: Cohort M2 | B72: 2 | D72: =IF(OR(D$4<Assumptions!$C$32,D$4<$B72),0,D50*IF(D$4>=Assumptions!$C$33,INDEX($D$94:$D$111,D$4-MAX($B72,Assumptions!$C$32)+1),INDEX($C$94:$C$111,D$4-MAX($B72,Assumptions!$C$32)+1))) -> 0 | E72: =IF(OR(E$4<Assumptions!$C$32,E$4<$B72),0,E50*IF(E$4>=Assumptions!$C$33,INDEX($D$94:$D$111,E$4-MAX($B72,Assumptions!$C$32)+1),INDEX($C$94:$C$111,E$4-MAX($B72,Assumptions!$C$32)+1))) -> 0 | F72: =IF(OR(F$4<Assumptions!$C$32,F$4<$B72),0,F50*IF(F$4>=Assumptions!$C$33,INDEX($D$94:$D$111,F$4-MAX($B72,Assumptions!$C$32)+1),INDEX($C$94:$C$111,F$4-MAX($B72,Assumptions!$C$32)+1))) -> 0 | G72: =IF(OR(G$4<Assumptions!$C$32,G$4<$B72),0,G50*IF(G$4>=Assumptions!$C$33,INDEX($D$94:$D$111,G$4-MAX($B72,Assumptions!$C$32)+1),INDEX($C$94:$C$111,G$4-MAX($B72,Assumptions!$C$32)+1))) -> 0.45375 | H72: =IF(OR(H$4<Assumptions!$C$32,H$4<$B72),0,H50*IF(H$4>=Assumptions!$C$33,INDEX($D$94:$D$111,H$4-MAX($B72,Assumptions!$C$32)+1),INDEX($C$94:$C$111,H$4-MAX($B72,Assumptions!$C$32)+1))) -> 0.7986 | I72: =IF(OR(I$4<Assumptions!$C$32,I$4<$B72),0,I50*IF(I$4>=Assumptions!$C$33,INDEX($D$94:$D$111,I$4-MAX($B72,Assumptions!$C$32)+1),INDEX($C$94:$C$111,I$4-MAX($B72,Assumptions!$C$32)+1))) -> 1.054152 | J72: =IF(OR(J$4<Assumptions!$C$32,J$4<$B72),0,J50*IF(J$4>=Assumptions!$C$33,INDEX($D$94:$D$111,J$4-MAX($B72,Assumptions!$C$32)+1),INDEX($C$94:$C$111,J$4-MAX($B72,Assumptions!$C$32)+1))) -> 1.5460896 | K72: =IF(OR(K$4<Assumptions!$C$32,K$4<$B72),0,K50*IF(K$4>=Assumptions!$C$33,INDEX($D$94:$D$111,K$4-MAX($B72,Assumptions!$C$32)+1),INDEX($C$94:$C$111,K$4-MAX($B72,Assumptions!$C$32)+1))) -> 1.38777 | ... U72: =IF(OR(U$4<Assumptions!$C$32,U$4<$B72),0,U50*IF(U$4>=Assumptions!$C$33,INDEX($D$94:$D$111,U$4-MAX($B72,Assumptions!$C$32)+1),INDEX($C$94:$C$111,U$4-MAX($B72,Assumptions!$C$32)+1))) -> 0.40165199
A73: Cohort M3 | B73: 3 | D73: =IF(OR(D$4<Assumptions!$C$32,D$4<$B73),0,D51*IF(D$4>=Assumptions!$C$33,INDEX($D$94:$D$111,D$4-MAX($B73,Assumptions!$C$32)+1),INDEX($C$94:$C$111,D$4-MAX($B73,Assumptions!$C$32)+1))) -> 0 | E73: =IF(OR(E$4<Assumptions!$C$32,E$4<$B73),0,E51*IF(E$4>=Assumptions!$C$33,INDEX($D$94:$D$111,E$4-MAX($B73,Assumptions!$C$32)+1),INDEX($C$94:$C$111,E$4-MAX($B73,Assumptions!$C$32)+1))) -> 0 | F73: =IF(OR(F$4<Assumptions!$C$32,F$4<$B73),0,F51*IF(F$4>=Assumptions!$C$33,INDEX($D$94:$D$111,F$4-MAX($B73,Assumptions!$C$32)+1),INDEX($C$94:$C$111,F$4-MAX($B73,Assumptions!$C$32)+1))) -> 0 | G73: =IF(OR(G$4<Assumptions!$C$32,G$4<$B73),0,G51*IF(G$4>=Assumptions!$C$33,INDEX($D$94:$D$111,G$4-MAX($B73,Assumptions!$C$32)+1),INDEX($C$94:$C$111,G$4-MAX($B73,Assumptions!$C$32)+1))) -> 0.6875 | H73: =IF(OR(H$4<Assumptions!$C$32,H$4<$B73),0,H51*IF(H$4>=Assumptions!$C$33,INDEX($D$94:$D$111,H$4-MAX($B73,Assumptions!$C$32)+1),INDEX($C$94:$C$111,H$4-MAX($B73,Assumptions!$C$32)+1))) -> 1.21 | I73: =IF(OR(I$4<Assumptions!$C$32,I$4<$B73),0,I51*IF(I$4>=Assumptions!$C$33,INDEX($D$94:$D$111,I$4-MAX($B73,Assumptions!$C$32)+1),INDEX($C$94:$C$111,I$4-MAX($B73,Assumptions!$C$32)+1))) -> 1.5972 | J73: =IF(OR(J$4<Assumptions!$C$32,J$4<$B73),0,J51*IF(J$4>=Assumptions!$C$33,INDEX($D$94:$D$111,J$4-MAX($B73,Assumptions!$C$32)+1),INDEX($C$94:$C$111,J$4-MAX($B73,Assumptions!$C$32)+1))) -> 2.34256 | K73: =IF(OR(K$4<Assumptions!$C$32,K$4<$B73),0,K51*IF(K$4>=Assumptions!$C$33,INDEX($D$94:$D$111,K$4-MAX($B73,Assumptions!$C$32)+1),INDEX($C$94:$C$111,K$4-MAX($B73,Assumptions!$C$32)+1))) -> 2.1026819 | ... U73: =IF(OR(U$4<Assumptions!$C$32,U$4<$B73),0,U51*IF(U$4>=Assumptions!$C$33,INDEX($D$94:$D$111,U$4-MAX($B73,Assumptions!$C$32)+1),INDEX($C$94:$C$111,U$4-MAX($B73,Assumptions!$C$32)+1))) -> 0.60856361
A74: Cohort M4 | B74: 4 | D74: =IF(OR(D$4<Assumptions!$C$32,D$4<$B74),0,D52*IF(D$4>=Assumptions!$C$33,INDEX($D$94:$D$111,D$4-MAX($B74,Assumptions!$C$32)+1),INDEX($C$94:$C$111,D$4-MAX($B74,Assumptions!$C$32)+1))) -> 0 | E74: =IF(OR(E$4<Assumptions!$C$32,E$4<$B74),0,E52*IF(E$4>=Assumptions!$C$33,INDEX($D$94:$D$111,E$4-MAX($B74,Assumptions!$C$32)+1),INDEX($C$94:$C$111,E$4-MAX($B74,Assumptions!$C$32)+1))) -> 0 | F74: =IF(OR(F$4<Assumptions!$C$32,F$4<$B74),0,F52*IF(F$4>=Assumptions!$C$33,INDEX($D$94:$D$111,F$4-MAX($B74,Assumptions!$C$32)+1),INDEX($C$94:$C$111,F$4-MAX($B74,Assumptions!$C$32)+1))) -> 0 | G74: =IF(OR(G$4<Assumptions!$C$32,G$4<$B74),0,G52*IF(G$4>=Assumptions!$C$33,INDEX($D$94:$D$111,G$4-MAX($B74,Assumptions!$C$32)+1),INDEX($C$94:$C$111,G$4-MAX($B74,Assumptions!$C$32)+1))) -> 0.9765625 | H74: =IF(OR(H$4<Assumptions!$C$32,H$4<$B74),0,H52*IF(H$4>=Assumptions!$C$33,INDEX($D$94:$D$111,H$4-MAX($B74,Assumptions!$C$32)+1),INDEX($C$94:$C$111,H$4-MAX($B74,Assumptions!$C$32)+1))) -> 1.71875 | I74: =IF(OR(I$4<Assumptions!$C$32,I$4<$B74),0,I52*IF(I$4>=Assumptions!$C$33,INDEX($D$94:$D$111,I$4-MAX($B74,Assumptions!$C$32)+1),INDEX($C$94:$C$111,I$4-MAX($B74,Assumptions!$C$32)+1))) -> 2.26875 | J74: =IF(OR(J$4<Assumptions!$C$32,J$4<$B74),0,J52*IF(J$4>=Assumptions!$C$33,INDEX($D$94:$D$111,J$4-MAX($B74,Assumptions!$C$32)+1),INDEX($C$94:$C$111,J$4-MAX($B74,Assumptions!$C$32)+1))) -> 3.3275 | K74: =IF(OR(K$4<Assumptions!$C$32,K$4<$B74),0,K52*IF(K$4>=Assumptions!$C$33,INDEX($D$94:$D$111,K$4-MAX($B74,Assumptions!$C$32)+1),INDEX($C$94:$C$111,K$4-MAX($B74,Assumptions!$C$32)+1))) -> 2.986764 | ... U74: =IF(OR(U$4<Assumptions!$C$32,U$4<$B74),0,U52*IF(U$4>=Assumptions!$C$33,INDEX($D$94:$D$111,U$4-MAX($B74,Assumptions!$C$32)+1),INDEX($C$94:$C$111,U$4-MAX($B74,Assumptions!$C$32)+1))) -> 0.86443695
A75: Cohort M5 | B75: 5 | D75: =IF(OR(D$4<Assumptions!$C$32,D$4<$B75),0,D53*IF(D$4>=Assumptions!$C$33,INDEX($D$94:$D$111,D$4-MAX($B75,Assumptions!$C$32)+1),INDEX($C$94:$C$111,D$4-MAX($B75,Assumptions!$C$32)+1))) -> 0 | E75: =IF(OR(E$4<Assumptions!$C$32,E$4<$B75),0,E53*IF(E$4>=Assumptions!$C$33,INDEX($D$94:$D$111,E$4-MAX($B75,Assumptions!$C$32)+1),INDEX($C$94:$C$111,E$4-MAX($B75,Assumptions!$C$32)+1))) -> 0 | F75: =IF(OR(F$4<Assumptions!$C$32,F$4<$B75),0,F53*IF(F$4>=Assumptions!$C$33,INDEX($D$94:$D$111,F$4-MAX($B75,Assumptions!$C$32)+1),INDEX($C$94:$C$111,F$4-MAX($B75,Assumptions!$C$32)+1))) -> 0 | G75: =IF(OR(G$4<Assumptions!$C$32,G$4<$B75),0,G53*IF(G$4>=Assumptions!$C$33,INDEX($D$94:$D$111,G$4-MAX($B75,Assumptions!$C$32)+1),INDEX($C$94:$C$111,G$4-MAX($B75,Assumptions!$C$32)+1))) -> 0 | H75: =IF(OR(H$4<Assumptions!$C$32,H$4<$B75),0,H53*IF(H$4>=Assumptions!$C$33,INDEX($D$94:$D$111,H$4-MAX($B75,Assumptions!$C$32)+1),INDEX($C$94:$C$111,H$4-MAX($B75,Assumptions!$C$32)+1))) -> 1.171875 | I75: =IF(OR(I$4<Assumptions!$C$32,I$4<$B75),0,I53*IF(I$4>=Assumptions!$C$33,INDEX($D$94:$D$111,I$4-MAX($B75,Assumptions!$C$32)+1),INDEX($C$94:$C$111,I$4-MAX($B75,Assumptions!$C$32)+1))) -> 2.0625 | J75: =IF(OR(J$4<Assumptions!$C$32,J$4<$B75),0,J53*IF(J$4>=Assumptions!$C$33,INDEX($D$94:$D$111,J$4-MAX($B75,Assumptions!$C$32)+1),INDEX($C$94:$C$111,J$4-MAX($B75,Assumptions!$C$32)+1))) -> 2.7225 | K75: =IF(OR(K$4<Assumptions!$C$32,K$4<$B75),0,K53*IF(K$4>=Assumptions!$C$33,INDEX($D$94:$D$111,K$4-MAX($B75,Assumptions!$C$32)+1),INDEX($C$94:$C$111,K$4-MAX($B75,Assumptions!$C$32)+1))) -> 3.993 | ... U75: =IF(OR(U$4<Assumptions!$C$32,U$4<$B75),0,U53*IF(U$4>=Assumptions!$C$33,INDEX($D$94:$D$111,U$4-MAX($B75,Assumptions!$C$32)+1),INDEX($C$94:$C$111,U$4-MAX($B75,Assumptions!$C$32)+1))) -> 1.1787777
A76: Cohort M6 | B76: 6 | D76: =IF(OR(D$4<Assumptions!$C$32,D$4<$B76),0,D54*IF(D$4>=Assumptions!$C$33,INDEX($D$94:$D$111,D$4-MAX($B76,Assumptions!$C$32)+1),INDEX($C$94:$C$111,D$4-MAX($B76,Assumptions!$C$32)+1))) -> 0 | E76: =IF(OR(E$4<Assumptions!$C$32,E$4<$B76),0,E54*IF(E$4>=Assumptions!$C$33,INDEX($D$94:$D$111,E$4-MAX($B76,Assumptions!$C$32)+1),INDEX($C$94:$C$111,E$4-MAX($B76,Assumptions!$C$32)+1))) -> 0 | F76: =IF(OR(F$4<Assumptions!$C$32,F$4<$B76),0,F54*IF(F$4>=Assumptions!$C$33,INDEX($D$94:$D$111,F$4-MAX($B76,Assumptions!$C$32)+1),INDEX($C$94:$C$111,F$4-MAX($B76,Assumptions!$C$32)+1))) -> 0 | G76: =IF(OR(G$4<Assumptions!$C$32,G$4<$B76),0,G54*IF(G$4>=Assumptions!$C$33,INDEX($D$94:$D$111,G$4-MAX($B76,Assumptions!$C$32)+1),INDEX($C$94:$C$111,G$4-MAX($B76,Assumptions!$C$32)+1))) -> 0 | H76: =IF(OR(H$4<Assumptions!$C$32,H$4<$B76),0,H54*IF(H$4>=Assumptions!$C$33,INDEX($D$94:$D$111,H$4-MAX($B76,Assumptions!$C$32)+1),INDEX($C$94:$C$111,H$4-MAX($B76,Assumptions!$C$32)+1))) -> 0 | I76: =IF(OR(I$4<Assumptions!$C$32,I$4<$B76),0,I54*IF(I$4>=Assumptions!$C$33,INDEX($D$94:$D$111,I$4-MAX($B76,Assumptions!$C$32)+1),INDEX($C$94:$C$111,I$4-MAX($B76,Assumptions!$C$32)+1))) -> 1.3671875 | J76: =IF(OR(J$4<Assumptions!$C$32,J$4<$B76),0,J54*IF(J$4>=Assumptions!$C$33,INDEX($D$94:$D$111,J$4-MAX($B76,Assumptions!$C$32)+1),INDEX($C$94:$C$111,J$4-MAX($B76,Assumptions!$C$32)+1))) -> 2.40625 | K76: =IF(OR(K$4<Assumptions!$C$32,K$4<$B76),0,K54*IF(K$4>=Assumptions!$C$33,INDEX($D$94:$D$111,K$4-MAX($B76,Assumptions!$C$32)+1),INDEX($C$94:$C$111,K$4-MAX($B76,Assumptions!$C$32)+1))) -> 3.17625 | ... U76: =IF(OR(U$4<Assumptions!$C$32,U$4<$B76),0,U54*IF(U$4>=Assumptions!$C$33,INDEX($D$94:$D$111,U$4-MAX($B76,Assumptions!$C$32)+1),INDEX($C$94:$C$111,U$4-MAX($B76,Assumptions!$C$32)+1))) -> 1.5627734
A77: Cohort M7 | B77: 7 | D77: =IF(OR(D$4<Assumptions!$C$32,D$4<$B77),0,D55*IF(D$4>=Assumptions!$C$33,INDEX($D$94:$D$111,D$4-MAX($B77,Assumptions!$C$32)+1),INDEX($C$94:$C$111,D$4-MAX($B77,Assumptions!$C$32)+1))) -> 0 | E77: =IF(OR(E$4<Assumptions!$C$32,E$4<$B77),0,E55*IF(E$4>=Assumptions!$C$33,INDEX($D$94:$D$111,E$4-MAX($B77,Assumptions!$C$32)+1),INDEX($C$94:$C$111,E$4-MAX($B77,Assumptions!$C$32)+1))) -> 0 | F77: =IF(OR(F$4<Assumptions!$C$32,F$4<$B77),0,F55*IF(F$4>=Assumptions!$C$33,INDEX($D$94:$D$111,F$4-MAX($B77,Assumptions!$C$32)+1),INDEX($C$94:$C$111,F$4-MAX($B77,Assumptions!$C$32)+1))) -> 0 | G77: =IF(OR(G$4<Assumptions!$C$32,G$4<$B77),0,G55*IF(G$4>=Assumptions!$C$33,INDEX($D$94:$D$111,G$4-MAX($B77,Assumptions!$C$32)+1),INDEX($C$94:$C$111,G$4-MAX($B77,Assumptions!$C$32)+1))) -> 0 | H77: =IF(OR(H$4<Assumptions!$C$32,H$4<$B77),0,H55*IF(H$4>=Assumptions!$C$33,INDEX($D$94:$D$111,H$4-MAX($B77,Assumptions!$C$32)+1),INDEX($C$94:$C$111,H$4-MAX($B77,Assumptions!$C$32)+1))) -> 0 | I77: =IF(OR(I$4<Assumptions!$C$32,I$4<$B77),0,I55*IF(I$4>=Assumptions!$C$33,INDEX($D$94:$D$111,I$4-MAX($B77,Assumptions!$C$32)+1),INDEX($C$94:$C$111,I$4-MAX($B77,Assumptions!$C$32)+1))) -> 0 | J77: =IF(OR(J$4<Assumptions!$C$32,J$4<$B77),0,J55*IF(J$4>=Assumptions!$C$33,INDEX($D$94:$D$111,J$4-MAX($B77,Assumptions!$C$32)+1),INDEX($C$94:$C$111,J$4-MAX($B77,Assumptions!$C$32)+1))) -> 1.3671875 | K77: =IF(OR(K$4<Assumptions!$C$32,K$4<$B77),0,K55*IF(K$4>=Assumptions!$C$33,INDEX($D$94:$D$111,K$4-MAX($B77,Assumptions!$C$32)+1),INDEX($C$94:$C$111,K$4-MAX($B77,Assumptions!$C$32)+1))) -> 2.40625 | ... U77: =IF(OR(U$4<Assumptions!$C$32,U$4<$B77),0,U55*IF(U$4>=Assumptions!$C$33,INDEX($D$94:$D$111,U$4-MAX($B77,Assumptions!$C$32)+1),INDEX($C$94:$C$111,U$4-MAX($B77,Assumptions!$C$32)+1))) -> 1.7758789
A78: Cohort M8 | B78: 8 | D78: =IF(OR(D$4<Assumptions!$C$32,D$4<$B78),0,D56*IF(D$4>=Assumptions!$C$33,INDEX($D$94:$D$111,D$4-MAX($B78,Assumptions!$C$32)+1),INDEX($C$94:$C$111,D$4-MAX($B78,Assumptions!$C$32)+1))) -> 0 | E78: =IF(OR(E$4<Assumptions!$C$32,E$4<$B78),0,E56*IF(E$4>=Assumptions!$C$33,INDEX($D$94:$D$111,E$4-MAX($B78,Assumptions!$C$32)+1),INDEX($C$94:$C$111,E$4-MAX($B78,Assumptions!$C$32)+1))) -> 0 | F78: =IF(OR(F$4<Assumptions!$C$32,F$4<$B78),0,F56*IF(F$4>=Assumptions!$C$33,INDEX($D$94:$D$111,F$4-MAX($B78,Assumptions!$C$32)+1),INDEX($C$94:$C$111,F$4-MAX($B78,Assumptions!$C$32)+1))) -> 0 | G78: =IF(OR(G$4<Assumptions!$C$32,G$4<$B78),0,G56*IF(G$4>=Assumptions!$C$33,INDEX($D$94:$D$111,G$4-MAX($B78,Assumptions!$C$32)+1),INDEX($C$94:$C$111,G$4-MAX($B78,Assumptions!$C$32)+1))) -> 0 | H78: =IF(OR(H$4<Assumptions!$C$32,H$4<$B78),0,H56*IF(H$4>=Assumptions!$C$33,INDEX($D$94:$D$111,H$4-MAX($B78,Assumptions!$C$32)+1),INDEX($C$94:$C$111,H$4-MAX($B78,Assumptions!$C$32)+1))) -> 0 | I78: =IF(OR(I$4<Assumptions!$C$32,I$4<$B78),0,I56*IF(I$4>=Assumptions!$C$33,INDEX($D$94:$D$111,I$4-MAX($B78,Assumptions!$C$32)+1),INDEX($C$94:$C$111,I$4-MAX($B78,Assumptions!$C$32)+1))) -> 0 | J78: =IF(OR(J$4<Assumptions!$C$32,J$4<$B78),0,J56*IF(J$4>=Assumptions!$C$33,INDEX($D$94:$D$111,J$4-MAX($B78,Assumptions!$C$32)+1),INDEX($C$94:$C$111,J$4-MAX($B78,Assumptions!$C$32)+1))) -> 0 | K78: =IF(OR(K$4<Assumptions!$C$32,K$4<$B78),0,K56*IF(K$4>=Assumptions!$C$33,INDEX($D$94:$D$111,K$4-MAX($B78,Assumptions!$C$32)+1),INDEX($C$94:$C$111,K$4-MAX($B78,Assumptions!$C$32)+1))) -> 1.3671875 | ... U78: =IF(OR(U$4<Assumptions!$C$32,U$4<$B78),0,U56*IF(U$4>=Assumptions!$C$33,INDEX($D$94:$D$111,U$4-MAX($B78,Assumptions!$C$32)+1),INDEX($C$94:$C$111,U$4-MAX($B78,Assumptions!$C$32)+1))) -> 2.0180442
A79: Cohort M9 | B79: 9 | D79: =IF(OR(D$4<Assumptions!$C$32,D$4<$B79),0,D57*IF(D$4>=Assumptions!$C$33,INDEX($D$94:$D$111,D$4-MAX($B79,Assumptions!$C$32)+1),INDEX($C$94:$C$111,D$4-MAX($B79,Assumptions!$C$32)+1))) -> 0 | E79: =IF(OR(E$4<Assumptions!$C$32,E$4<$B79),0,E57*IF(E$4>=Assumptions!$C$33,INDEX($D$94:$D$111,E$4-MAX($B79,Assumptions!$C$32)+1),INDEX($C$94:$C$111,E$4-MAX($B79,Assumptions!$C$32)+1))) -> 0 | F79: =IF(OR(F$4<Assumptions!$C$32,F$4<$B79),0,F57*IF(F$4>=Assumptions!$C$33,INDEX($D$94:$D$111,F$4-MAX($B79,Assumptions!$C$32)+1),INDEX($C$94:$C$111,F$4-MAX($B79,Assumptions!$C$32)+1))) -> 0 | G79: =IF(OR(G$4<Assumptions!$C$32,G$4<$B79),0,G57*IF(G$4>=Assumptions!$C$33,INDEX($D$94:$D$111,G$4-MAX($B79,Assumptions!$C$32)+1),INDEX($C$94:$C$111,G$4-MAX($B79,Assumptions!$C$32)+1))) -> 0 | H79: =IF(OR(H$4<Assumptions!$C$32,H$4<$B79),0,H57*IF(H$4>=Assumptions!$C$33,INDEX($D$94:$D$111,H$4-MAX($B79,Assumptions!$C$32)+1),INDEX($C$94:$C$111,H$4-MAX($B79,Assumptions!$C$32)+1))) -> 0 | I79: =IF(OR(I$4<Assumptions!$C$32,I$4<$B79),0,I57*IF(I$4>=Assumptions!$C$33,INDEX($D$94:$D$111,I$4-MAX($B79,Assumptions!$C$32)+1),INDEX($C$94:$C$111,I$4-MAX($B79,Assumptions!$C$32)+1))) -> 0 | J79: =IF(OR(J$4<Assumptions!$C$32,J$4<$B79),0,J57*IF(J$4>=Assumptions!$C$33,INDEX($D$94:$D$111,J$4-MAX($B79,Assumptions!$C$32)+1),INDEX($C$94:$C$111,J$4-MAX($B79,Assumptions!$C$32)+1))) -> 0 | K79: =IF(OR(K$4<Assumptions!$C$32,K$4<$B79),0,K57*IF(K$4>=Assumptions!$C$33,INDEX($D$94:$D$111,K$4-MAX($B79,Assumptions!$C$32)+1),INDEX($C$94:$C$111,K$4-MAX($B79,Assumptions!$C$32)+1))) -> 0 | ... U79: =IF(OR(U$4<Assumptions!$C$32,U$4<$B79),0,U57*IF(U$4>=Assumptions!$C$33,INDEX($D$94:$D$111,U$4-MAX($B79,Assumptions!$C$32)+1),INDEX($C$94:$C$111,U$4-MAX($B79,Assumptions!$C$32)+1))) -> 2.293232
A80: Cohort M10 | B80: 10 | D80: =IF(OR(D$4<Assumptions!$C$32,D$4<$B80),0,D58*IF(D$4>=Assumptions!$C$33,INDEX($D$94:$D$111,D$4-MAX($B80,Assumptions!$C$32)+1),INDEX($C$94:$C$111,D$4-MAX($B80,Assumptions!$C$32)+1))) -> 0 | E80: =IF(OR(E$4<Assumptions!$C$32,E$4<$B80),0,E58*IF(E$4>=Assumptions!$C$33,INDEX($D$94:$D$111,E$4-MAX($B80,Assumptions!$C$32)+1),INDEX($C$94:$C$111,E$4-MAX($B80,Assumptions!$C$32)+1))) -> 0 | F80: =IF(OR(F$4<Assumptions!$C$32,F$4<$B80),0,F58*IF(F$4>=Assumptions!$C$33,INDEX($D$94:$D$111,F$4-MAX($B80,Assumptions!$C$32)+1),INDEX($C$94:$C$111,F$4-MAX($B80,Assumptions!$C$32)+1))) -> 0 | G80: =IF(OR(G$4<Assumptions!$C$32,G$4<$B80),0,G58*IF(G$4>=Assumptions!$C$33,INDEX($D$94:$D$111,G$4-MAX($B80,Assumptions!$C$32)+1),INDEX($C$94:$C$111,G$4-MAX($B80,Assumptions!$C$32)+1))) -> 0 | H80: =IF(OR(H$4<Assumptions!$C$32,H$4<$B80),0,H58*IF(H$4>=Assumptions!$C$33,INDEX($D$94:$D$111,H$4-MAX($B80,Assumptions!$C$32)+1),INDEX($C$94:$C$111,H$4-MAX($B80,Assumptions!$C$32)+1))) -> 0 | I80: =IF(OR(I$4<Assumptions!$C$32,I$4<$B80),0,I58*IF(I$4>=Assumptions!$C$33,INDEX($D$94:$D$111,I$4-MAX($B80,Assumptions!$C$32)+1),INDEX($C$94:$C$111,I$4-MAX($B80,Assumptions!$C$32)+1))) -> 0 | J80: =IF(OR(J$4<Assumptions!$C$32,J$4<$B80),0,J58*IF(J$4>=Assumptions!$C$33,INDEX($D$94:$D$111,J$4-MAX($B80,Assumptions!$C$32)+1),INDEX($C$94:$C$111,J$4-MAX($B80,Assumptions!$C$32)+1))) -> 0 | K80: =IF(OR(K$4<Assumptions!$C$32,K$4<$B80),0,K58*IF(K$4>=Assumptions!$C$33,INDEX($D$94:$D$111,K$4-MAX($B80,Assumptions!$C$32)+1),INDEX($C$94:$C$111,K$4-MAX($B80,Assumptions!$C$32)+1))) -> 0 | ... U80: =IF(OR(U$4<Assumptions!$C$32,U$4<$B80),0,U58*IF(U$4>=Assumptions!$C$33,INDEX($D$94:$D$111,U$4-MAX($B80,Assumptions!$C$32)+1),INDEX($C$94:$C$111,U$4-MAX($B80,Assumptions!$C$32)+1))) -> 2.6059455
A81: Cohort M11 | B81: 11 | D81: =IF(OR(D$4<Assumptions!$C$32,D$4<$B81),0,D59*IF(D$4>=Assumptions!$C$33,INDEX($D$94:$D$111,D$4-MAX($B81,Assumptions!$C$32)+1),INDEX($C$94:$C$111,D$4-MAX($B81,Assumptions!$C$32)+1))) -> 0 | E81: =IF(OR(E$4<Assumptions!$C$32,E$4<$B81),0,E59*IF(E$4>=Assumptions!$C$33,INDEX($D$94:$D$111,E$4-MAX($B81,Assumptions!$C$32)+1),INDEX($C$94:$C$111,E$4-MAX($B81,Assumptions!$C$32)+1))) -> 0 | F81: =IF(OR(F$4<Assumptions!$C$32,F$4<$B81),0,F59*IF(F$4>=Assumptions!$C$33,INDEX($D$94:$D$111,F$4-MAX($B81,Assumptions!$C$32)+1),INDEX($C$94:$C$111,F$4-MAX($B81,Assumptions!$C$32)+1))) -> 0 | G81: =IF(OR(G$4<Assumptions!$C$32,G$4<$B81),0,G59*IF(G$4>=Assumptions!$C$33,INDEX($D$94:$D$111,G$4-MAX($B81,Assumptions!$C$32)+1),INDEX($C$94:$C$111,G$4-MAX($B81,Assumptions!$C$32)+1))) -> 0 | H81: =IF(OR(H$4<Assumptions!$C$32,H$4<$B81),0,H59*IF(H$4>=Assumptions!$C$33,INDEX($D$94:$D$111,H$4-MAX($B81,Assumptions!$C$32)+1),INDEX($C$94:$C$111,H$4-MAX($B81,Assumptions!$C$32)+1))) -> 0 | I81: =IF(OR(I$4<Assumptions!$C$32,I$4<$B81),0,I59*IF(I$4>=Assumptions!$C$33,INDEX($D$94:$D$111,I$4-MAX($B81,Assumptions!$C$32)+1),INDEX($C$94:$C$111,I$4-MAX($B81,Assumptions!$C$32)+1))) -> 0 | J81: =IF(OR(J$4<Assumptions!$C$32,J$4<$B81),0,J59*IF(J$4>=Assumptions!$C$33,INDEX($D$94:$D$111,J$4-MAX($B81,Assumptions!$C$32)+1),INDEX($C$94:$C$111,J$4-MAX($B81,Assumptions!$C$32)+1))) -> 0 | K81: =IF(OR(K$4<Assumptions!$C$32,K$4<$B81),0,K59*IF(K$4>=Assumptions!$C$33,INDEX($D$94:$D$111,K$4-MAX($B81,Assumptions!$C$32)+1),INDEX($C$94:$C$111,K$4-MAX($B81,Assumptions!$C$32)+1))) -> 0 | ... U81: =IF(OR(U$4<Assumptions!$C$32,U$4<$B81),0,U59*IF(U$4>=Assumptions!$C$33,INDEX($D$94:$D$111,U$4-MAX($B81,Assumptions!$C$32)+1),INDEX($C$94:$C$111,U$4-MAX($B81,Assumptions!$C$32)+1))) -> 2.5382586
A82: Cohort M12 | B82: 12 | D82: =IF(OR(D$4<Assumptions!$C$32,D$4<$B82),0,D60*IF(D$4>=Assumptions!$C$33,INDEX($D$94:$D$111,D$4-MAX($B82,Assumptions!$C$32)+1),INDEX($C$94:$C$111,D$4-MAX($B82,Assumptions!$C$32)+1))) -> 0 | E82: =IF(OR(E$4<Assumptions!$C$32,E$4<$B82),0,E60*IF(E$4>=Assumptions!$C$33,INDEX($D$94:$D$111,E$4-MAX($B82,Assumptions!$C$32)+1),INDEX($C$94:$C$111,E$4-MAX($B82,Assumptions!$C$32)+1))) -> 0 | F82: =IF(OR(F$4<Assumptions!$C$32,F$4<$B82),0,F60*IF(F$4>=Assumptions!$C$33,INDEX($D$94:$D$111,F$4-MAX($B82,Assumptions!$C$32)+1),INDEX($C$94:$C$111,F$4-MAX($B82,Assumptions!$C$32)+1))) -> 0 | G82: =IF(OR(G$4<Assumptions!$C$32,G$4<$B82),0,G60*IF(G$4>=Assumptions!$C$33,INDEX($D$94:$D$111,G$4-MAX($B82,Assumptions!$C$32)+1),INDEX($C$94:$C$111,G$4-MAX($B82,Assumptions!$C$32)+1))) -> 0 | H82: =IF(OR(H$4<Assumptions!$C$32,H$4<$B82),0,H60*IF(H$4>=Assumptions!$C$33,INDEX($D$94:$D$111,H$4-MAX($B82,Assumptions!$C$32)+1),INDEX($C$94:$C$111,H$4-MAX($B82,Assumptions!$C$32)+1))) -> 0 | I82: =IF(OR(I$4<Assumptions!$C$32,I$4<$B82),0,I60*IF(I$4>=Assumptions!$C$33,INDEX($D$94:$D$111,I$4-MAX($B82,Assumptions!$C$32)+1),INDEX($C$94:$C$111,I$4-MAX($B82,Assumptions!$C$32)+1))) -> 0 | J82: =IF(OR(J$4<Assumptions!$C$32,J$4<$B82),0,J60*IF(J$4>=Assumptions!$C$33,INDEX($D$94:$D$111,J$4-MAX($B82,Assumptions!$C$32)+1),INDEX($C$94:$C$111,J$4-MAX($B82,Assumptions!$C$32)+1))) -> 0 | K82: =IF(OR(K$4<Assumptions!$C$32,K$4<$B82),0,K60*IF(K$4>=Assumptions!$C$33,INDEX($D$94:$D$111,K$4-MAX($B82,Assumptions!$C$32)+1),INDEX($C$94:$C$111,K$4-MAX($B82,Assumptions!$C$32)+1))) -> 0 | ... U82: =IF(OR(U$4<Assumptions!$C$32,U$4<$B82),0,U60*IF(U$4>=Assumptions!$C$33,INDEX($D$94:$D$111,U$4-MAX($B82,Assumptions!$C$32)+1),INDEX($C$94:$C$111,U$4-MAX($B82,Assumptions!$C$32)+1))) -> 2.77554
... A88: Cohort M18 | B88: 18 | D88: =IF(OR(D$4<Assumptions!$C$32,D$4<$B88),0,D66*IF(D$4>=Assumptions!$C$33,INDEX($D$94:$D$111,D$4-MAX($B88,Assumptions!$C$32)+1),INDEX($C$94:$C$111,D$4-MAX($B88,Assumptions!$C$32)+1))) -> 0 | E88: =IF(OR(E$4<Assumptions!$C$32,E$4<$B88),0,E66*IF(E$4>=Assumptions!$C$33,INDEX($D$94:$D$111,E$4-MAX($B88,Assumptions!$C$32)+1),INDEX($C$94:$C$111,E$4-MAX($B88,Assumptions!$C$32)+1))) -> 0 | F88: =IF(OR(F$4<Assumptions!$C$32,F$4<$B88),0,F66*IF(F$4>=Assumptions!$C$33,INDEX($D$94:$D$111,F$4-MAX($B88,Assumptions!$C$32)+1),INDEX($C$94:$C$111,F$4-MAX($B88,Assumptions!$C$32)+1))) -> 0 | G88: =IF(OR(G$4<Assumptions!$C$32,G$4<$B88),0,G66*IF(G$4>=Assumptions!$C$33,INDEX($D$94:$D$111,G$4-MAX($B88,Assumptions!$C$32)+1),INDEX($C$94:$C$111,G$4-MAX($B88,Assumptions!$C$32)+1))) -> 0 | H88: =IF(OR(H$4<Assumptions!$C$32,H$4<$B88),0,H66*IF(H$4>=Assumptions!$C$33,INDEX($D$94:$D$111,H$4-MAX($B88,Assumptions!$C$32)+1),INDEX($C$94:$C$111,H$4-MAX($B88,Assumptions!$C$32)+1))) -> 0 | I88: =IF(OR(I$4<Assumptions!$C$32,I$4<$B88),0,I66*IF(I$4>=Assumptions!$C$33,INDEX($D$94:$D$111,I$4-MAX($B88,Assumptions!$C$32)+1),INDEX($C$94:$C$111,I$4-MAX($B88,Assumptions!$C$32)+1))) -> 0 | J88: =IF(OR(J$4<Assumptions!$C$32,J$4<$B88),0,J66*IF(J$4>=Assumptions!$C$33,INDEX($D$94:$D$111,J$4-MAX($B88,Assumptions!$C$32)+1),INDEX($C$94:$C$111,J$4-MAX($B88,Assumptions!$C$32)+1))) -> 0 | K88: =IF(OR(K$4<Assumptions!$C$32,K$4<$B88),0,K66*IF(K$4>=Assumptions!$C$33,INDEX($D$94:$D$111,K$4-MAX($B88,Assumptions!$C$32)+1),INDEX($C$94:$C$111,K$4-MAX($B88,Assumptions!$C$32)+1))) -> 0 | ... U88: =IF(OR(U$4<Assumptions!$C$32,U$4<$B88),0,U66*IF(U$4>=Assumptions!$C$33,INDEX($D$94:$D$111,U$4-MAX($B88,Assumptions!$C$32)+1),INDEX($C$94:$C$111,U$4-MAX($B88,Assumptions!$C$32)+1))) -> 0.78125
A92: Bonus curve by badge age (months since max(cohort start, badge launch) + 1)
A93: Badge age | B93: Age # | C93: Rate before AI launch | D93: Rate after AI launch
A94: Age 1 | B94: 1 | C94: =Assumptions!$C$36*IF($B94<=3,INDEX(Assumptions!$C$48:$C$53,$B94),INDEX(Assumptions!$C$48:$C$53,4)) -> 0.00025 | D94: =Assumptions!$C$36*IF($B94<=3,INDEX(Assumptions!$C$48:$C$53,$B94),IF($B94<5,INDEX(Assumptions!$C$48:$C$53,4),IF($B94<8,(1-Assumptions!$C$37)*INDEX(Assumptions!$C$48:$C$53,4)+Assumptions!$C$37*INDEX(Assumptions!$C$48:$C$53,5),(1-Assumptions!$C$37)*INDEX(Assumptions!$C$48:$C$53,4)+Assumptions!$C$37*INDEX(Assumptions!$C$48:$C$53,6)))) -> 0.00025
A95: Age 2 | B95: 2 | C95: =Assumptions!$C$36*IF($B95<=3,INDEX(Assumptions!$C$48:$C$53,$B95),INDEX(Assumptions!$C$48:$C$53,4)) -> 0.0005 | D95: =Assumptions!$C$36*IF($B95<=3,INDEX(Assumptions!$C$48:$C$53,$B95),IF($B95<5,INDEX(Assumptions!$C$48:$C$53,4),IF($B95<8,(1-Assumptions!$C$37)*INDEX(Assumptions!$C$48:$C$53,4)+Assumptions!$C$37*INDEX(Assumptions!$C$48:$C$53,5),(1-Assumptions!$C$37)*INDEX(Assumptions!$C$48:$C$53,4)+Assumptions!$C$37*INDEX(Assumptions!$C$48:$C$53,6)))) -> 0.0005
A96: Age 3 | B96: 3 | C96: =Assumptions!$C$36*IF($B96<=3,INDEX(Assumptions!$C$48:$C$53,$B96),INDEX(Assumptions!$C$48:$C$53,4)) -> 0.00075 | D96: =Assumptions!$C$36*IF($B96<=3,INDEX(Assumptions!$C$48:$C$53,$B96),IF($B96<5,INDEX(Assumptions!$C$48:$C$53,4),IF($B96<8,(1-Assumptions!$C$37)*INDEX(Assumptions!$C$48:$C$53,4)+Assumptions!$C$37*INDEX(Assumptions!$C$48:$C$53,5),(1-Assumptions!$C$37)*INDEX(Assumptions!$C$48:$C$53,4)+Assumptions!$C$37*INDEX(Assumptions!$C$48:$C$53,6)))) -> 0.00075
A97: Age 4 | B97: 4 | C97: =Assumptions!$C$36*IF($B97<=3,INDEX(Assumptions!$C$48:$C$53,$B97),INDEX(Assumptions!$C$48:$C$53,4)) -> 0.00125 | D97: =Assumptions!$C$36*IF($B97<=3,INDEX(Assumptions!$C$48:$C$53,$B97),IF($B97<5,INDEX(Assumptions!$C$48:$C$53,4),IF($B97<8,(1-Assumptions!$C$37)*INDEX(Assumptions!$C$48:$C$53,4)+Assumptions!$C$37*INDEX(Assumptions!$C$48:$C$53,5),(1-Assumptions!$C$37)*INDEX(Assumptions!$C$48:$C$53,4)+Assumptions!$C$37*INDEX(Assumptions!$C$48:$C$53,6)))) -> 0.00125
A98: Age 5 | B98: 5 | C98: =Assumptions!$C$36*IF($B98<=3,INDEX(Assumptions!$C$48:$C$53,$B98),INDEX(Assumptions!$C$48:$C$53,4)) -> 0.00125 | D98: =Assumptions!$C$36*IF($B98<=3,INDEX(Assumptions!$C$48:$C$53,$B98),IF($B98<5,INDEX(Assumptions!$C$48:$C$53,4),IF($B98<8,(1-Assumptions!$C$37)*INDEX(Assumptions!$C$48:$C$53,4)+Assumptions!$C$37*INDEX(Assumptions!$C$48:$C$53,5),(1-Assumptions!$C$37)*INDEX(Assumptions!$C$48:$C$53,4)+Assumptions!$C$37*INDEX(Assumptions!$C$48:$C$53,6)))) -> 0.001275
A99: Age 6 | B99: 6 | C99: =Assumptions!$C$36*IF($B99<=3,INDEX(Assumptions!$C$48:$C$53,$B99),INDEX(Assumptions!$C$48:$C$53,4)) -> 0.00125 | D99: =Assumptions!$C$36*IF($B99<=3,INDEX(Assumptions!$C$48:$C$53,$B99),IF($B99<5,INDEX(Assumptions!$C$48:$C$53,4),IF($B99<8,(1-Assumptions!$C$37)*INDEX(Assumptions!$C$48:$C$53,4)+Assumptions!$C$37*INDEX(Assumptions!$C$48:$C$53,5),(1-Assumptions!$C$37)*INDEX(Assumptions!$C$48:$C$53,4)+Assumptions!$C$37*INDEX(Assumptions!$C$48:$C$53,6)))) -> 0.001275
A100: Age 7 | B100: 7 | C100: =Assumptions!$C$36*IF($B100<=3,INDEX(Assumptions!$C$48:$C$53,$B100),INDEX(Assumptions!$C$48:$C$53,4)) -> 0.00125 | D100: =Assumptions!$C$36*IF($B100<=3,INDEX(Assumptions!$C$48:$C$53,$B100),IF($B100<5,INDEX(Assumptions!$C$48:$C$53,4),IF($B100<8,(1-Assumptions!$C$37)*INDEX(Assumptions!$C$48:$C$53,4)+Assumptions!$C$37*INDEX(Assumptions!$C$48:$C$53,5),(1-Assumptions!$C$37)*INDEX(Assumptions!$C$48:$C$53,4)+Assumptions!$C$37*INDEX(Assumptions!$C$48:$C$53,6)))) -> 0.001275
A101: Age 8 | B101: 8 | C101: =Assumptions!$C$36*IF($B101<=3,INDEX(Assumptions!$C$48:$C$53,$B101),INDEX(Assumptions!$C$48:$C$53,4)) -> 0.00125 | D101: =Assumptions!$C$36*IF($B101<=3,INDEX(Assumptions!$C$48:$C$53,$B101),IF($B101<5,INDEX(Assumptions!$C$48:$C$53,4),IF($B101<8,(1-Assumptions!$C$37)*INDEX(Assumptions!$C$48:$C$53,4)+Assumptions!$C$37*INDEX(Assumptions!$C$48:$C$53,5),(1-Assumptions!$C$37)*INDEX(Assumptions!$C$48:$C$53,4)+Assumptions!$C$37*INDEX(Assumptions!$C$48:$C$53,6)))) -> 0.001325
A102: Age 9 | B102: 9 | C102: =Assumptions!$C$36*IF($B102<=3,INDEX(Assumptions!$C$48:$C$53,$B102),INDEX(Assumptions!$C$48:$C$53,4)) -> 0.00125 | D102: =Assumptions!$C$36*IF($B102<=3,INDEX(Assumptions!$C$48:$C$53,$B102),IF($B102<5,INDEX(Assumptions!$C$48:$C$53,4),IF($B102<8,(1-Assumptions!$C$37)*INDEX(Assumptions!$C$48:$C$53,4)+Assumptions!$C$37*INDEX(Assumptions!$C$48:$C$53,5),(1-Assumptions!$C$37)*INDEX(Assumptions!$C$48:$C$53,4)+Assumptions!$C$37*INDEX(Assumptions!$C$48:$C$53,6)))) -> 0.001325
A103: Age 10 | B103: 10 | C103: =Assumptions!$C$36*IF($B103<=3,INDEX(Assumptions!$C$48:$C$53,$B103),INDEX(Assumptions!$C$48:$C$53,4)) -> 0.00125 | D103: =Assumptions!$C$36*IF($B103<=3,INDEX(Assumptions!$C$48:$C$53,$B103),IF($B103<5,INDEX(Assumptions!$C$48:$C$53,4),IF($B103<8,(1-Assumptions!$C$37)*INDEX(Assumptions!$C$48:$C$53,4)+Assumptions!$C$37*INDEX(Assumptions!$C$48:$C$53,5),(1-Assumptions!$C$37)*INDEX(Assumptions!$C$48:$C$53,4)+Assumptions!$C$37*INDEX(Assumptions!$C$48:$C$53,6)))) -> 0.001325
A104: Age 11 | B104: 11 | C104: =Assumptions!$C$36*IF($B104<=3,INDEX(Assumptions!$C$48:$C$53,$B104),INDEX(Assumptions!$C$48:$C$53,4)) -> 0.00125 | D104: =Assumptions!$C$36*IF($B104<=3,INDEX(Assumptions!$C$48:$C$53,$B104),IF($B104<5,INDEX(Assumptions!$C$48:$C$53,4),IF($B104<8,(1-Assumptions!$C$37)*INDEX(Assumptions!$C$48:$C$53,4)+Assumptions!$C$37*INDEX(Assumptions!$C$48:$C$53,5),(1-Assumptions!$C$37)*INDEX(Assumptions!$C$48:$C$53,4)+Assumptions!$C$37*INDEX(Assumptions!$C$48:$C$53,6)))) -> 0.001325
A105: Age 12 | B105: 12 | C105: =Assumptions!$C$36*IF($B105<=3,INDEX(Assumptions!$C$48:$C$53,$B105),INDEX(Assumptions!$C$48:$C$53,4)) -> 0.00125 | D105: =Assumptions!$C$36*IF($B105<=3,INDEX(Assumptions!$C$48:$C$53,$B105),IF($B105<5,INDEX(Assumptions!$C$48:$C$53,4),IF($B105<8,(1-Assumptions!$C$37)*INDEX(Assumptions!$C$48:$C$53,4)+Assumptions!$C$37*INDEX(Assumptions!$C$48:$C$53,5),(1-Assumptions!$C$37)*INDEX(Assumptions!$C$48:$C$53,4)+Assumptions!$C$37*INDEX(Assumptions!$C$48:$C$53,6)))) -> 0.001325
... A111: Age 18 | B111: 18 | C111: =Assumptions!$C$36*IF($B111<=3,INDEX(Assumptions!$C$48:$C$53,$B111),INDEX(Assumptions!$C$48:$C$53,4)) -> 0.00125 | D111: =Assumptions!$C$36*IF($B111<=3,INDEX(Assumptions!$C$48:$C$53,$B111),IF($B111<5,INDEX(Assumptions!$C$48:$C$53,4),IF($B111<8,(1-Assumptions!$C$37)*INDEX(Assumptions!$C$48:$C$53,4)+Assumptions!$C$37*INDEX(Assumptions!$C$48:$C$53,5),(1-Assumptions!$C$37)*INDEX(Assumptions!$C$48:$C$53,4)+Assumptions!$C$37*INDEX(Assumptions!$C$48:$C$53,6)))) -> 0.001325

Sheet Model_Base
A1: Habitlock model, Base scenario
A2: All money in VND million unless stated. Months are counted from launch. Flows are monthly; stocks are end of month.
A3: Line item | B3: Unit | C3: 18M total | D3: M1 | E3: M2 | F3: M3 | G3: M4 | H3: M5 | I3: M6 | J3: M7 | K3: M8 | L3: M9 | M3: M10 | N3: M11 | O3: M12 | P3: M13 | Q3: M14 | R3: M15 | S3: M16 | T3: M17 | U3: M18
A4: Month since launch | B4: # | D4: 1 | E4: 2 | F4: 3 | G4: 4 | H4: 5 | I4: 6 | J4: 7 | K4: 8 | L4: 9 | M4: 10 | N4: 11 | O4: 12 | P4: 13 | Q4: 14 | R4: 15 | S4: 16 | T4: 17 | U4: 18
A5: Calendar month | B5: 1-12 | D5: =MOD(Assumptions!$D$30-1+D4-1,12)+1 -> 7 | E5: =MOD(Assumptions!$D$30-1+E4-1,12)+1 -> 8 | F5: =MOD(Assumptions!$D$30-1+F4-1,12)+1 -> 9 | G5: =MOD(Assumptions!$D$30-1+G4-1,12)+1 -> 10 | H5: =MOD(Assumptions!$D$30-1+H4-1,12)+1 -> 11 | I5: =MOD(Assumptions!$D$30-1+I4-1,12)+1 -> 12 | J5: =MOD(Assumptions!$D$30-1+J4-1,12)+1 -> 1 | K5: =MOD(Assumptions!$D$30-1+K4-1,12)+1 -> 2 | ... U5: =MOD(Assumptions!$D$30-1+U4-1,12)+1 -> 12
A6: Withdrawal seasonality | B6: x | D6: =INDEX(Assumptions!$C$57:$N$57,D5) -> 1 | E6: =INDEX(Assumptions!$C$57:$N$57,E5) -> 1 | F6: =INDEX(Assumptions!$C$57:$N$57,F5) -> 1 | G6: =INDEX(Assumptions!$C$57:$N$57,G5) -> 1 | H6: =INDEX(Assumptions!$C$57:$N$57,H5) -> 1 | I6: =INDEX(Assumptions!$C$57:$N$57,I5) -> 1.3 | J6: =INDEX(Assumptions!$C$57:$N$57,J5) -> 1.4 | K6: =INDEX(Assumptions!$C$57:$N$57,K5) -> 1.2 | ... U6: =INDEX(Assumptions!$C$57:$N$57,U5) -> 1.3
A7: Signup weight (normalised) | B7: % | D7: =INDEX(Assumptions!$C$61:$T$61,D4)/SUM(Assumptions!$C$61:$T$61) -> 0.020833333 | E7: =INDEX(Assumptions!$C$61:$T$61,E4)/SUM(Assumptions!$C$61:$T$61) -> 0.03125 | F7: =INDEX(Assumptions!$C$61:$T$61,F4)/SUM(Assumptions!$C$61:$T$61) -> 0.041666667 | G7: =INDEX(Assumptions!$C$61:$T$61,G4)/SUM(Assumptions!$C$61:$T$61) -> 0.052083333 | H7: =INDEX(Assumptions!$C$61:$T$61,H4)/SUM(Assumptions!$C$61:$T$61) -> 0.0625 | I7: =INDEX(Assumptions!$C$61:$T$61,I4)/SUM(Assumptions!$C$61:$T$61) -> 0.072916667 | J7: =INDEX(Assumptions!$C$61:$T$61,J4)/SUM(Assumptions!$C$61:$T$61) -> 0.072916667 | K7: =INDEX(Assumptions!$C$61:$T$61,K4)/SUM(Assumptions!$C$61:$T$61) -> 0.072916667 | ... U7: =INDEX(Assumptions!$C$61:$T$61,U4)/SUM(Assumptions!$C$61:$T$61) -> 0.041666667
A8: Funnel
A9: New users acquired | B9: users | C9: =SUM(D9:U9) -> 300000 | D9: =Assumptions!$D$14*Assumptions!$D$12*D7 -> 6250 | E9: =Assumptions!$D$14*Assumptions!$D$12*E7 -> 9375 | F9: =Assumptions!$D$14*Assumptions!$D$12*F7 -> 12500 | G9: =Assumptions!$D$14*Assumptions!$D$12*G7 -> 15625 | H9: =Assumptions!$D$14*Assumptions!$D$12*H7 -> 18750 | I9: =Assumptions!$D$14*Assumptions!$D$12*I7 -> 21875 | J9: =Assumptions!$D$14*Assumptions!$D$12*J7 -> 21875 | K9: =Assumptions!$D$14*Assumptions!$D$12*K7 -> 21875 | ... U9: =Assumptions!$D$14*Assumptions!$D$12*U7 -> 12500
A10: New activated users (first deposit) | B10: users | C10: =SUM(D10:U10) -> 180000 | D10: =D9*Assumptions!$D$15 -> 3750 | E10: =E9*Assumptions!$D$15 -> 5625 | F10: =F9*Assumptions!$D$15 -> 7500 | G10: =G9*Assumptions!$D$15 -> 9375 | H10: =H9*Assumptions!$D$15 -> 11250 | I10: =I9*Assumptions!$D$15 -> 13125 | J10: =J9*Assumptions!$D$15 -> 13125 | K10: =K9*Assumptions!$D$15 -> 13125 | ... U10: =U9*Assumptions!$D$15 -> 7500
A11: Active users, end of month | B11: users | D11: =SUM(D49:D66) -> 3750 | E11: =SUM(E49:E66) -> 9075 | F11: =SUM(F49:F66) -> 15849 | G11: =SUM(G49:G66) -> 23956.08 | H11: =SUM(H49:H66) -> 33289.594 | I11: =SUM(I49:I66) -> 43751.426 | J11: =SUM(J49:J66) -> 53376.312 | K11: =SUM(K49:K66) -> 62231.207 | ... U11: =SUM(U49:U66) -> 96828.953
A12: Users who exit in month | B12: users | C12: =SUM(D12:U12) -> 83171.047 | D12: =0 -> 0 | E12: =D11*Assumptions!$D$18 -> 300 | F12: =E11*Assumptions!$D$18 -> 726 | G12: =F11*Assumptions!$D$18 -> 1267.92 | H12: =G11*Assumptions!$D$18 -> 1916.4864 | I12: =H11*Assumptions!$D$18 -> 2663.1675 | J12: =I11*Assumptions!$D$18 -> 3500.1141 | K12: =J11*Assumptions!$D$18 -> 4270.105 | L12: =K11*Assumptions!$D$18 -> 4978.4966 | ... U12: =T11*Assumptions!$D$18 -> 7767.735
A13: Cumulative users acquired | B13: users | D13: =D9 -> 6250 | E13: =D13+E9 -> 15625 | F13: =E13+F9 -> 28125 | G13: =F13+G9 -> 43750 | H13: =G13+H9 -> 62500 | I13: =H13+I9 -> 84375 | J13: =I13+J9 -> 106250 | K13: =J13+K9 -> 128125 | L13: =K13+L9 -> 150000 | ... U13: =T13+U9 -> 300000
A14: AUM
A15: Average balance per active user, start of month | B15: VND mn/user | D15: =IF(0>0,0/0,0) -> 0 | E15: =IF(D11>0,D21/D11,0) -> 0.5 | F15: =IF(E11>0,E21/E11,0) -> 0.68057851 | G15: =IF(F11>0,F21/F11,0) -> 0.8427431 | H15: =IF(G11>0,G21/G11,0) -> 0.99037355 | I15: =IF(H11>0,H21/H11,0) -> 1.1268332 | J15: =IF(I11>0,I21/I11,0) -> 1.2436752 | K15: =IF(J11>0,J21/J11,0) -> 1.3800887 | L15: =IF(K11>0,K21/K11,0) -> 1.5315181 | ... U15: =IF(T11>0,T21/T11,0) -> 2.9704234
A16: Gross deposits | B16: VND mn | C16: =SUM(D16:U16) -> 568233.52 | D16: =D11*Assumptions!$D$19/Assumptions!$D$7 -> 1875 | E16: =E11*Assumptions!$D$19/Assumptions!$D$7 -> 4537.5 | F16: =F11*Assumptions!$D$19/Assumptions!$D$7 -> 7924.5 | G16: =G11*Assumptions!$D$19/Assumptions!$D$7 -> 11978.04 | H16: =H11*Assumptions!$D$19/Assumptions!$D$7 -> 16644.797 | I16: =I11*Assumptions!$D$19/Assumptions!$D$7 -> 21875.713 | J16: =J11*Assumptions!$D$19/Assumptions!$D$7 -> 26688.156 | K16: =K11*Assumptions!$D$19/Assumptions!$D$7 -> 31115.604 | ... U16: =U11*Assumptions!$D$19/Assumptions!$D$7 -> 48414.476
A17: Exit withdrawals (churned users take full balance) | B17: VND mn | C17: =SUM(D17:U17) -> 175435.65 | D17: =D12*D15 -> 0 | E17: =E12*E15 -> 150 | F17: =F12*F15 -> 494.1 | G17: =G12*G15 -> 1068.5308 | H17: =H12*H15 -> 1898.0374 | I17: =I12*I15 -> 3000.9456 | J17: =J12*J15 -> 4353.0053 | K17: =K12*K15 -> 5893.1238 | ... U17: =U12*U15 -> 23073.462
A18: Pause & Reflect live (1/0) | B18: flag | D18: =IF(D4>=Assumptions!$D$31,1,0) -> 0 | E18: =IF(E4>=Assumptions!$D$31,1,0) -> 0 | F18: =IF(F4>=Assumptions!$D$31,1,0) -> 1 | G18: =IF(G4>=Assumptions!$D$31,1,0) -> 1 | H18: =IF(H4>=Assumptions!$D$31,1,0) -> 1 | I18: =IF(I4>=Assumptions!$D$31,1,0) -> 1 | J18: =IF(J4>=Assumptions!$D$31,1,0) -> 1 | K18: =IF(K4>=Assumptions!$D$31,1,0) -> 1 | ... U18: =IF(U4>=Assumptions!$D$31,1,0) -> 1
A19: Partial withdrawal rate after Pause & Reflect | B19: %/month | D19: =Assumptions!$D$20*D6*(1-Assumptions!$D$21*Assumptions!$D$22*D18) -> 0.05 | E19: =Assumptions!$D$20*E6*(1-Assumptions!$D$21*Assumptions!$D$22*E18) -> 0.05 | F19: =Assumptions!$D$20*F6*(1-Assumptions!$D$21*Assumptions!$D$22*F18) -> 0.044 | G19: =Assumptions!$D$20*G6*(1-Assumptions!$D$21*Assumptions!$D$22*G18) -> 0.044 | H19: =Assumptions!$D$20*H6*(1-Assumptions!$D$21*Assumptions!$D$22*H18) -> 0.044 | I19: =Assumptions!$D$20*I6*(1-Assumptions!$D$21*Assumptions!$D$22*I18) -> 0.0572 | J19: =Assumptions!$D$20*J6*(1-Assumptions!$D$21*Assumptions!$D$22*J18) -> 0.0616 | K19: =Assumptions!$D$20*K6*(1-Assumptions!$D$21*Assumptions!$D$22*K18) -> 0.0528 | ... U19: =Assumptions!$D$20*U6*(1-Assumptions!$D$21*Assumptions!$D$22*U18) -> 0.0572
A20: Partial withdrawals | B20: VND mn | C20: =SUM(D20:U20) -> 94216.314 | D20: =(0-D17)*D19 -> 0 | E20: =(D21-E17)*E19 -> 86.25 | F20: =(E21-F17)*F19 -> 250.0146 | G20: =(F21-G17)*G19 -> 540.6766 | H20: =(G21-H17)*H19 -> 960.40694 | I20: =(H21-I17)*I19 -> 1974.022 | J20: =(I21-J17)*J19 -> 3083.6689 | K20: =(J21-K17)*K19 -> 3578.3048 | L20: =(K21-L17)*L19 -> 3858.0768 | ... U20: =(T21-U17)*U19 -> 15177.723
A21: AUM, end of month | B21: VND mn | D21: =0+D16-D17-D20 -> 1875 | E21: =D21+E16-E17-E20 -> 6176.25 | F21: =E21+F16-F17-F20 -> 13356.635 | G21: =F21+G16-G17-G20 -> 23725.468 | H21: =G21+H16-H17-H20 -> 37511.82 | I21: =H21+I16-I17-I20 -> 54412.566 | J21: =I21+J16-J17-J20 -> 73664.048 | K21: =J21+K16-K17-K20 -> 95308.223 | L21: =K21+L16-L17-L20 -> 119014.34 | ... U21: =T21+U16-U17-U20 -> 298581.56
A22: Fund share of AUM | B22: % | D22: =IF(D4<Assumptions!$D$33,0,MIN(1,(D4-Assumptions!$D$33+1)/Assumptions!$D$28))*Assumptions!$D$27 -> 0 | E22: =IF(E4<Assumptions!$D$33,0,MIN(1,(E4-Assumptions!$D$33+1)/Assumptions!$D$28))*Assumptions!$D$27 -> 0 | F22: =IF(F4<Assumptions!$D$33,0,MIN(1,(F4-Assumptions!$D$33+1)/Assumptions!$D$28))*Assumptions!$D$27 -> 0 | G22: =IF(G4<Assumptions!$D$33,0,MIN(1,(G4-Assumptions!$D$33+1)/Assumptions!$D$28))*Assumptions!$D$27 -> 0 | H22: =IF(H4<Assumptions!$D$33,0,MIN(1,(H4-Assumptions!$D$33+1)/Assumptions!$D$28))*Assumptions!$D$27 -> 0.016666667 | I22: =IF(I4<Assumptions!$D$33,0,MIN(1,(I4-Assumptions!$D$33+1)/Assumptions!$D$28))*Assumptions!$D$27 -> 0.033333333 | J22: =IF(J4<Assumptions!$D$33,0,MIN(1,(J4-Assumptions!$D$33+1)/Assumptions!$D$28))*Assumptions!$D$27 -> 0.05 | K22: =IF(K4<Assumptions!$D$33,0,MIN(1,(K4-Assumptions!$D$33+1)/Assumptions!$D$28))*Assumptions!$D$27 -> 0.066666667 | ... U22: =IF(U4<Assumptions!$D$33,0,MIN(1,(U4-Assumptions!$D$33+1)/Assumptions!$D$28))*Assumptions!$D$27 -> 0.1
A23: AUM in funds | B23: VND mn | D23: =D21*D22 -> 0 | E23: =E21*E22 -> 0 | F23: =F21*F22 -> 0 | G23: =G21*G22 -> 0 | H23: =H21*H22 -> 625.19701 | I23: =I21*I22 -> 1813.7522 | J23: =J21*J22 -> 3683.2024 | K23: =K21*K22 -> 6353.8815 | ... U23: =U21*U22 -> 29858.156
A24: AUM in savings | B24: VND mn | D24: =D21-D23 -> 1875 | E24: =E21-E23 -> 6176.25 | F24: =F21-F23 -> 13356.635 | G24: =G21-G23 -> 23725.468 | H24: =H21-H23 -> 36886.623 | I24: =I21-I23 -> 52598.814 | J24: =J21-J23 -> 69980.845 | K24: =K21-K23 -> 88954.341 | ... U24: =U21-U23 -> 268723.41
A25: Average AUM in month | B25: VND mn | D25: =(0+D21)/2 -> 937.5 | E25: =(D21+E21)/2 -> 4025.625 | F25: =(E21+F21)/2 -> 9766.4427 | G25: =(F21+G21)/2 -> 18541.052 | H25: =(G21+H21)/2 -> 30618.644 | I25: =(H21+I21)/2 -> 45962.193 | J25: =(I21+J21)/2 -> 64038.307 | K25: =(J21+K21)/2 -> 84486.135 | L25: =(K21+L21)/2 -> 107161.28 | ... U25: =(T21+U21)/2 -> 293499.92
A26: Counterfactual: same cohort without Pause & Reflect
A27: Avg balance per active user, no P&R | B27: VND mn/user | D27: =IF(0>0,0/0,0) -> 0 | E27: =IF(D11>0,D30/D11,0) -> 0.5 | F27: =IF(E11>0,E30/E11,0) -> 0.68057851 | G27: =IF(F11>0,F30/F11,0) -> 0.84059199 | H27: =IF(G11>0,G30/G11,0) -> 0.98605206 | I27: =IF(H11>0,H30/H11,0) -> 1.1201811 | J27: =IF(I11>0,I30/I11,0) -> 1.2331688 | K27: =IF(J11>0,J30/J11,0) -> 1.3648424 | L27: =IF(K11>0,K30/K11,0) -> 1.5123682 | ... U27: =IF(T11>0,T30/T11,0) -> 2.9009376
A28: Exit withdrawals, no P&R | B28: VND mn | C28: =SUM(D28:U28) -> 172355.97 | D28: =D12*D27 -> 0 | E28: =E12*E27 -> 150 | F28: =F12*F27 -> 494.1 | G28: =G12*G27 -> 1065.8034 | H28: =H12*H27 -> 1889.7554 | I28: =I12*I27 -> 2983.2299 | J28: =J12*J27 -> 4316.2314 | K28: =K12*K27 -> 5828.0201 | ... U28: =U12*U27 -> 22533.715
A29: Partial withdrawals, no P&R | B29: VND mn | C29: =SUM(D29:U29) -> 105169.31 | D29: =(0-D28)*Assumptions!$D$20*D6 -> 0 | E29: =(D30-E28)*Assumptions!$D$20*E6 -> 86.25 | F29: =(E30-F28)*Assumptions!$D$20*F6 -> 284.1075 | G29: =(F30-G28)*Assumptions!$D$20*G6 -> 612.83695 | H29: =(G30-H28)*Assumptions!$D$20*H6 -> 1086.6093 | I29: =(H30-I28)*Assumptions!$D$20*I6 -> 2229.9644 | J29: =(I30-J28)*Assumptions!$D$20*J6 -> 3474.5663 | K29: =(J30-K28)*Assumptions!$D$20*K6 -> 4021.3339 | L29: =(K30-L28)*Assumptions!$D$20*L6 -> 4329.359 | ... U29: =(T30-U28)*Assumptions!$D$20*U6 -> 16843.952
A30: AUM, no P&R | B30: VND mn | D30: =0+D16-D28-D29 -> 1875 | E30: =D30+E16-E28-E29 -> 6176.25 | F30: =E30+F16-F28-F29 -> 13322.542 | G30: =F30+G16-G28-G29 -> 23621.942 | H30: =G30+H16-H28-H29 -> 37290.374 | I30: =H30+I16-I28-I29 -> 53952.893 | J30: =I30+J16-J28-J29 -> 72850.251 | K30: =J30+K16-K28-K29 -> 94116.501 | L30: =K30+L16-L28-L29 -> 117446.68 | ... U30: =T30+U16-U28-U29 -> 290708.24
A31: AUM retained thanks to Pause & Reflect | B31: VND mn | D31: =D21-D30 -> 0 | E31: =E21-E30 -> 0 | F31: =F21-F30 -> 34.0929 | G31: =G21-G30 -> 103.52582 | H31: =H21-H30 -> 221.44615 | I31: =I21-I30 -> 459.6728 | J31: =J21-J30 -> 813.79636 | K31: =K21-K30 -> 1191.7217 | ... U31: =U21-U30 -> 7873.3198
A32: P&L to Infina (incremental)
A33: Revenue on savings AUM | B33: VND mn | C33: =SUM(D33:U33) -> 885.31651 | D33: =D25*(1-D22)*Assumptions!$D$24/12 -> 0.390625 | E33: =E25*(1-E22)*Assumptions!$D$24/12 -> 1.6773437 | F33: =F25*(1-F22)*Assumptions!$D$24/12 -> 4.0693511 | G33: =G25*(1-G22)*Assumptions!$D$24/12 -> 7.7254382 | H33: =H25*(1-H22)*Assumptions!$D$24/12 -> 12.545139 | I33: =I25*(1-I22)*Assumptions!$D$24/12 -> 18.51255 | J33: =J25*(1-J22)*Assumptions!$D$24/12 -> 25.348496 | K33: =K25*(1-K22)*Assumptions!$D$24/12 -> 32.855719 | ... U33: =U25*(1-U22)*Assumptions!$D$24/12 -> 110.06247
A34: Revenue on fund AUM | B34: VND mn | C34: =SUM(D34:U34) -> 144.98449 | D34: =D25*D22*Assumptions!$D$25/12 -> 0 | E34: =E25*E22*Assumptions!$D$25/12 -> 0 | F34: =F25*F22*Assumptions!$D$25/12 -> 0 | G34: =G25*G22*Assumptions!$D$25/12 -> 0 | H34: =H25*H22*Assumptions!$D$25/12 -> 0.34020716 | I34: =I25*I22*Assumptions!$D$25/12 -> 1.0213821 | J34: =J25*J22*Assumptions!$D$25/12 -> 2.1346102 | K34: =K25*K22*Assumptions!$D$25/12 -> 3.7549393 | ... U34: =U25*U22*Assumptions!$D$25/12 -> 19.566661
A35: Gross revenue on Habitlock AUM | B35: VND mn | C35: =SUM(D35:U35) -> 1030.301 | D35: =D33+D34 -> 0.390625 | E35: =E33+E34 -> 1.6773437 | F35: =F33+F34 -> 4.0693511 | G35: =G33+G34 -> 7.7254382 | H35: =H33+H34 -> 12.885346 | I35: =I33+I34 -> 19.533932 | J35: =J33+J34 -> 27.483107 | K35: =K33+K34 -> 36.610659 | ... U35: =U33+U34 -> 129.62913
A36: Incremental revenue (after incrementality) | B36: VND mn | C36: =SUM(D36:U36) -> 721.2107 | D36: =D35*Assumptions!$D$26 -> 0.2734375 | E36: =E35*Assumptions!$D$26 -> 1.1741406 | F36: =F35*Assumptions!$D$26 -> 2.8485458 | G36: =G35*Assumptions!$D$26 -> 5.4078067 | H36: =H35*Assumptions!$D$26 -> 9.0197423 | I36: =I35*Assumptions!$D$26 -> 13.673752 | J36: =J35*Assumptions!$D$26 -> 19.238175 | K36: =K35*Assumptions!$D$26 -> 25.627461 | ... U36: =U35*Assumptions!$D$26 -> 90.740391
A37: Weighted average bonus rate (annual, savings AUM) | B37: %/yr | D37: =IF(D11>0,SUM(D71:D88)/D11,0) -> 0 | E37: =IF(E11>0,SUM(E71:E88)/E11,0) -> 0 | F37: =IF(F11>0,SUM(F71:F88)/F11,0) -> 0 | G37: =IF(G11>0,SUM(G71:G88)/G11,0) -> 0.000325 | H37: =IF(H11>0,SUM(H71:H88)/H11,0) -> 0.00054016838 | I37: =IF(I11>0,SUM(I71:I88)/I11,0) -> 0.00070312315 | J37: =IF(J11>0,SUM(J71:J88)/J11,0) -> 0.00096881145 | K37: =IF(K11>0,SUM(K71:K88)/K11,0) -> 0.0010635301 | ... U37: =IF(U11>0,SUM(U71:U88)/U11,0) -> 0.001508751
A38: Bonus interest cost (paid on ALL Habitlock savings AUM) | B38: VND mn | C38: =SUM(D38:U38) -> 233.83508 | D38: =D25*(1-D22)*D37/12 -> 0 | E38: =E25*(1-E22)*E37/12 -> 0 | F38: =F25*(1-F22)*F37/12 -> 0 | G38: =G25*(1-G22)*G37/12 -> 0.50215348 | H38: =H25*(1-H22)*H37/12 -> 1.3552975 | I38: =I25*(1-I22)*I37/12 -> 2.6033205 | J38: =J25*(1-J22)*J37/12 -> 4.9115827 | K38: =K25*(1-K22)*K37/12 -> 6.9886095 | ... U38: =U25*(1-U22)*U37/12 -> 33.211371
A39: Acquisition spend | B39: VND mn | C39: =SUM(D39:U39) -> 21600 | D39: =D10*Assumptions!$D$16/Assumptions!$D$7 -> 450 | E39: =E10*Assumptions!$D$16/Assumptions!$D$7 -> 675 | F39: =F10*Assumptions!$D$16/Assumptions!$D$7 -> 900 | G39: =G10*Assumptions!$D$16/Assumptions!$D$7 -> 1125 | H39: =H10*Assumptions!$D$16/Assumptions!$D$7 -> 1350 | I39: =I10*Assumptions!$D$16/Assumptions!$D$7 -> 1575 | J39: =J10*Assumptions!$D$16/Assumptions!$D$7 -> 1575 | K39: =K10*Assumptions!$D$16/Assumptions!$D$7 -> 1575 | ... U39: =U10*Assumptions!$D$16/Assumptions!$D$7 -> 900
A40: Build cost | B40: VND mn | C40: =SUM(D40:U40) -> 1500 | D40: =IF(D4<=Assumptions!$D$40,Assumptions!$D$39/Assumptions!$D$40/Assumptions!$D$7,0) -> 500 | E40: =IF(E4<=Assumptions!$D$40,Assumptions!$D$39/Assumptions!$D$40/Assumptions!$D$7,0) -> 500 | F40: =IF(F4<=Assumptions!$D$40,Assumptions!$D$39/Assumptions!$D$40/Assumptions!$D$7,0) -> 500 | G40: =IF(G4<=Assumptions!$D$40,Assumptions!$D$39/Assumptions!$D$40/Assumptions!$D$7,0) -> 0 | H40: =IF(H4<=Assumptions!$D$40,Assumptions!$D$39/Assumptions!$D$40/Assumptions!$D$7,0) -> 0 | I40: =IF(I4<=Assumptions!$D$40,Assumptions!$D$39/Assumptions!$D$40/Assumptions!$D$7,0) -> 0 | J40: =IF(J4<=Assumptions!$D$40,Assumptions!$D$39/Assumptions!$D$40/Assumptions!$D$7,0) -> 0 | K40: =IF(K4<=Assumptions!$D$40,Assumptions!$D$39/Assumptions!$D$40/Assumptions!$D$7,0) -> 0 | ... U40: =IF(U4<=Assumptions!$D$40,Assumptions!$D$39/Assumptions!$D$40/Assumptions!$D$7,0) -> 0
A41: Run cost | B41: VND mn | C41: =SUM(D41:U41) -> 2160 | D41: =Assumptions!$D$41/Assumptions!$D$7 -> 120 | E41: =Assumptions!$D$41/Assumptions!$D$7 -> 120 | F41: =Assumptions!$D$41/Assumptions!$D$7 -> 120 | G41: =Assumptions!$D$41/Assumptions!$D$7 -> 120 | H41: =Assumptions!$D$41/Assumptions!$D$7 -> 120 | I41: =Assumptions!$D$41/Assumptions!$D$7 -> 120 | J41: =Assumptions!$D$41/Assumptions!$D$7 -> 120 | K41: =Assumptions!$D$41/Assumptions!$D$7 -> 120 | ... U41: =Assumptions!$D$41/Assumptions!$D$7 -> 120
A42: Net contribution | B42: VND mn | C42: =SUM(D42:U42) -> -24772.624 | D42: =D36-D38-D39-D40-D41 -> -1069.7266 | E42: =E36-E38-E39-E40-E41 -> -1293.8259 | F42: =F36-F38-F39-F40-F41 -> -1517.1515 | G42: =G36-G38-G39-G40-G41 -> -1240.0943 | H42: =H36-H38-H39-H40-H41 -> -1462.3356 | I42: =I36-I38-I39-I40-I41 -> -1683.9296 | J42: =J36-J38-J39-J40-J41 -> -1680.6734 | K42: =K36-K38-K39-K40-K41 -> -1676.3611 | ... U42: =U36-U38-U39-U40-U41 -> -962.47098
A43: Cumulative net contribution | B43: VND mn | D43: =D42 -> -1069.7266 | E43: =D43+E42 -> -2363.5524 | F43: =E43+F42 -> -3880.7039 | G43: =F43+G42 -> -5120.7982 | H43: =G43+H42 -> -6583.1338 | I43: =H43+I42 -> -8267.0633 | J43: =I43+J42 -> -9947.7368 | K43: =J43+K42 -> -11624.098 | L43: =K43+L42 -> -13295.568 | ... U43: =T43+U42 -> -24772.624
A44: Flag: cumulative net >= 0 | B44: flag | D44: =IF(D43>=0,1,0) -> 0 | E44: =IF(E43>=0,1,0) -> 0 | F44: =IF(F43>=0,1,0) -> 0 | G44: =IF(G43>=0,1,0) -> 0 | H44: =IF(H43>=0,1,0) -> 0 | I44: =IF(I43>=0,1,0) -> 0 | J44: =IF(J43>=0,1,0) -> 0 | K44: =IF(K43>=0,1,0) -> 0 | ... U44: =IF(U43>=0,1,0) -> 0
A45: Flag: monthly net >= 0 | B45: flag | D45: =IF(D42>=0,1,0) -> 0 | E45: =IF(E42>=0,1,0) -> 0 | F45: =IF(F42>=0,1,0) -> 0 | G45: =IF(G42>=0,1,0) -> 0 | H45: =IF(H42>=0,1,0) -> 0 | I45: =IF(I42>=0,1,0) -> 0 | J45: =IF(J42>=0,1,0) -> 0 | K45: =IF(K42>=0,1,0) -> 0 | ... U45: =IF(U42>=0,1,0) -> 0
A47: Cohort matrix: active users by acquisition cohort (rows) and month (columns)
A48: Cohort | B48: Cohort # | D48: M1 | E48: M2 | F48: M3 | G48: M4 | H48: M5 | I48: M6 | J48: M7 | K48: M8 | L48: M9 | M48: M10 | N48: M11 | O48: M12 | P48: M13 | Q48: M14 | R48: M15 | S48: M16 | T48: M17 | U48: M18
A49: Cohort M1 | B49: 1 | D49: =IF(D$4<$B49,0,INDEX($D$10:$U$10,$B49)*(1-Assumptions!$D$18)^(D$4-$B49)) -> 3750 | E49: =IF(E$4<$B49,0,INDEX($D$10:$U$10,$B49)*(1-Assumptions!$D$18)^(E$4-$B49)) -> 3450 | F49: =IF(F$4<$B49,0,INDEX($D$10:$U$10,$B49)*(1-Assumptions!$D$18)^(F$4-$B49)) -> 3174 | G49: =IF(G$4<$B49,0,INDEX($D$10:$U$10,$B49)*(1-Assumptions!$D$18)^(G$4-$B49)) -> 2920.08 | H49: =IF(H$4<$B49,0,INDEX($D$10:$U$10,$B49)*(1-Assumptions!$D$18)^(H$4-$B49)) -> 2686.4736 | I49: =IF(I$4<$B49,0,INDEX($D$10:$U$10,$B49)*(1-Assumptions!$D$18)^(I$4-$B49)) -> 2471.5557 | J49: =IF(J$4<$B49,0,INDEX($D$10:$U$10,$B49)*(1-Assumptions!$D$18)^(J$4-$B49)) -> 2273.8313 | K49: =IF(K$4<$B49,0,INDEX($D$10:$U$10,$B49)*(1-Assumptions!$D$18)^(K$4-$B49)) -> 2091.9248 | ... U49: =IF(U$4<$B49,0,INDEX($D$10:$U$10,$B49)*(1-Assumptions!$D$18)^(U$4-$B49)) -> 908.70796
A50: Cohort M2 | B50: 2 | D50: =IF(D$4<$B50,0,INDEX($D$10:$U$10,$B50)*(1-Assumptions!$D$18)^(D$4-$B50)) -> 0 | E50: =IF(E$4<$B50,0,INDEX($D$10:$U$10,$B50)*(1-Assumptions!$D$18)^(E$4-$B50)) -> 5625 | F50: =IF(F$4<$B50,0,INDEX($D$10:$U$10,$B50)*(1-Assumptions!$D$18)^(F$4-$B50)) -> 5175 | G50: =IF(G$4<$B50,0,INDEX($D$10:$U$10,$B50)*(1-Assumptions!$D$18)^(G$4-$B50)) -> 4761 | H50: =IF(H$4<$B50,0,INDEX($D$10:$U$10,$B50)*(1-Assumptions!$D$18)^(H$4-$B50)) -> 4380.12 | I50: =IF(I$4<$B50,0,INDEX($D$10:$U$10,$B50)*(1-Assumptions!$D$18)^(I$4-$B50)) -> 4029.7104 | J50: =IF(J$4<$B50,0,INDEX($D$10:$U$10,$B50)*(1-Assumptions!$D$18)^(J$4-$B50)) -> 3707.3336 | K50: =IF(K$4<$B50,0,INDEX($D$10:$U$10,$B50)*(1-Assumptions!$D$18)^(K$4-$B50)) -> 3410.7469 | ... U50: =IF(U$4<$B50,0,INDEX($D$10:$U$10,$B50)*(1-Assumptions!$D$18)^(U$4-$B50)) -> 1481.5891
A51: Cohort M3 | B51: 3 | D51: =IF(D$4<$B51,0,INDEX($D$10:$U$10,$B51)*(1-Assumptions!$D$18)^(D$4-$B51)) -> 0 | E51: =IF(E$4<$B51,0,INDEX($D$10:$U$10,$B51)*(1-Assumptions!$D$18)^(E$4-$B51)) -> 0 | F51: =IF(F$4<$B51,0,INDEX($D$10:$U$10,$B51)*(1-Assumptions!$D$18)^(F$4-$B51)) -> 7500 | G51: =IF(G$4<$B51,0,INDEX($D$10:$U$10,$B51)*(1-Assumptions!$D$18)^(G$4-$B51)) -> 6900 | H51: =IF(H$4<$B51,0,INDEX($D$10:$U$10,$B51)*(1-Assumptions!$D$18)^(H$4-$B51)) -> 6348 | I51: =IF(I$4<$B51,0,INDEX($D$10:$U$10,$B51)*(1-Assumptions!$D$18)^(I$4-$B51)) -> 5840.16 | J51: =IF(J$4<$B51,0,INDEX($D$10:$U$10,$B51)*(1-Assumptions!$D$18)^(J$4-$B51)) -> 5372.9472 | K51: =IF(K$4<$B51,0,INDEX($D$10:$U$10,$B51)*(1-Assumptions!$D$18)^(K$4-$B51)) -> 4943.1114 | ... U51: =IF(U$4<$B51,0,INDEX($D$10:$U$10,$B51)*(1-Assumptions!$D$18)^(U$4-$B51)) -> 2147.2305
A52: Cohort M4 | B52: 4 | D52: =IF(D$4<$B52,0,INDEX($D$10:$U$10,$B52)*(1-Assumptions!$D$18)^(D$4-$B52)) -> 0 | E52: =IF(E$4<$B52,0,INDEX($D$10:$U$10,$B52)*(1-Assumptions!$D$18)^(E$4-$B52)) -> 0 | F52: =IF(F$4<$B52,0,INDEX($D$10:$U$10,$B52)*(1-Assumptions!$D$18)^(F$4-$B52)) -> 0 | G52: =IF(G$4<$B52,0,INDEX($D$10:$U$10,$B52)*(1-Assumptions!$D$18)^(G$4-$B52)) -> 9375 | H52: =IF(H$4<$B52,0,INDEX($D$10:$U$10,$B52)*(1-Assumptions!$D$18)^(H$4-$B52)) -> 8625 | I52: =IF(I$4<$B52,0,INDEX($D$10:$U$10,$B52)*(1-Assumptions!$D$18)^(I$4-$B52)) -> 7935 | J52: =IF(J$4<$B52,0,INDEX($D$10:$U$10,$B52)*(1-Assumptions!$D$18)^(J$4-$B52)) -> 7300.2 | K52: =IF(K$4<$B52,0,INDEX($D$10:$U$10,$B52)*(1-Assumptions!$D$18)^(K$4-$B52)) -> 6716.184 | ... U52: =IF(U$4<$B52,0,INDEX($D$10:$U$10,$B52)*(1-Assumptions!$D$18)^(U$4-$B52)) -> 2917.4328
A53: Cohort M5 | B53: 5 | D53: =IF(D$4<$B53,0,INDEX($D$10:$U$10,$B53)*(1-Assumptions!$D$18)^(D$4-$B53)) -> 0 | E53: =IF(E$4<$B53,0,INDEX($D$10:$U$10,$B53)*(1-Assumptions!$D$18)^(E$4-$B53)) -> 0 | F53: =IF(F$4<$B53,0,INDEX($D$10:$U$10,$B53)*(1-Assumptions!$D$18)^(F$4-$B53)) -> 0 | G53: =IF(G$4<$B53,0,INDEX($D$10:$U$10,$B53)*(1-Assumptions!$D$18)^(G$4-$B53)) -> 0 | H53: =IF(H$4<$B53,0,INDEX($D$10:$U$10,$B53)*(1-Assumptions!$D$18)^(H$4-$B53)) -> 11250 | I53: =IF(I$4<$B53,0,INDEX($D$10:$U$10,$B53)*(1-Assumptions!$D$18)^(I$4-$B53)) -> 10350 | J53: =IF(J$4<$B53,0,INDEX($D$10:$U$10,$B53)*(1-Assumptions!$D$18)^(J$4-$B53)) -> 9522 | K53: =IF(K$4<$B53,0,INDEX($D$10:$U$10,$B53)*(1-Assumptions!$D$18)^(K$4-$B53)) -> 8760.24 | ... U53: =IF(U$4<$B53,0,INDEX($D$10:$U$10,$B53)*(1-Assumptions!$D$18)^(U$4-$B53)) -> 3805.3471
A54: Cohort M6 | B54: 6 | D54: =IF(D$4<$B54,0,INDEX($D$10:$U$10,$B54)*(1-Assumptions!$D$18)^(D$4-$B54)) -> 0 | E54: =IF(E$4<$B54,0,INDEX($D$10:$U$10,$B54)*(1-Assumptions!$D$18)^(E$4-$B54)) -> 0 | F54: =IF(F$4<$B54,0,INDEX($D$10:$U$10,$B54)*(1-Assumptions!$D$18)^(F$4-$B54)) -> 0 | G54: =IF(G$4<$B54,0,INDEX($D$10:$U$10,$B54)*(1-Assumptions!$D$18)^(G$4-$B54)) -> 0 | H54: =IF(H$4<$B54,0,INDEX($D$10:$U$10,$B54)*(1-Assumptions!$D$18)^(H$4-$B54)) -> 0 | I54: =IF(I$4<$B54,0,INDEX($D$10:$U$10,$B54)*(1-Assumptions!$D$18)^(I$4-$B54)) -> 13125 | J54: =IF(J$4<$B54,0,INDEX($D$10:$U$10,$B54)*(1-Assumptions!$D$18)^(J$4-$B54)) -> 12075 | K54: =IF(K$4<$B54,0,INDEX($D$10:$U$10,$B54)*(1-Assumptions!$D$18)^(K$4-$B54)) -> 11109 | ... U54: =IF(U$4<$B54,0,INDEX($D$10:$U$10,$B54)*(1-Assumptions!$D$18)^(U$4-$B54)) -> 4825.6213
A55: Cohort M7 | B55: 7 | D55: =IF(D$4<$B55,0,INDEX($D$10:$U$10,$B55)*(1-Assumptions!$D$18)^(D$4-$B55)) -> 0 | E55: =IF(E$4<$B55,0,INDEX($D$10:$U$10,$B55)*(1-Assumptions!$D$18)^(E$4-$B55)) -> 0 | F55: =IF(F$4<$B55,0,INDEX($D$10:$U$10,$B55)*(1-Assumptions!$D$18)^(F$4-$B55)) -> 0 | G55: =IF(G$4<$B55,0,INDEX($D$10:$U$10,$B55)*(1-Assumptions!$D$18)^(G$4-$B55)) -> 0 | H55: =IF(H$4<$B55,0,INDEX($D$10:$U$10,$B55)*(1-Assumptions!$D$18)^(H$4-$B55)) -> 0 | I55: =IF(I$4<$B55,0,INDEX($D$10:$U$10,$B55)*(1-Assumptions!$D$18)^(I$4-$B55)) -> 0 | J55: =IF(J$4<$B55,0,INDEX($D$10:$U$10,$B55)*(1-Assumptions!$D$18)^(J$4-$B55)) -> 13125 | K55: =IF(K$4<$B55,0,INDEX($D$10:$U$10,$B55)*(1-Assumptions!$D$18)^(K$4-$B55)) -> 12075 | ... U55: =IF(U$4<$B55,0,INDEX($D$10:$U$10,$B55)*(1-Assumptions!$D$18)^(U$4-$B55)) -> 5245.2406
A56: Cohort M8 | B56: 8 | D56: =IF(D$4<$B56,0,INDEX($D$10:$U$10,$B56)*(1-Assumptions!$D$18)^(D$4-$B56)) -> 0 | E56: =IF(E$4<$B56,0,INDEX($D$10:$U$10,$B56)*(1-Assumptions!$D$18)^(E$4-$B56)) -> 0 | F56: =IF(F$4<$B56,0,INDEX($D$10:$U$10,$B56)*(1-Assumptions!$D$18)^(F$4-$B56)) -> 0 | G56: =IF(G$4<$B56,0,INDEX($D$10:$U$10,$B56)*(1-Assumptions!$D$18)^(G$4-$B56)) -> 0 | H56: =IF(H$4<$B56,0,INDEX($D$10:$U$10,$B56)*(1-Assumptions!$D$18)^(H$4-$B56)) -> 0 | I56: =IF(I$4<$B56,0,INDEX($D$10:$U$10,$B56)*(1-Assumptions!$D$18)^(I$4-$B56)) -> 0 | J56: =IF(J$4<$B56,0,INDEX($D$10:$U$10,$B56)*(1-Assumptions!$D$18)^(J$4-$B56)) -> 0 | K56: =IF(K$4<$B56,0,INDEX($D$10:$U$10,$B56)*(1-Assumptions!$D$18)^(K$4-$B56)) -> 13125 | ... U56: =IF(U$4<$B56,0,INDEX($D$10:$U$10,$B56)*(1-Assumptions!$D$18)^(U$4-$B56)) -> 5701.3485
A57: Cohort M9 | B57: 9 | D57: =IF(D$4<$B57,0,INDEX($D$10:$U$10,$B57)*(1-Assumptions!$D$18)^(D$4-$B57)) -> 0 | E57: =IF(E$4<$B57,0,INDEX($D$10:$U$10,$B57)*(1-Assumptions!$D$18)^(E$4-$B57)) -> 0 | F57: =IF(F$4<$B57,0,INDEX($D$10:$U$10,$B57)*(1-Assumptions!$D$18)^(F$4-$B57)) -> 0 | G57: =IF(G$4<$B57,0,INDEX($D$10:$U$10,$B57)*(1-Assumptions!$D$18)^(G$4-$B57)) -> 0 | H57: =IF(H$4<$B57,0,INDEX($D$10:$U$10,$B57)*(1-Assumptions!$D$18)^(H$4-$B57)) -> 0 | I57: =IF(I$4<$B57,0,INDEX($D$10:$U$10,$B57)*(1-Assumptions!$D$18)^(I$4-$B57)) -> 0 | J57: =IF(J$4<$B57,0,INDEX($D$10:$U$10,$B57)*(1-Assumptions!$D$18)^(J$4-$B57)) -> 0 | K57: =IF(K$4<$B57,0,INDEX($D$10:$U$10,$B57)*(1-Assumptions!$D$18)^(K$4-$B57)) -> 0 | ... U57: =IF(U$4<$B57,0,INDEX($D$10:$U$10,$B57)*(1-Assumptions!$D$18)^(U$4-$B57)) -> 6197.1179
A58: Cohort M10 | B58: 10 | D58: =IF(D$4<$B58,0,INDEX($D$10:$U$10,$B58)*(1-Assumptions!$D$18)^(D$4-$B58)) -> 0 | E58: =IF(E$4<$B58,0,INDEX($D$10:$U$10,$B58)*(1-Assumptions!$D$18)^(E$4-$B58)) -> 0 | F58: =IF(F$4<$B58,0,INDEX($D$10:$U$10,$B58)*(1-Assumptions!$D$18)^(F$4-$B58)) -> 0 | G58: =IF(G$4<$B58,0,INDEX($D$10:$U$10,$B58)*(1-Assumptions!$D$18)^(G$4-$B58)) -> 0 | H58: =IF(H$4<$B58,0,INDEX($D$10:$U$10,$B58)*(1-Assumptions!$D$18)^(H$4-$B58)) -> 0 | I58: =IF(I$4<$B58,0,INDEX($D$10:$U$10,$B58)*(1-Assumptions!$D$18)^(I$4-$B58)) -> 0 | J58: =IF(J$4<$B58,0,INDEX($D$10:$U$10,$B58)*(1-Assumptions!$D$18)^(J$4-$B58)) -> 0 | K58: =IF(K$4<$B58,0,INDEX($D$10:$U$10,$B58)*(1-Assumptions!$D$18)^(K$4-$B58)) -> 0 | ... U58: =IF(U$4<$B58,0,INDEX($D$10:$U$10,$B58)*(1-Assumptions!$D$18)^(U$4-$B58)) -> 6735.9977
A59: Cohort M11 | B59: 11 | D59: =IF(D$4<$B59,0,INDEX($D$10:$U$10,$B59)*(1-Assumptions!$D$18)^(D$4-$B59)) -> 0 | E59: =IF(E$4<$B59,0,INDEX($D$10:$U$10,$B59)*(1-Assumptions!$D$18)^(E$4-$B59)) -> 0 | F59: =IF(F$4<$B59,0,INDEX($D$10:$U$10,$B59)*(1-Assumptions!$D$18)^(F$4-$B59)) -> 0 | G59: =IF(G$4<$B59,0,INDEX($D$10:$U$10,$B59)*(1-Assumptions!$D$18)^(G$4-$B59)) -> 0 | H59: =IF(H$4<$B59,0,INDEX($D$10:$U$10,$B59)*(1-Assumptions!$D$18)^(H$4-$B59)) -> 0 | I59: =IF(I$4<$B59,0,INDEX($D$10:$U$10,$B59)*(1-Assumptions!$D$18)^(I$4-$B59)) -> 0 | J59: =IF(J$4<$B59,0,INDEX($D$10:$U$10,$B59)*(1-Assumptions!$D$18)^(J$4-$B59)) -> 0 | K59: =IF(K$4<$B59,0,INDEX($D$10:$U$10,$B59)*(1-Assumptions!$D$18)^(K$4-$B59)) -> 0 | ... U59: =IF(U$4<$B59,0,INDEX($D$10:$U$10,$B59)*(1-Assumptions!$D$18)^(U$4-$B59)) -> 6275.7743
A60: Cohort M12 | B60: 12 | D60: =IF(D$4<$B60,0,INDEX($D$10:$U$10,$B60)*(1-Assumptions!$D$18)^(D$4-$B60)) -> 0 | E60: =IF(E$4<$B60,0,INDEX($D$10:$U$10,$B60)*(1-Assumptions!$D$18)^(E$4-$B60)) -> 0 | F60: =IF(F$4<$B60,0,INDEX($D$10:$U$10,$B60)*(1-Assumptions!$D$18)^(F$4-$B60)) -> 0 | G60: =IF(G$4<$B60,0,INDEX($D$10:$U$10,$B60)*(1-Assumptions!$D$18)^(G$4-$B60)) -> 0 | H60: =IF(H$4<$B60,0,INDEX($D$10:$U$10,$B60)*(1-Assumptions!$D$18)^(H$4-$B60)) -> 0 | I60: =IF(I$4<$B60,0,INDEX($D$10:$U$10,$B60)*(1-Assumptions!$D$18)^(I$4-$B60)) -> 0 | J60: =IF(J$4<$B60,0,INDEX($D$10:$U$10,$B60)*(1-Assumptions!$D$18)^(J$4-$B60)) -> 0 | K60: =IF(K$4<$B60,0,INDEX($D$10:$U$10,$B60)*(1-Assumptions!$D$18)^(K$4-$B60)) -> 0 | ... U60: =IF(U$4<$B60,0,INDEX($D$10:$U$10,$B60)*(1-Assumptions!$D$18)^(U$4-$B60)) -> 6821.4938
... A66: Cohort M18 | B66: 18 | D66: =IF(D$4<$B66,0,INDEX($D$10:$U$10,$B66)*(1-Assumptions!$D$18)^(D$4-$B66)) -> 0 | E66: =IF(E$4<$B66,0,INDEX($D$10:$U$10,$B66)*(1-Assumptions!$D$18)^(E$4-$B66)) -> 0 | F66: =IF(F$4<$B66,0,INDEX($D$10:$U$10,$B66)*(1-Assumptions!$D$18)^(F$4-$B66)) -> 0 | G66: =IF(G$4<$B66,0,INDEX($D$10:$U$10,$B66)*(1-Assumptions!$D$18)^(G$4-$B66)) -> 0 | H66: =IF(H$4<$B66,0,INDEX($D$10:$U$10,$B66)*(1-Assumptions!$D$18)^(H$4-$B66)) -> 0 | I66: =IF(I$4<$B66,0,INDEX($D$10:$U$10,$B66)*(1-Assumptions!$D$18)^(I$4-$B66)) -> 0 | J66: =IF(J$4<$B66,0,INDEX($D$10:$U$10,$B66)*(1-Assumptions!$D$18)^(J$4-$B66)) -> 0 | K66: =IF(K$4<$B66,0,INDEX($D$10:$U$10,$B66)*(1-Assumptions!$D$18)^(K$4-$B66)) -> 0 | ... U66: =IF(U$4<$B66,0,INDEX($D$10:$U$10,$B66)*(1-Assumptions!$D$18)^(U$4-$B66)) -> 7500
A69: Cohort matrix: active users x bonus rate (feeds weighted average bonus rate)
A70: Cohort | B70: Cohort # | D70: M1 | E70: M2 | F70: M3 | G70: M4 | H70: M5 | I70: M6 | J70: M7 | K70: M8 | L70: M9 | M70: M10 | N70: M11 | O70: M12 | P70: M13 | Q70: M14 | R70: M15 | S70: M16 | T70: M17 | U70: M18
A71: Cohort M1 | B71: 1 | D71: =IF(OR(D$4<Assumptions!$D$32,D$4<$B71),0,D49*IF(D$4>=Assumptions!$D$33,INDEX($D$94:$D$111,D$4-MAX($B71,Assumptions!$D$32)+1),INDEX($C$94:$C$111,D$4-MAX($B71,Assumptions!$D$32)+1))) -> 0 | E71: =IF(OR(E$4<Assumptions!$D$32,E$4<$B71),0,E49*IF(E$4>=Assumptions!$D$33,INDEX($D$94:$D$111,E$4-MAX($B71,Assumptions!$D$32)+1),INDEX($C$94:$C$111,E$4-MAX($B71,Assumptions!$D$32)+1))) -> 0 | F71: =IF(OR(F$4<Assumptions!$D$32,F$4<$B71),0,F49*IF(F$4>=Assumptions!$D$33,INDEX($D$94:$D$111,F$4-MAX($B71,Assumptions!$D$32)+1),INDEX($C$94:$C$111,F$4-MAX($B71,Assumptions!$D$32)+1))) -> 0 | G71: =IF(OR(G$4<Assumptions!$D$32,G$4<$B71),0,G49*IF(G$4>=Assumptions!$D$33,INDEX($D$94:$D$111,G$4-MAX($B71,Assumptions!$D$32)+1),INDEX($C$94:$C$111,G$4-MAX($B71,Assumptions!$D$32)+1))) -> 0.949026 | H71: =IF(OR(H$4<Assumptions!$D$32,H$4<$B71),0,H49*IF(H$4>=Assumptions!$D$33,INDEX($D$94:$D$111,H$4-MAX($B71,Assumptions!$D$32)+1),INDEX($C$94:$C$111,H$4-MAX($B71,Assumptions!$D$32)+1))) -> 1.7462078 | I71: =IF(OR(I$4<Assumptions!$D$32,I$4<$B71),0,I49*IF(I$4>=Assumptions!$D$33,INDEX($D$94:$D$111,I$4-MAX($B71,Assumptions!$D$32)+1),INDEX($C$94:$C$111,I$4-MAX($B71,Assumptions!$D$32)+1))) -> 2.4097668 | J71: =IF(OR(J$4<Assumptions!$D$32,J$4<$B71),0,J49*IF(J$4>=Assumptions!$D$33,INDEX($D$94:$D$111,J$4-MAX($B71,Assumptions!$D$32)+1),INDEX($C$94:$C$111,J$4-MAX($B71,Assumptions!$D$32)+1))) -> 3.6949758 | K71: =IF(OR(K$4<Assumptions!$D$32,K$4<$B71),0,K49*IF(K$4>=Assumptions!$D$33,INDEX($D$94:$D$111,K$4-MAX($B71,Assumptions!$D$32)+1),INDEX($C$94:$C$111,K$4-MAX($B71,Assumptions!$D$32)+1))) -> 3.5353528 | ... U71: =IF(OR(U$4<Assumptions!$D$32,U$4<$B71),0,U49*IF(U$4>=Assumptions!$D$33,INDEX($D$94:$D$111,U$4-MAX($B71,Assumptions!$D$32)+1),INDEX($C$94:$C$111,U$4-MAX($B71,Assumptions!$D$32)+1))) -> 1.6538485
A72: Cohort M2 | B72: 2 | D72: =IF(OR(D$4<Assumptions!$D$32,D$4<$B72),0,D50*IF(D$4>=Assumptions!$D$33,INDEX($D$94:$D$111,D$4-MAX($B72,Assumptions!$D$32)+1),INDEX($C$94:$C$111,D$4-MAX($B72,Assumptions!$D$32)+1))) -> 0 | E72: =IF(OR(E$4<Assumptions!$D$32,E$4<$B72),0,E50*IF(E$4>=Assumptions!$D$33,INDEX($D$94:$D$111,E$4-MAX($B72,Assumptions!$D$32)+1),INDEX($C$94:$C$111,E$4-MAX($B72,Assumptions!$D$32)+1))) -> 0 | F72: =IF(OR(F$4<Assumptions!$D$32,F$4<$B72),0,F50*IF(F$4>=Assumptions!$D$33,INDEX($D$94:$D$111,F$4-MAX($B72,Assumptions!$D$32)+1),INDEX($C$94:$C$111,F$4-MAX($B72,Assumptions!$D$32)+1))) -> 0 | G72: =IF(OR(G$4<Assumptions!$D$32,G$4<$B72),0,G50*IF(G$4>=Assumptions!$D$33,INDEX($D$94:$D$111,G$4-MAX($B72,Assumptions!$D$32)+1),INDEX($C$94:$C$111,G$4-MAX($B72,Assumptions!$D$32)+1))) -> 1.547325 | H72: =IF(OR(H$4<Assumptions!$D$32,H$4<$B72),0,H50*IF(H$4>=Assumptions!$D$33,INDEX($D$94:$D$111,H$4-MAX($B72,Assumptions!$D$32)+1),INDEX($C$94:$C$111,H$4-MAX($B72,Assumptions!$D$32)+1))) -> 2.847078 | I72: =IF(OR(I$4<Assumptions!$D$32,I$4<$B72),0,I50*IF(I$4>=Assumptions!$D$33,INDEX($D$94:$D$111,I$4-MAX($B72,Assumptions!$D$32)+1),INDEX($C$94:$C$111,I$4-MAX($B72,Assumptions!$D$32)+1))) -> 3.9289676 | J72: =IF(OR(J$4<Assumptions!$D$32,J$4<$B72),0,J50*IF(J$4>=Assumptions!$D$33,INDEX($D$94:$D$111,J$4-MAX($B72,Assumptions!$D$32)+1),INDEX($C$94:$C$111,J$4-MAX($B72,Assumptions!$D$32)+1))) -> 6.024417 | K72: =IF(OR(K$4<Assumptions!$D$32,K$4<$B72),0,K50*IF(K$4>=Assumptions!$D$33,INDEX($D$94:$D$111,K$4-MAX($B72,Assumptions!$D$32)+1),INDEX($C$94:$C$111,K$4-MAX($B72,Assumptions!$D$32)+1))) -> 5.7641622 | ... U72: =IF(OR(U$4<Assumptions!$D$32,U$4<$B72),0,U50*IF(U$4>=Assumptions!$D$33,INDEX($D$94:$D$111,U$4-MAX($B72,Assumptions!$D$32)+1),INDEX($C$94:$C$111,U$4-MAX($B72,Assumptions!$D$32)+1))) -> 2.6964921
A73: Cohort M3 | B73: 3 | D73: =IF(OR(D$4<Assumptions!$D$32,D$4<$B73),0,D51*IF(D$4>=Assumptions!$D$33,INDEX($D$94:$D$111,D$4-MAX($B73,Assumptions!$D$32)+1),INDEX($C$94:$C$111,D$4-MAX($B73,Assumptions!$D$32)+1))) -> 0 | E73: =IF(OR(E$4<Assumptions!$D$32,E$4<$B73),0,E51*IF(E$4>=Assumptions!$D$33,INDEX($D$94:$D$111,E$4-MAX($B73,Assumptions!$D$32)+1),INDEX($C$94:$C$111,E$4-MAX($B73,Assumptions!$D$32)+1))) -> 0 | F73: =IF(OR(F$4<Assumptions!$D$32,F$4<$B73),0,F51*IF(F$4>=Assumptions!$D$33,INDEX($D$94:$D$111,F$4-MAX($B73,Assumptions!$D$32)+1),INDEX($C$94:$C$111,F$4-MAX($B73,Assumptions!$D$32)+1))) -> 0 | G73: =IF(OR(G$4<Assumptions!$D$32,G$4<$B73),0,G51*IF(G$4>=Assumptions!$D$33,INDEX($D$94:$D$111,G$4-MAX($B73,Assumptions!$D$32)+1),INDEX($C$94:$C$111,G$4-MAX($B73,Assumptions!$D$32)+1))) -> 2.2425 | H73: =IF(OR(H$4<Assumptions!$D$32,H$4<$B73),0,H51*IF(H$4>=Assumptions!$D$33,INDEX($D$94:$D$111,H$4-MAX($B73,Assumptions!$D$32)+1),INDEX($C$94:$C$111,H$4-MAX($B73,Assumptions!$D$32)+1))) -> 4.1262 | I73: =IF(OR(I$4<Assumptions!$D$32,I$4<$B73),0,I51*IF(I$4>=Assumptions!$D$33,INDEX($D$94:$D$111,I$4-MAX($B73,Assumptions!$D$32)+1),INDEX($C$94:$C$111,I$4-MAX($B73,Assumptions!$D$32)+1))) -> 5.694156 | J73: =IF(OR(J$4<Assumptions!$D$32,J$4<$B73),0,J51*IF(J$4>=Assumptions!$D$33,INDEX($D$94:$D$111,J$4-MAX($B73,Assumptions!$D$32)+1),INDEX($C$94:$C$111,J$4-MAX($B73,Assumptions!$D$32)+1))) -> 8.7310392 | K73: =IF(OR(K$4<Assumptions!$D$32,K$4<$B73),0,K51*IF(K$4>=Assumptions!$D$33,INDEX($D$94:$D$111,K$4-MAX($B73,Assumptions!$D$32)+1),INDEX($C$94:$C$111,K$4-MAX($B73,Assumptions!$D$32)+1))) -> 8.3538583 | ... U73: =IF(OR(U$4<Assumptions!$D$32,U$4<$B73),0,U51*IF(U$4>=Assumptions!$D$33,INDEX($D$94:$D$111,U$4-MAX($B73,Assumptions!$D$32)+1),INDEX($C$94:$C$111,U$4-MAX($B73,Assumptions!$D$32)+1))) -> 3.9079596
A74: Cohort M4 | B74: 4 | D74: =IF(OR(D$4<Assumptions!$D$32,D$4<$B74),0,D52*IF(D$4>=Assumptions!$D$33,INDEX($D$94:$D$111,D$4-MAX($B74,Assumptions!$D$32)+1),INDEX($C$94:$C$111,D$4-MAX($B74,Assumptions!$D$32)+1))) -> 0 | E74: =IF(OR(E$4<Assumptions!$D$32,E$4<$B74),0,E52*IF(E$4>=Assumptions!$D$33,INDEX($D$94:$D$111,E$4-MAX($B74,Assumptions!$D$32)+1),INDEX($C$94:$C$111,E$4-MAX($B74,Assumptions!$D$32)+1))) -> 0 | F74: =IF(OR(F$4<Assumptions!$D$32,F$4<$B74),0,F52*IF(F$4>=Assumptions!$D$33,INDEX($D$94:$D$111,F$4-MAX($B74,Assumptions!$D$32)+1),INDEX($C$94:$C$111,F$4-MAX($B74,Assumptions!$D$32)+1))) -> 0 | G74: =IF(OR(G$4<Assumptions!$D$32,G$4<$B74),0,G52*IF(G$4>=Assumptions!$D$33,INDEX($D$94:$D$111,G$4-MAX($B74,Assumptions!$D$32)+1),INDEX($C$94:$C$111,G$4-MAX($B74,Assumptions!$D$32)+1))) -> 3.046875 | H74: =IF(OR(H$4<Assumptions!$D$32,H$4<$B74),0,H52*IF(H$4>=Assumptions!$D$33,INDEX($D$94:$D$111,H$4-MAX($B74,Assumptions!$D$32)+1),INDEX($C$94:$C$111,H$4-MAX($B74,Assumptions!$D$32)+1))) -> 5.60625 | I74: =IF(OR(I$4<Assumptions!$D$32,I$4<$B74),0,I52*IF(I$4>=Assumptions!$D$33,INDEX($D$94:$D$111,I$4-MAX($B74,Assumptions!$D$32)+1),INDEX($C$94:$C$111,I$4-MAX($B74,Assumptions!$D$32)+1))) -> 7.736625 | J74: =IF(OR(J$4<Assumptions!$D$32,J$4<$B74),0,J52*IF(J$4>=Assumptions!$D$33,INDEX($D$94:$D$111,J$4-MAX($B74,Assumptions!$D$32)+1),INDEX($C$94:$C$111,J$4-MAX($B74,Assumptions!$D$32)+1))) -> 11.862825 | K74: =IF(OR(K$4<Assumptions!$D$32,K$4<$B74),0,K52*IF(K$4>=Assumptions!$D$33,INDEX($D$94:$D$111,K$4-MAX($B74,Assumptions!$D$32)+1),INDEX($C$94:$C$111,K$4-MAX($B74,Assumptions!$D$32)+1))) -> 11.350351 | ... U74: =IF(OR(U$4<Assumptions!$D$32,U$4<$B74),0,U52*IF(U$4>=Assumptions!$D$33,INDEX($D$94:$D$111,U$4-MAX($B74,Assumptions!$D$32)+1),INDEX($C$94:$C$111,U$4-MAX($B74,Assumptions!$D$32)+1))) -> 5.3097277
A75: Cohort M5 | B75: 5 | D75: =IF(OR(D$4<Assumptions!$D$32,D$4<$B75),0,D53*IF(D$4>=Assumptions!$D$33,INDEX($D$94:$D$111,D$4-MAX($B75,Assumptions!$D$32)+1),INDEX($C$94:$C$111,D$4-MAX($B75,Assumptions!$D$32)+1))) -> 0 | E75: =IF(OR(E$4<Assumptions!$D$32,E$4<$B75),0,E53*IF(E$4>=Assumptions!$D$33,INDEX($D$94:$D$111,E$4-MAX($B75,Assumptions!$D$32)+1),INDEX($C$94:$C$111,E$4-MAX($B75,Assumptions!$D$32)+1))) -> 0 | F75: =IF(OR(F$4<Assumptions!$D$32,F$4<$B75),0,F53*IF(F$4>=Assumptions!$D$33,INDEX($D$94:$D$111,F$4-MAX($B75,Assumptions!$D$32)+1),INDEX($C$94:$C$111,F$4-MAX($B75,Assumptions!$D$32)+1))) -> 0 | G75: =IF(OR(G$4<Assumptions!$D$32,G$4<$B75),0,G53*IF(G$4>=Assumptions!$D$33,INDEX($D$94:$D$111,G$4-MAX($B75,Assumptions!$D$32)+1),INDEX($C$94:$C$111,G$4-MAX($B75,Assumptions!$D$32)+1))) -> 0 | H75: =IF(OR(H$4<Assumptions!$D$32,H$4<$B75),0,H53*IF(H$4>=Assumptions!$D$33,INDEX($D$94:$D$111,H$4-MAX($B75,Assumptions!$D$32)+1),INDEX($C$94:$C$111,H$4-MAX($B75,Assumptions!$D$32)+1))) -> 3.65625 | I75: =IF(OR(I$4<Assumptions!$D$32,I$4<$B75),0,I53*IF(I$4>=Assumptions!$D$33,INDEX($D$94:$D$111,I$4-MAX($B75,Assumptions!$D$32)+1),INDEX($C$94:$C$111,I$4-MAX($B75,Assumptions!$D$32)+1))) -> 6.7275 | J75: =IF(OR(J$4<Assumptions!$D$32,J$4<$B75),0,J53*IF(J$4>=Assumptions!$D$33,INDEX($D$94:$D$111,J$4-MAX($B75,Assumptions!$D$32)+1),INDEX($C$94:$C$111,J$4-MAX($B75,Assumptions!$D$32)+1))) -> 9.28395 | K75: =IF(OR(K$4<Assumptions!$D$32,K$4<$B75),0,K53*IF(K$4>=Assumptions!$D$33,INDEX($D$94:$D$111,K$4-MAX($B75,Assumptions!$D$32)+1),INDEX($C$94:$C$111,K$4-MAX($B75,Assumptions!$D$32)+1))) -> 14.23539 | ... U75: =IF(OR(U$4<Assumptions!$D$32,U$4<$B75),0,U53*IF(U$4>=Assumptions!$D$33,INDEX($D$94:$D$111,U$4-MAX($B75,Assumptions!$D$32)+1),INDEX($C$94:$C$111,U$4-MAX($B75,Assumptions!$D$32)+1))) -> 6.9257317
A76: Cohort M6 | B76: 6 | D76: =IF(OR(D$4<Assumptions!$D$32,D$4<$B76),0,D54*IF(D$4>=Assumptions!$D$33,INDEX($D$94:$D$111,D$4-MAX($B76,Assumptions!$D$32)+1),INDEX($C$94:$C$111,D$4-MAX($B76,Assumptions!$D$32)+1))) -> 0 | E76: =IF(OR(E$4<Assumptions!$D$32,E$4<$B76),0,E54*IF(E$4>=Assumptions!$D$33,INDEX($D$94:$D$111,E$4-MAX($B76,Assumptions!$D$32)+1),INDEX($C$94:$C$111,E$4-MAX($B76,Assumptions!$D$32)+1))) -> 0 | F76: =IF(OR(F$4<Assumptions!$D$32,F$4<$B76),0,F54*IF(F$4>=Assumptions!$D$33,INDEX($D$94:$D$111,F$4-MAX($B76,Assumptions!$D$32)+1),INDEX($C$94:$C$111,F$4-MAX($B76,Assumptions!$D$32)+1))) -> 0 | G76: =IF(OR(G$4<Assumptions!$D$32,G$4<$B76),0,G54*IF(G$4>=Assumptions!$D$33,INDEX($D$94:$D$111,G$4-MAX($B76,Assumptions!$D$32)+1),INDEX($C$94:$C$111,G$4-MAX($B76,Assumptions!$D$32)+1))) -> 0 | H76: =IF(OR(H$4<Assumptions!$D$32,H$4<$B76),0,H54*IF(H$4>=Assumptions!$D$33,INDEX($D$94:$D$111,H$4-MAX($B76,Assumptions!$D$32)+1),INDEX($C$94:$C$111,H$4-MAX($B76,Assumptions!$D$32)+1))) -> 0 | I76: =IF(OR(I$4<Assumptions!$D$32,I$4<$B76),0,I54*IF(I$4>=Assumptions!$D$33,INDEX($D$94:$D$111,I$4-MAX($B76,Assumptions!$D$32)+1),INDEX($C$94:$C$111,I$4-MAX($B76,Assumptions!$D$32)+1))) -> 4.265625 | J76: =IF(OR(J$4<Assumptions!$D$32,J$4<$B76),0,J54*IF(J$4>=Assumptions!$D$33,INDEX($D$94:$D$111,J$4-MAX($B76,Assumptions!$D$32)+1),INDEX($C$94:$C$111,J$4-MAX($B76,Assumptions!$D$32)+1))) -> 7.84875 | K76: =IF(OR(K$4<Assumptions!$D$32,K$4<$B76),0,K54*IF(K$4>=Assumptions!$D$33,INDEX($D$94:$D$111,K$4-MAX($B76,Assumptions!$D$32)+1),INDEX($C$94:$C$111,K$4-MAX($B76,Assumptions!$D$32)+1))) -> 10.831275 | ... U76: =IF(OR(U$4<Assumptions!$D$32,U$4<$B76),0,U54*IF(U$4>=Assumptions!$D$33,INDEX($D$94:$D$111,U$4-MAX($B76,Assumptions!$D$32)+1),INDEX($C$94:$C$111,U$4-MAX($B76,Assumptions!$D$32)+1))) -> 8.7826308
A77: Cohort M7 | B77: 7 | D77: =IF(OR(D$4<Assumptions!$D$32,D$4<$B77),0,D55*IF(D$4>=Assumptions!$D$33,INDEX($D$94:$D$111,D$4-MAX($B77,Assumptions!$D$32)+1),INDEX($C$94:$C$111,D$4-MAX($B77,Assumptions!$D$32)+1))) -> 0 | E77: =IF(OR(E$4<Assumptions!$D$32,E$4<$B77),0,E55*IF(E$4>=Assumptions!$D$33,INDEX($D$94:$D$111,E$4-MAX($B77,Assumptions!$D$32)+1),INDEX($C$94:$C$111,E$4-MAX($B77,Assumptions!$D$32)+1))) -> 0 | F77: =IF(OR(F$4<Assumptions!$D$32,F$4<$B77),0,F55*IF(F$4>=Assumptions!$D$33,INDEX($D$94:$D$111,F$4-MAX($B77,Assumptions!$D$32)+1),INDEX($C$94:$C$111,F$4-MAX($B77,Assumptions!$D$32)+1))) -> 0 | G77: =IF(OR(G$4<Assumptions!$D$32,G$4<$B77),0,G55*IF(G$4>=Assumptions!$D$33,INDEX($D$94:$D$111,G$4-MAX($B77,Assumptions!$D$32)+1),INDEX($C$94:$C$111,G$4-MAX($B77,Assumptions!$D$32)+1))) -> 0 | H77: =IF(OR(H$4<Assumptions!$D$32,H$4<$B77),0,H55*IF(H$4>=Assumptions!$D$33,INDEX($D$94:$D$111,H$4-MAX($B77,Assumptions!$D$32)+1),INDEX($C$94:$C$111,H$4-MAX($B77,Assumptions!$D$32)+1))) -> 0 | I77: =IF(OR(I$4<Assumptions!$D$32,I$4<$B77),0,I55*IF(I$4>=Assumptions!$D$33,INDEX($D$94:$D$111,I$4-MAX($B77,Assumptions!$D$32)+1),INDEX($C$94:$C$111,I$4-MAX($B77,Assumptions!$D$32)+1))) -> 0 | J77: =IF(OR(J$4<Assumptions!$D$32,J$4<$B77),0,J55*IF(J$4>=Assumptions!$D$33,INDEX($D$94:$D$111,J$4-MAX($B77,Assumptions!$D$32)+1),INDEX($C$94:$C$111,J$4-MAX($B77,Assumptions!$D$32)+1))) -> 4.265625 | K77: =IF(OR(K$4<Assumptions!$D$32,K$4<$B77),0,K55*IF(K$4>=Assumptions!$D$33,INDEX($D$94:$D$111,K$4-MAX($B77,Assumptions!$D$32)+1),INDEX($C$94:$C$111,K$4-MAX($B77,Assumptions!$D$32)+1))) -> 7.84875 | ... U77: =IF(OR(U$4<Assumptions!$D$32,U$4<$B77),0,U55*IF(U$4>=Assumptions!$D$33,INDEX($D$94:$D$111,U$4-MAX($B77,Assumptions!$D$32)+1),INDEX($C$94:$C$111,U$4-MAX($B77,Assumptions!$D$32)+1))) -> 9.5463379
A78: Cohort M8 | B78: 8 | D78: =IF(OR(D$4<Assumptions!$D$32,D$4<$B78),0,D56*IF(D$4>=Assumptions!$D$33,INDEX($D$94:$D$111,D$4-MAX($B78,Assumptions!$D$32)+1),INDEX($C$94:$C$111,D$4-MAX($B78,Assumptions!$D$32)+1))) -> 0 | E78: =IF(OR(E$4<Assumptions!$D$32,E$4<$B78),0,E56*IF(E$4>=Assumptions!$D$33,INDEX($D$94:$D$111,E$4-MAX($B78,Assumptions!$D$32)+1),INDEX($C$94:$C$111,E$4-MAX($B78,Assumptions!$D$32)+1))) -> 0 | F78: =IF(OR(F$4<Assumptions!$D$32,F$4<$B78),0,F56*IF(F$4>=Assumptions!$D$33,INDEX($D$94:$D$111,F$4-MAX($B78,Assumptions!$D$32)+1),INDEX($C$94:$C$111,F$4-MAX($B78,Assumptions!$D$32)+1))) -> 0 | G78: =IF(OR(G$4<Assumptions!$D$32,G$4<$B78),0,G56*IF(G$4>=Assumptions!$D$33,INDEX($D$94:$D$111,G$4-MAX($B78,Assumptions!$D$32)+1),INDEX($C$94:$C$111,G$4-MAX($B78,Assumptions!$D$32)+1))) -> 0 | H78: =IF(OR(H$4<Assumptions!$D$32,H$4<$B78),0,H56*IF(H$4>=Assumptions!$D$33,INDEX($D$94:$D$111,H$4-MAX($B78,Assumptions!$D$32)+1),INDEX($C$94:$C$111,H$4-MAX($B78,Assumptions!$D$32)+1))) -> 0 | I78: =IF(OR(I$4<Assumptions!$D$32,I$4<$B78),0,I56*IF(I$4>=Assumptions!$D$33,INDEX($D$94:$D$111,I$4-MAX($B78,Assumptions!$D$32)+1),INDEX($C$94:$C$111,I$4-MAX($B78,Assumptions!$D$32)+1))) -> 0 | J78: =IF(OR(J$4<Assumptions!$D$32,J$4<$B78),0,J56*IF(J$4>=Assumptions!$D$33,INDEX($D$94:$D$111,J$4-MAX($B78,Assumptions!$D$32)+1),INDEX($C$94:$C$111,J$4-MAX($B78,Assumptions!$D$32)+1))) -> 0 | K78: =IF(OR(K$4<Assumptions!$D$32,K$4<$B78),0,K56*IF(K$4>=Assumptions!$D$33,INDEX($D$94:$D$111,K$4-MAX($B78,Assumptions!$D$32)+1),INDEX($C$94:$C$111,K$4-MAX($B78,Assumptions!$D$32)+1))) -> 4.265625 | ... U78: =IF(OR(U$4<Assumptions!$D$32,U$4<$B78),0,U56*IF(U$4>=Assumptions!$D$33,INDEX($D$94:$D$111,U$4-MAX($B78,Assumptions!$D$32)+1),INDEX($C$94:$C$111,U$4-MAX($B78,Assumptions!$D$32)+1))) -> 10.376454
A79: Cohort M9 | B79: 9 | D79: =IF(OR(D$4<Assumptions!$D$32,D$4<$B79),0,D57*IF(D$4>=Assumptions!$D$33,INDEX($D$94:$D$111,D$4-MAX($B79,Assumptions!$D$32)+1),INDEX($C$94:$C$111,D$4-MAX($B79,Assumptions!$D$32)+1))) -> 0 | E79: =IF(OR(E$4<Assumptions!$D$32,E$4<$B79),0,E57*IF(E$4>=Assumptions!$D$33,INDEX($D$94:$D$111,E$4-MAX($B79,Assumptions!$D$32)+1),INDEX($C$94:$C$111,E$4-MAX($B79,Assumptions!$D$32)+1))) -> 0 | F79: =IF(OR(F$4<Assumptions!$D$32,F$4<$B79),0,F57*IF(F$4>=Assumptions!$D$33,INDEX($D$94:$D$111,F$4-MAX($B79,Assumptions!$D$32)+1),INDEX($C$94:$C$111,F$4-MAX($B79,Assumptions!$D$32)+1))) -> 0 | G79: =IF(OR(G$4<Assumptions!$D$32,G$4<$B79),0,G57*IF(G$4>=Assumptions!$D$33,INDEX($D$94:$D$111,G$4-MAX($B79,Assumptions!$D$32)+1),INDEX($C$94:$C$111,G$4-MAX($B79,Assumptions!$D$32)+1))) -> 0 | H79: =IF(OR(H$4<Assumptions!$D$32,H$4<$B79),0,H57*IF(H$4>=Assumptions!$D$33,INDEX($D$94:$D$111,H$4-MAX($B79,Assumptions!$D$32)+1),INDEX($C$94:$C$111,H$4-MAX($B79,Assumptions!$D$32)+1))) -> 0 | I79: =IF(OR(I$4<Assumptions!$D$32,I$4<$B79),0,I57*IF(I$4>=Assumptions!$D$33,INDEX($D$94:$D$111,I$4-MAX($B79,Assumptions!$D$32)+1),INDEX($C$94:$C$111,I$4-MAX($B79,Assumptions!$D$32)+1))) -> 0 | J79: =IF(OR(J$4<Assumptions!$D$32,J$4<$B79),0,J57*IF(J$4>=Assumptions!$D$33,INDEX($D$94:$D$111,J$4-MAX($B79,Assumptions!$D$32)+1),INDEX($C$94:$C$111,J$4-MAX($B79,Assumptions!$D$32)+1))) -> 0 | K79: =IF(OR(K$4<Assumptions!$D$32,K$4<$B79),0,K57*IF(K$4>=Assumptions!$D$33,INDEX($D$94:$D$111,K$4-MAX($B79,Assumptions!$D$32)+1),INDEX($C$94:$C$111,K$4-MAX($B79,Assumptions!$D$32)+1))) -> 0 | ... U79: =IF(OR(U$4<Assumptions!$D$32,U$4<$B79),0,U57*IF(U$4>=Assumptions!$D$33,INDEX($D$94:$D$111,U$4-MAX($B79,Assumptions!$D$32)+1),INDEX($C$94:$C$111,U$4-MAX($B79,Assumptions!$D$32)+1))) -> 11.278755
A80: Cohort M10 | B80: 10 | D80: =IF(OR(D$4<Assumptions!$D$32,D$4<$B80),0,D58*IF(D$4>=Assumptions!$D$33,INDEX($D$94:$D$111,D$4-MAX($B80,Assumptions!$D$32)+1),INDEX($C$94:$C$111,D$4-MAX($B80,Assumptions!$D$32)+1))) -> 0 | E80: =IF(OR(E$4<Assumptions!$D$32,E$4<$B80),0,E58*IF(E$4>=Assumptions!$D$33,INDEX($D$94:$D$111,E$4-MAX($B80,Assumptions!$D$32)+1),INDEX($C$94:$C$111,E$4-MAX($B80,Assumptions!$D$32)+1))) -> 0 | F80: =IF(OR(F$4<Assumptions!$D$32,F$4<$B80),0,F58*IF(F$4>=Assumptions!$D$33,INDEX($D$94:$D$111,F$4-MAX($B80,Assumptions!$D$32)+1),INDEX($C$94:$C$111,F$4-MAX($B80,Assumptions!$D$32)+1))) -> 0 | G80: =IF(OR(G$4<Assumptions!$D$32,G$4<$B80),0,G58*IF(G$4>=Assumptions!$D$33,INDEX($D$94:$D$111,G$4-MAX($B80,Assumptions!$D$32)+1),INDEX($C$94:$C$111,G$4-MAX($B80,Assumptions!$D$32)+1))) -> 0 | H80: =IF(OR(H$4<Assumptions!$D$32,H$4<$B80),0,H58*IF(H$4>=Assumptions!$D$33,INDEX($D$94:$D$111,H$4-MAX($B80,Assumptions!$D$32)+1),INDEX($C$94:$C$111,H$4-MAX($B80,Assumptions!$D$32)+1))) -> 0 | I80: =IF(OR(I$4<Assumptions!$D$32,I$4<$B80),0,I58*IF(I$4>=Assumptions!$D$33,INDEX($D$94:$D$111,I$4-MAX($B80,Assumptions!$D$32)+1),INDEX($C$94:$C$111,I$4-MAX($B80,Assumptions!$D$32)+1))) -> 0 | J80: =IF(OR(J$4<Assumptions!$D$32,J$4<$B80),0,J58*IF(J$4>=Assumptions!$D$33,INDEX($D$94:$D$111,J$4-MAX($B80,Assumptions!$D$32)+1),INDEX($C$94:$C$111,J$4-MAX($B80,Assumptions!$D$32)+1))) -> 0 | K80: =IF(OR(K$4<Assumptions!$D$32,K$4<$B80),0,K58*IF(K$4>=Assumptions!$D$33,INDEX($D$94:$D$111,K$4-MAX($B80,Assumptions!$D$32)+1),INDEX($C$94:$C$111,K$4-MAX($B80,Assumptions!$D$32)+1))) -> 0 | ... U80: =IF(OR(U$4<Assumptions!$D$32,U$4<$B80),0,U58*IF(U$4>=Assumptions!$D$33,INDEX($D$94:$D$111,U$4-MAX($B80,Assumptions!$D$32)+1),INDEX($C$94:$C$111,U$4-MAX($B80,Assumptions!$D$32)+1))) -> 12.259516
A81: Cohort M11 | B81: 11 | D81: =IF(OR(D$4<Assumptions!$D$32,D$4<$B81),0,D59*IF(D$4>=Assumptions!$D$33,INDEX($D$94:$D$111,D$4-MAX($B81,Assumptions!$D$32)+1),INDEX($C$94:$C$111,D$4-MAX($B81,Assumptions!$D$32)+1))) -> 0 | E81: =IF(OR(E$4<Assumptions!$D$32,E$4<$B81),0,E59*IF(E$4>=Assumptions!$D$33,INDEX($D$94:$D$111,E$4-MAX($B81,Assumptions!$D$32)+1),INDEX($C$94:$C$111,E$4-MAX($B81,Assumptions!$D$32)+1))) -> 0 | F81: =IF(OR(F$4<Assumptions!$D$32,F$4<$B81),0,F59*IF(F$4>=Assumptions!$D$33,INDEX($D$94:$D$111,F$4-MAX($B81,Assumptions!$D$32)+1),INDEX($C$94:$C$111,F$4-MAX($B81,Assumptions!$D$32)+1))) -> 0 | G81: =IF(OR(G$4<Assumptions!$D$32,G$4<$B81),0,G59*IF(G$4>=Assumptions!$D$33,INDEX($D$94:$D$111,G$4-MAX($B81,Assumptions!$D$32)+1),INDEX($C$94:$C$111,G$4-MAX($B81,Assumptions!$D$32)+1))) -> 0 | H81: =IF(OR(H$4<Assumptions!$D$32,H$4<$B81),0,H59*IF(H$4>=Assumptions!$D$33,INDEX($D$94:$D$111,H$4-MAX($B81,Assumptions!$D$32)+1),INDEX($C$94:$C$111,H$4-MAX($B81,Assumptions!$D$32)+1))) -> 0 | I81: =IF(OR(I$4<Assumptions!$D$32,I$4<$B81),0,I59*IF(I$4>=Assumptions!$D$33,INDEX($D$94:$D$111,I$4-MAX($B81,Assumptions!$D$32)+1),INDEX($C$94:$C$111,I$4-MAX($B81,Assumptions!$D$32)+1))) -> 0 | J81: =IF(OR(J$4<Assumptions!$D$32,J$4<$B81),0,J59*IF(J$4>=Assumptions!$D$33,INDEX($D$94:$D$111,J$4-MAX($B81,Assumptions!$D$32)+1),INDEX($C$94:$C$111,J$4-MAX($B81,Assumptions!$D$32)+1))) -> 0 | K81: =IF(OR(K$4<Assumptions!$D$32,K$4<$B81),0,K59*IF(K$4>=Assumptions!$D$33,INDEX($D$94:$D$111,K$4-MAX($B81,Assumptions!$D$32)+1),INDEX($C$94:$C$111,K$4-MAX($B81,Assumptions!$D$32)+1))) -> 0 | ... U81: =IF(OR(U$4<Assumptions!$D$32,U$4<$B81),0,U59*IF(U$4>=Assumptions!$D$33,INDEX($D$94:$D$111,U$4-MAX($B81,Assumptions!$D$32)+1),INDEX($C$94:$C$111,U$4-MAX($B81,Assumptions!$D$32)+1))) -> 11.421909
A82: Cohort M12 | B82: 12 | D82: =IF(OR(D$4<Assumptions!$D$32,D$4<$B82),0,D60*IF(D$4>=Assumptions!$D$33,INDEX($D$94:$D$111,D$4-MAX($B82,Assumptions!$D$32)+1),INDEX($C$94:$C$111,D$4-MAX($B82,Assumptions!$D$32)+1))) -> 0 | E82: =IF(OR(E$4<Assumptions!$D$32,E$4<$B82),0,E60*IF(E$4>=Assumptions!$D$33,INDEX($D$94:$D$111,E$4-MAX($B82,Assumptions!$D$32)+1),INDEX($C$94:$C$111,E$4-MAX($B82,Assumptions!$D$32)+1))) -> 0 | F82: =IF(OR(F$4<Assumptions!$D$32,F$4<$B82),0,F60*IF(F$4>=Assumptions!$D$33,INDEX($D$94:$D$111,F$4-MAX($B82,Assumptions!$D$32)+1),INDEX($C$94:$C$111,F$4-MAX($B82,Assumptions!$D$32)+1))) -> 0 | G82: =IF(OR(G$4<Assumptions!$D$32,G$4<$B82),0,G60*IF(G$4>=Assumptions!$D$33,INDEX($D$94:$D$111,G$4-MAX($B82,Assumptions!$D$32)+1),INDEX($C$94:$C$111,G$4-MAX($B82,Assumptions!$D$32)+1))) -> 0 | H82: =IF(OR(H$4<Assumptions!$D$32,H$4<$B82),0,H60*IF(H$4>=Assumptions!$D$33,INDEX($D$94:$D$111,H$4-MAX($B82,Assumptions!$D$32)+1),INDEX($C$94:$C$111,H$4-MAX($B82,Assumptions!$D$32)+1))) -> 0 | I82: =IF(OR(I$4<Assumptions!$D$32,I$4<$B82),0,I60*IF(I$4>=Assumptions!$D$33,INDEX($D$94:$D$111,I$4-MAX($B82,Assumptions!$D$32)+1),INDEX($C$94:$C$111,I$4-MAX($B82,Assumptions!$D$32)+1))) -> 0 | J82: =IF(OR(J$4<Assumptions!$D$32,J$4<$B82),0,J60*IF(J$4>=Assumptions!$D$33,INDEX($D$94:$D$111,J$4-MAX($B82,Assumptions!$D$32)+1),INDEX($C$94:$C$111,J$4-MAX($B82,Assumptions!$D$32)+1))) -> 0 | K82: =IF(OR(K$4<Assumptions!$D$32,K$4<$B82),0,K60*IF(K$4>=Assumptions!$D$33,INDEX($D$94:$D$111,K$4-MAX($B82,Assumptions!$D$32)+1),INDEX($C$94:$C$111,K$4-MAX($B82,Assumptions!$D$32)+1))) -> 0 | ... U82: =IF(OR(U$4<Assumptions!$D$32,U$4<$B82),0,U60*IF(U$4>=Assumptions!$D$33,INDEX($D$94:$D$111,U$4-MAX($B82,Assumptions!$D$32)+1),INDEX($C$94:$C$111,U$4-MAX($B82,Assumptions!$D$32)+1))) -> 11.528324
... A88: Cohort M18 | B88: 18 | D88: =IF(OR(D$4<Assumptions!$D$32,D$4<$B88),0,D66*IF(D$4>=Assumptions!$D$33,INDEX($D$94:$D$111,D$4-MAX($B88,Assumptions!$D$32)+1),INDEX($C$94:$C$111,D$4-MAX($B88,Assumptions!$D$32)+1))) -> 0 | E88: =IF(OR(E$4<Assumptions!$D$32,E$4<$B88),0,E66*IF(E$4>=Assumptions!$D$33,INDEX($D$94:$D$111,E$4-MAX($B88,Assumptions!$D$32)+1),INDEX($C$94:$C$111,E$4-MAX($B88,Assumptions!$D$32)+1))) -> 0 | F88: =IF(OR(F$4<Assumptions!$D$32,F$4<$B88),0,F66*IF(F$4>=Assumptions!$D$33,INDEX($D$94:$D$111,F$4-MAX($B88,Assumptions!$D$32)+1),INDEX($C$94:$C$111,F$4-MAX($B88,Assumptions!$D$32)+1))) -> 0 | G88: =IF(OR(G$4<Assumptions!$D$32,G$4<$B88),0,G66*IF(G$4>=Assumptions!$D$33,INDEX($D$94:$D$111,G$4-MAX($B88,Assumptions!$D$32)+1),INDEX($C$94:$C$111,G$4-MAX($B88,Assumptions!$D$32)+1))) -> 0 | H88: =IF(OR(H$4<Assumptions!$D$32,H$4<$B88),0,H66*IF(H$4>=Assumptions!$D$33,INDEX($D$94:$D$111,H$4-MAX($B88,Assumptions!$D$32)+1),INDEX($C$94:$C$111,H$4-MAX($B88,Assumptions!$D$32)+1))) -> 0 | I88: =IF(OR(I$4<Assumptions!$D$32,I$4<$B88),0,I66*IF(I$4>=Assumptions!$D$33,INDEX($D$94:$D$111,I$4-MAX($B88,Assumptions!$D$32)+1),INDEX($C$94:$C$111,I$4-MAX($B88,Assumptions!$D$32)+1))) -> 0 | J88: =IF(OR(J$4<Assumptions!$D$32,J$4<$B88),0,J66*IF(J$4>=Assumptions!$D$33,INDEX($D$94:$D$111,J$4-MAX($B88,Assumptions!$D$32)+1),INDEX($C$94:$C$111,J$4-MAX($B88,Assumptions!$D$32)+1))) -> 0 | K88: =IF(OR(K$4<Assumptions!$D$32,K$4<$B88),0,K66*IF(K$4>=Assumptions!$D$33,INDEX($D$94:$D$111,K$4-MAX($B88,Assumptions!$D$32)+1),INDEX($C$94:$C$111,K$4-MAX($B88,Assumptions!$D$32)+1))) -> 0 | ... U88: =IF(OR(U$4<Assumptions!$D$32,U$4<$B88),0,U66*IF(U$4>=Assumptions!$D$33,INDEX($D$94:$D$111,U$4-MAX($B88,Assumptions!$D$32)+1),INDEX($C$94:$C$111,U$4-MAX($B88,Assumptions!$D$32)+1))) -> 2.4375
A92: Bonus curve by badge age (months since max(cohort start, badge launch) + 1)
A93: Badge age | B93: Age # | C93: Rate before AI launch | D93: Rate after AI launch
A94: Age 1 | B94: 1 | C94: =Assumptions!$D$36*IF($B94<=3,INDEX(Assumptions!$C$48:$C$53,$B94),INDEX(Assumptions!$C$48:$C$53,4)) -> 0.000325 | D94: =Assumptions!$D$36*IF($B94<=3,INDEX(Assumptions!$C$48:$C$53,$B94),IF($B94<5,INDEX(Assumptions!$C$48:$C$53,4),IF($B94<8,(1-Assumptions!$D$37)*INDEX(Assumptions!$C$48:$C$53,4)+Assumptions!$D$37*INDEX(Assumptions!$C$48:$C$53,5),(1-Assumptions!$D$37)*INDEX(Assumptions!$C$48:$C$53,4)+Assumptions!$D$37*INDEX(Assumptions!$C$48:$C$53,6)))) -> 0.000325
A95: Age 2 | B95: 2 | C95: =Assumptions!$D$36*IF($B95<=3,INDEX(Assumptions!$C$48:$C$53,$B95),INDEX(Assumptions!$C$48:$C$53,4)) -> 0.00065 | D95: =Assumptions!$D$36*IF($B95<=3,INDEX(Assumptions!$C$48:$C$53,$B95),IF($B95<5,INDEX(Assumptions!$C$48:$C$53,4),IF($B95<8,(1-Assumptions!$D$37)*INDEX(Assumptions!$C$48:$C$53,4)+Assumptions!$D$37*INDEX(Assumptions!$C$48:$C$53,5),(1-Assumptions!$D$37)*INDEX(Assumptions!$C$48:$C$53,4)+Assumptions!$D$37*INDEX(Assumptions!$C$48:$C$53,6)))) -> 0.00065
A96: Age 3 | B96: 3 | C96: =Assumptions!$D$36*IF($B96<=3,INDEX(Assumptions!$C$48:$C$53,$B96),INDEX(Assumptions!$C$48:$C$53,4)) -> 0.000975 | D96: =Assumptions!$D$36*IF($B96<=3,INDEX(Assumptions!$C$48:$C$53,$B96),IF($B96<5,INDEX(Assumptions!$C$48:$C$53,4),IF($B96<8,(1-Assumptions!$D$37)*INDEX(Assumptions!$C$48:$C$53,4)+Assumptions!$D$37*INDEX(Assumptions!$C$48:$C$53,5),(1-Assumptions!$D$37)*INDEX(Assumptions!$C$48:$C$53,4)+Assumptions!$D$37*INDEX(Assumptions!$C$48:$C$53,6)))) -> 0.000975
A97: Age 4 | B97: 4 | C97: =Assumptions!$D$36*IF($B97<=3,INDEX(Assumptions!$C$48:$C$53,$B97),INDEX(Assumptions!$C$48:$C$53,4)) -> 0.001625 | D97: =Assumptions!$D$36*IF($B97<=3,INDEX(Assumptions!$C$48:$C$53,$B97),IF($B97<5,INDEX(Assumptions!$C$48:$C$53,4),IF($B97<8,(1-Assumptions!$D$37)*INDEX(Assumptions!$C$48:$C$53,4)+Assumptions!$D$37*INDEX(Assumptions!$C$48:$C$53,5),(1-Assumptions!$D$37)*INDEX(Assumptions!$C$48:$C$53,4)+Assumptions!$D$37*INDEX(Assumptions!$C$48:$C$53,6)))) -> 0.001625
A98: Age 5 | B98: 5 | C98: =Assumptions!$D$36*IF($B98<=3,INDEX(Assumptions!$C$48:$C$53,$B98),INDEX(Assumptions!$C$48:$C$53,4)) -> 0.001625 | D98: =Assumptions!$D$36*IF($B98<=3,INDEX(Assumptions!$C$48:$C$53,$B98),IF($B98<5,INDEX(Assumptions!$C$48:$C$53,4),IF($B98<8,(1-Assumptions!$D$37)*INDEX(Assumptions!$C$48:$C$53,4)+Assumptions!$D$37*INDEX(Assumptions!$C$48:$C$53,5),(1-Assumptions!$D$37)*INDEX(Assumptions!$C$48:$C$53,4)+Assumptions!$D$37*INDEX(Assumptions!$C$48:$C$53,6)))) -> 0.00169
A99: Age 6 | B99: 6 | C99: =Assumptions!$D$36*IF($B99<=3,INDEX(Assumptions!$C$48:$C$53,$B99),INDEX(Assumptions!$C$48:$C$53,4)) -> 0.001625 | D99: =Assumptions!$D$36*IF($B99<=3,INDEX(Assumptions!$C$48:$C$53,$B99),IF($B99<5,INDEX(Assumptions!$C$48:$C$53,4),IF($B99<8,(1-Assumptions!$D$37)*INDEX(Assumptions!$C$48:$C$53,4)+Assumptions!$D$37*INDEX(Assumptions!$C$48:$C$53,5),(1-Assumptions!$D$37)*INDEX(Assumptions!$C$48:$C$53,4)+Assumptions!$D$37*INDEX(Assumptions!$C$48:$C$53,6)))) -> 0.00169
A100: Age 7 | B100: 7 | C100: =Assumptions!$D$36*IF($B100<=3,INDEX(Assumptions!$C$48:$C$53,$B100),INDEX(Assumptions!$C$48:$C$53,4)) -> 0.001625 | D100: =Assumptions!$D$36*IF($B100<=3,INDEX(Assumptions!$C$48:$C$53,$B100),IF($B100<5,INDEX(Assumptions!$C$48:$C$53,4),IF($B100<8,(1-Assumptions!$D$37)*INDEX(Assumptions!$C$48:$C$53,4)+Assumptions!$D$37*INDEX(Assumptions!$C$48:$C$53,5),(1-Assumptions!$D$37)*INDEX(Assumptions!$C$48:$C$53,4)+Assumptions!$D$37*INDEX(Assumptions!$C$48:$C$53,6)))) -> 0.00169
A101: Age 8 | B101: 8 | C101: =Assumptions!$D$36*IF($B101<=3,INDEX(Assumptions!$C$48:$C$53,$B101),INDEX(Assumptions!$C$48:$C$53,4)) -> 0.001625 | D101: =Assumptions!$D$36*IF($B101<=3,INDEX(Assumptions!$C$48:$C$53,$B101),IF($B101<5,INDEX(Assumptions!$C$48:$C$53,4),IF($B101<8,(1-Assumptions!$D$37)*INDEX(Assumptions!$C$48:$C$53,4)+Assumptions!$D$37*INDEX(Assumptions!$C$48:$C$53,5),(1-Assumptions!$D$37)*INDEX(Assumptions!$C$48:$C$53,4)+Assumptions!$D$37*INDEX(Assumptions!$C$48:$C$53,6)))) -> 0.00182
A102: Age 9 | B102: 9 | C102: =Assumptions!$D$36*IF($B102<=3,INDEX(Assumptions!$C$48:$C$53,$B102),INDEX(Assumptions!$C$48:$C$53,4)) -> 0.001625 | D102: =Assumptions!$D$36*IF($B102<=3,INDEX(Assumptions!$C$48:$C$53,$B102),IF($B102<5,INDEX(Assumptions!$C$48:$C$53,4),IF($B102<8,(1-Assumptions!$D$37)*INDEX(Assumptions!$C$48:$C$53,4)+Assumptions!$D$37*INDEX(Assumptions!$C$48:$C$53,5),(1-Assumptions!$D$37)*INDEX(Assumptions!$C$48:$C$53,4)+Assumptions!$D$37*INDEX(Assumptions!$C$48:$C$53,6)))) -> 0.00182
A103: Age 10 | B103: 10 | C103: =Assumptions!$D$36*IF($B103<=3,INDEX(Assumptions!$C$48:$C$53,$B103),INDEX(Assumptions!$C$48:$C$53,4)) -> 0.001625 | D103: =Assumptions!$D$36*IF($B103<=3,INDEX(Assumptions!$C$48:$C$53,$B103),IF($B103<5,INDEX(Assumptions!$C$48:$C$53,4),IF($B103<8,(1-Assumptions!$D$37)*INDEX(Assumptions!$C$48:$C$53,4)+Assumptions!$D$37*INDEX(Assumptions!$C$48:$C$53,5),(1-Assumptions!$D$37)*INDEX(Assumptions!$C$48:$C$53,4)+Assumptions!$D$37*INDEX(Assumptions!$C$48:$C$53,6)))) -> 0.00182
A104: Age 11 | B104: 11 | C104: =Assumptions!$D$36*IF($B104<=3,INDEX(Assumptions!$C$48:$C$53,$B104),INDEX(Assumptions!$C$48:$C$53,4)) -> 0.001625 | D104: =Assumptions!$D$36*IF($B104<=3,INDEX(Assumptions!$C$48:$C$53,$B104),IF($B104<5,INDEX(Assumptions!$C$48:$C$53,4),IF($B104<8,(1-Assumptions!$D$37)*INDEX(Assumptions!$C$48:$C$53,4)+Assumptions!$D$37*INDEX(Assumptions!$C$48:$C$53,5),(1-Assumptions!$D$37)*INDEX(Assumptions!$C$48:$C$53,4)+Assumptions!$D$37*INDEX(Assumptions!$C$48:$C$53,6)))) -> 0.00182
A105: Age 12 | B105: 12 | C105: =Assumptions!$D$36*IF($B105<=3,INDEX(Assumptions!$C$48:$C$53,$B105),INDEX(Assumptions!$C$48:$C$53,4)) -> 0.001625 | D105: =Assumptions!$D$36*IF($B105<=3,INDEX(Assumptions!$C$48:$C$53,$B105),IF($B105<5,INDEX(Assumptions!$C$48:$C$53,4),IF($B105<8,(1-Assumptions!$D$37)*INDEX(Assumptions!$C$48:$C$53,4)+Assumptions!$D$37*INDEX(Assumptions!$C$48:$C$53,5),(1-Assumptions!$D$37)*INDEX(Assumptions!$C$48:$C$53,4)+Assumptions!$D$37*INDEX(Assumptions!$C$48:$C$53,6)))) -> 0.00182
... A111: Age 18 | B111: 18 | C111: =Assumptions!$D$36*IF($B111<=3,INDEX(Assumptions!$C$48:$C$53,$B111),INDEX(Assumptions!$C$48:$C$53,4)) -> 0.001625 | D111: =Assumptions!$D$36*IF($B111<=3,INDEX(Assumptions!$C$48:$C$53,$B111),IF($B111<5,INDEX(Assumptions!$C$48:$C$53,4),IF($B111<8,(1-Assumptions!$D$37)*INDEX(Assumptions!$C$48:$C$53,4)+Assumptions!$D$37*INDEX(Assumptions!$C$48:$C$53,5),(1-Assumptions!$D$37)*INDEX(Assumptions!$C$48:$C$53,4)+Assumptions!$D$37*INDEX(Assumptions!$C$48:$C$53,6)))) -> 0.00182

Sheet Model_Aggr
A1: Habitlock model, Aggressive scenario
A2: All money in VND million unless stated. Months are counted from launch. Flows are monthly; stocks are end of month.
A3: Line item | B3: Unit | C3: 18M total | D3: M1 | E3: M2 | F3: M3 | G3: M4 | H3: M5 | I3: M6 | J3: M7 | K3: M8 | L3: M9 | M3: M10 | N3: M11 | O3: M12 | P3: M13 | Q3: M14 | R3: M15 | S3: M16 | T3: M17 | U3: M18
A4: Month since launch | B4: # | D4: 1 | E4: 2 | F4: 3 | G4: 4 | H4: 5 | I4: 6 | J4: 7 | K4: 8 | L4: 9 | M4: 10 | N4: 11 | O4: 12 | P4: 13 | Q4: 14 | R4: 15 | S4: 16 | T4: 17 | U4: 18
A5: Calendar month | B5: 1-12 | D5: =MOD(Assumptions!$E$30-1+D4-1,12)+1 -> 7 | E5: =MOD(Assumptions!$E$30-1+E4-1,12)+1 -> 8 | F5: =MOD(Assumptions!$E$30-1+F4-1,12)+1 -> 9 | G5: =MOD(Assumptions!$E$30-1+G4-1,12)+1 -> 10 | H5: =MOD(Assumptions!$E$30-1+H4-1,12)+1 -> 11 | I5: =MOD(Assumptions!$E$30-1+I4-1,12)+1 -> 12 | J5: =MOD(Assumptions!$E$30-1+J4-1,12)+1 -> 1 | K5: =MOD(Assumptions!$E$30-1+K4-1,12)+1 -> 2 | ... U5: =MOD(Assumptions!$E$30-1+U4-1,12)+1 -> 12
A6: Withdrawal seasonality | B6: x | D6: =INDEX(Assumptions!$C$57:$N$57,D5) -> 1 | E6: =INDEX(Assumptions!$C$57:$N$57,E5) -> 1 | F6: =INDEX(Assumptions!$C$57:$N$57,F5) -> 1 | G6: =INDEX(Assumptions!$C$57:$N$57,G5) -> 1 | H6: =INDEX(Assumptions!$C$57:$N$57,H5) -> 1 | I6: =INDEX(Assumptions!$C$57:$N$57,I5) -> 1.3 | J6: =INDEX(Assumptions!$C$57:$N$57,J5) -> 1.4 | K6: =INDEX(Assumptions!$C$57:$N$57,K5) -> 1.2 | ... U6: =INDEX(Assumptions!$C$57:$N$57,U5) -> 1.3
A7: Signup weight (normalised) | B7: % | D7: =INDEX(Assumptions!$C$61:$T$61,D4)/SUM(Assumptions!$C$61:$T$61) -> 0.020833333 | E7: =INDEX(Assumptions!$C$61:$T$61,E4)/SUM(Assumptions!$C$61:$T$61) -> 0.03125 | F7: =INDEX(Assumptions!$C$61:$T$61,F4)/SUM(Assumptions!$C$61:$T$61) -> 0.041666667 | G7: =INDEX(Assumptions!$C$61:$T$61,G4)/SUM(Assumptions!$C$61:$T$61) -> 0.052083333 | H7: =INDEX(Assumptions!$C$61:$T$61,H4)/SUM(Assumptions!$C$61:$T$61) -> 0.0625 | I7: =INDEX(Assumptions!$C$61:$T$61,I4)/SUM(Assumptions!$C$61:$T$61) -> 0.072916667 | J7: =INDEX(Assumptions!$C$61:$T$61,J4)/SUM(Assumptions!$C$61:$T$61) -> 0.072916667 | K7: =INDEX(Assumptions!$C$61:$T$61,K4)/SUM(Assumptions!$C$61:$T$61) -> 0.072916667 | ... U7: =INDEX(Assumptions!$C$61:$T$61,U4)/SUM(Assumptions!$C$61:$T$61) -> 0.041666667
A8: Funnel
A9: New users acquired | B9: users | C9: =SUM(D9:U9) -> 600000 | D9: =Assumptions!$E$14*Assumptions!$E$12*D7 -> 12500 | E9: =Assumptions!$E$14*Assumptions!$E$12*E7 -> 18750 | F9: =Assumptions!$E$14*Assumptions!$E$12*F7 -> 25000 | G9: =Assumptions!$E$14*Assumptions!$E$12*G7 -> 31250 | H9: =Assumptions!$E$14*Assumptions!$E$12*H7 -> 37500 | I9: =Assumptions!$E$14*Assumptions!$E$12*I7 -> 43750 | J9: =Assumptions!$E$14*Assumptions!$E$12*J7 -> 43750 | K9: =Assumptions!$E$14*Assumptions!$E$12*K7 -> 43750 | ... U9: =Assumptions!$E$14*Assumptions!$E$12*U7 -> 25000
A10: New activated users (first deposit) | B10: users | C10: =SUM(D10:U10) -> 420000 | D10: =D9*Assumptions!$E$15 -> 8750 | E10: =E9*Assumptions!$E$15 -> 13125 | F10: =F9*Assumptions!$E$15 -> 17500 | G10: =G9*Assumptions!$E$15 -> 21875 | H10: =H9*Assumptions!$E$15 -> 26250 | I10: =I9*Assumptions!$E$15 -> 30625 | J10: =J9*Assumptions!$E$15 -> 30625 | K10: =K9*Assumptions!$E$15 -> 30625 | ... U10: =U9*Assumptions!$E$15 -> 17500
A11: Active users, end of month | B11: users | D11: =SUM(D49:D66) -> 8750 | E11: =SUM(E49:E66) -> 21437.5 | F11: =SUM(F49:F66) -> 37865.625 | G11: =SUM(G49:G66) -> 57847.344 | H11: =SUM(H49:H66) -> 81204.977 | I11: =SUM(I49:I66) -> 107769.73 | J11: =SUM(J49:J66) -> 133006.24 | K11: =SUM(K49:K66) -> 156980.93 | ... U11: =SUM(U49:U66) -> 281987.78
A12: Users who exit in month | B12: users | C12: =SUM(D12:U12) -> 138012.22 | D12: =0 -> 0 | E12: =D11*Assumptions!$E$18 -> 437.5 | F12: =E11*Assumptions!$E$18 -> 1071.875 | G12: =F11*Assumptions!$E$18 -> 1893.2812 | H12: =G11*Assumptions!$E$18 -> 2892.3672 | I12: =H11*Assumptions!$E$18 -> 4060.2488 | J12: =I11*Assumptions!$E$18 -> 5388.4864 | K12: =J11*Assumptions!$E$18 -> 6650.3121 | L12: =K11*Assumptions!$E$18 -> 7849.0465 | ... U12: =T11*Assumptions!$E$18 -> 13920.409
A13: Cumulative users acquired | B13: users | D13: =D9 -> 12500 | E13: =D13+E9 -> 31250 | F13: =E13+F9 -> 56250 | G13: =F13+G9 -> 87500 | H13: =G13+H9 -> 125000 | I13: =H13+I9 -> 168750 | J13: =I13+J9 -> 212500 | K13: =J13+K9 -> 256250 | L13: =K13+L9 -> 300000 | ... U13: =T13+U9 -> 600000
A14: AUM
A15: Average balance per active user, start of month | B15: VND mn/user | D15: =IF(0>0,0/0,0) -> 0 | E15: =IF(D11>0,D21/D11,0) -> 0.8 | F15: =IF(E11>0,E21/E11,0) -> 1.0977959 | G15: =IF(F11>0,F21/F11,0) -> 1.3717801 | H15: =IF(G11>0,G21/G11,0) -> 1.6260847 | I15: =IF(H11>0,H21/H11,0) -> 1.865669 | J15: =IF(I11>0,I21/I11,0) -> 2.0806381 | K15: =IF(J11>0,J21/J11,0) -> 2.330713 | L15: =IF(K11>0,K21/K11,0) -> 2.6048816 | ... U15: =IF(T11>0,T21/T11,0) -> 5.3591025
A16: Gross deposits | B16: VND mn | C16: =SUM(D16:U16) -> 2433785.8 | D16: =D11*Assumptions!$E$19/Assumptions!$E$7 -> 7000 | E16: =E11*Assumptions!$E$19/Assumptions!$E$7 -> 17150 | F16: =F11*Assumptions!$E$19/Assumptions!$E$7 -> 30292.5 | G16: =G11*Assumptions!$E$19/Assumptions!$E$7 -> 46277.875 | H16: =H11*Assumptions!$E$19/Assumptions!$E$7 -> 64963.981 | I16: =I11*Assumptions!$E$19/Assumptions!$E$7 -> 86215.782 | J16: =J11*Assumptions!$E$19/Assumptions!$E$7 -> 106404.99 | K16: =K11*Assumptions!$E$19/Assumptions!$E$7 -> 125584.74 | ... U16: =U11*Assumptions!$E$19/Assumptions!$E$7 -> 225590.22
A17: Exit withdrawals (churned users take full balance) | B17: VND mn | C17: =SUM(D17:U17) -> 518367.16 | D17: =D12*D15 -> 0 | E17: =E12*E15 -> 350 | F17: =F12*F15 -> 1176.7 | G17: =G12*G15 -> 2597.1655 | H17: =H12*H15 -> 4703.234 | I17: =I12*I15 -> 7575.0803 | J17: =J12*J15 -> 11211.49 | K17: =K12*K15 -> 15499.969 | ... U17: =U12*U15 -> 74600.9
A18: Pause & Reflect live (1/0) | B18: flag | D18: =IF(D4>=Assumptions!$E$31,1,0) -> 0 | E18: =IF(E4>=Assumptions!$E$31,1,0) -> 0 | F18: =IF(F4>=Assumptions!$E$31,1,0) -> 1 | G18: =IF(G4>=Assumptions!$E$31,1,0) -> 1 | H18: =IF(H4>=Assumptions!$E$31,1,0) -> 1 | I18: =IF(I4>=Assumptions!$E$31,1,0) -> 1 | J18: =IF(J4>=Assumptions!$E$31,1,0) -> 1 | K18: =IF(K4>=Assumptions!$E$31,1,0) -> 1 | ... U18: =IF(U4>=Assumptions!$E$31,1,0) -> 1
A19: Partial withdrawal rate after Pause & Reflect | B19: %/month | D19: =Assumptions!$E$20*D6*(1-Assumptions!$E$21*Assumptions!$E$22*D18) -> 0.04 | E19: =Assumptions!$E$20*E6*(1-Assumptions!$E$21*Assumptions!$E$22*E18) -> 0.04 | F19: =Assumptions!$E$20*F6*(1-Assumptions!$E$21*Assumptions!$E$22*F18) -> 0.0316 | G19: =Assumptions!$E$20*G6*(1-Assumptions!$E$21*Assumptions!$E$22*G18) -> 0.0316 | H19: =Assumptions!$E$20*H6*(1-Assumptions!$E$21*Assumptions!$E$22*H18) -> 0.0316 | I19: =Assumptions!$E$20*I6*(1-Assumptions!$E$21*Assumptions!$E$22*I18) -> 0.04108 | J19: =Assumptions!$E$20*J6*(1-Assumptions!$E$21*Assumptions!$E$22*J18) -> 0.04424 | K19: =Assumptions!$E$20*K6*(1-Assumptions!$E$21*Assumptions!$E$22*K18) -> 0.03792 | ... U19: =Assumptions!$E$20*U6*(1-Assumptions!$E$21*Assumptions!$E$22*U18) -> 0.04108
A20: Partial withdrawals | B20: VND mn | C20: =SUM(D20:U20) -> 330638.83 | D20: =(0-D17)*D19 -> 0 | E20: =(D21-E17)*E19 -> 266 | F20: =(E21-F17)*F19 -> 706.49068 | G20: =(F21-G17)*G19 -> 1559.3381 | H20: =(G21-H17)*H19 -> 2823.8217 | I20: =(H21-I17)*I19 -> 5912.5017 | J20: =(I21-J17)*J19 -> 9423.9303 | K20: =(J21-K17)*K19 -> 11167.418 | L20: =(K21-L17)*L19 -> 12275.68 | ... U20: =(T21-U17)*U19 -> 58227.495
A21: AUM, end of month | B21: VND mn | D21: =0+D16-D17-D20 -> 7000 | E21: =D21+E16-E17-E20 -> 23534 | F21: =E21+F16-F17-F20 -> 51943.309 | G21: =F21+G16-G17-G20 -> 94064.681 | H21: =G21+H16-H17-H20 -> 151501.61 | I21: =H21+I16-I17-I20 -> 224229.81 | J21: =I21+J16-J17-J20 -> 309999.38 | K21: =J21+K16-K17-K20 -> 408916.74 | L21: =K21+L16-L17-L20 -> 520000.72 | ... U21: =T21+U16-U17-U20 -> 1584779.8
A22: Fund share of AUM | B22: % | D22: =IF(D4<Assumptions!$E$33,0,MIN(1,(D4-Assumptions!$E$33+1)/Assumptions!$E$28))*Assumptions!$E$27 -> 0 | E22: =IF(E4<Assumptions!$E$33,0,MIN(1,(E4-Assumptions!$E$33+1)/Assumptions!$E$28))*Assumptions!$E$27 -> 0 | F22: =IF(F4<Assumptions!$E$33,0,MIN(1,(F4-Assumptions!$E$33+1)/Assumptions!$E$28))*Assumptions!$E$27 -> 0 | G22: =IF(G4<Assumptions!$E$33,0,MIN(1,(G4-Assumptions!$E$33+1)/Assumptions!$E$28))*Assumptions!$E$27 -> 0 | H22: =IF(H4<Assumptions!$E$33,0,MIN(1,(H4-Assumptions!$E$33+1)/Assumptions!$E$28))*Assumptions!$E$27 -> 0.033333333 | I22: =IF(I4<Assumptions!$E$33,0,MIN(1,(I4-Assumptions!$E$33+1)/Assumptions!$E$28))*Assumptions!$E$27 -> 0.066666667 | J22: =IF(J4<Assumptions!$E$33,0,MIN(1,(J4-Assumptions!$E$33+1)/Assumptions!$E$28))*Assumptions!$E$27 -> 0.1 | K22: =IF(K4<Assumptions!$E$33,0,MIN(1,(K4-Assumptions!$E$33+1)/Assumptions!$E$28))*Assumptions!$E$27 -> 0.13333333 | ... U22: =IF(U4<Assumptions!$E$33,0,MIN(1,(U4-Assumptions!$E$33+1)/Assumptions!$E$28))*Assumptions!$E$27 -> 0.2
A23: AUM in funds | B23: VND mn | D23: =D21*D22 -> 0 | E23: =E21*E22 -> 0 | F23: =F21*F22 -> 0 | G23: =G21*G22 -> 0 | H23: =H21*H22 -> 5050.0535 | I23: =I21*I22 -> 14948.654 | J23: =J21*J22 -> 30999.938 | K23: =K21*K22 -> 54522.231 | ... U23: =U21*U22 -> 316955.97
A24: AUM in savings | B24: VND mn | D24: =D21-D23 -> 7000 | E24: =E21-E23 -> 23534 | F24: =F21-F23 -> 51943.309 | G24: =G21-G23 -> 94064.681 | H24: =H21-H23 -> 146451.55 | I24: =I21-I23 -> 209281.15 | J24: =J21-J23 -> 278999.44 | K24: =K21-K23 -> 354394.5 | ... U24: =U21-U23 -> 1267823.9
A25: Average AUM in month | B25: VND mn | D25: =(0+D21)/2 -> 3500 | E25: =(D21+E21)/2 -> 15267 | F25: =(E21+F21)/2 -> 37738.655 | G25: =(F21+G21)/2 -> 73003.995 | H25: =(G21+H21)/2 -> 122783.14 | I25: =(H21+I21)/2 -> 187865.71 | J25: =(I21+J21)/2 -> 267114.59 | K25: =(J21+K21)/2 -> 359458.06 | L25: =(K21+L21)/2 -> 464458.73 | ... U25: =(T21+U21)/2 -> 1538398.9
A26: Counterfactual: same cohort without Pause & Reflect
A27: Avg balance per active user, no P&R | B27: VND mn/user | D27: =IF(0>0,0/0,0) -> 0 | E27: =IF(D11>0,D30/D11,0) -> 0.8 | F27: =IF(E11>0,E30/E11,0) -> 1.0977959 | G27: =IF(F11>0,F30/F11,0) -> 1.3668204 | H27: =IF(G11>0,G30/G11,0) -> 1.6159584 | I27: =IF(H11>0,H30/H11,0) -> 1.8498464 | J27: =IF(I11>0,I30/I11,0) -> 2.0553172 | K27: =IF(J11>0,J30/J11,0) -> 2.2934793 | L27: =IF(K11>0,K30/K11,0) -> 2.55744 | ... U27: =IF(T11>0,T30/T11,0) -> 5.1703315
A28: Exit withdrawals, no P&R | B28: VND mn | C28: =SUM(D28:U28) -> 504550.03 | D28: =D12*D27 -> 0 | E28: =E12*E27 -> 350 | F28: =F12*F27 -> 1176.7 | G28: =G12*G27 -> 2587.7754 | H28: =H12*H27 -> 4673.9449 | I28: =I12*I27 -> 7510.8368 | J28: =J12*J27 -> 11075.049 | K28: =K12*K27 -> 15252.353 | ... U28: =U12*U27 -> 71973.13
A29: Partial withdrawals, no P&R | B29: VND mn | C29: =SUM(D29:U29) -> 407265.54 | D29: =(0-D28)*Assumptions!$E$20*D6 -> 0 | E29: =(D30-E28)*Assumptions!$E$20*E6 -> 266 | F29: =(E30-F28)*Assumptions!$E$20*F6 -> 894.292 | G29: =(F30-G28)*Assumptions!$E$20*G6 -> 1966.7093 | H29: =(G30-H28)*Assumptions!$E$20*H6 -> 3552.1981 | I29: =(H30-I28)*Assumptions!$E$20*I6 -> 7420.7068 | J29: =(I30-J28)*Assumptions!$E$20*J6 -> 11783.852 | K29: =(J30-K28)*Assumptions!$E$20*K6 -> 13910.146 | L29: =(K30-L28)*Assumptions!$E$20*L6 -> 15255.834 | ... U29: =(T30-U28)*Assumptions!$E$20*U6 -> 71109.452
A30: AUM, no P&R | B30: VND mn | D30: =0+D16-D28-D29 -> 7000 | E30: =D30+E16-E28-E29 -> 23534 | F30: =E30+F16-F28-F29 -> 51755.508 | G30: =F30+G16-G28-G29 -> 93478.898 | H30: =G30+H16-H28-H29 -> 150216.74 | I30: =H30+I16-I28-I29 -> 221500.98 | J30: =I30+J16-J28-J29 -> 305047.07 | K30: =J30+K16-K28-K29 -> 401469.31 | L30: =K30+L16-L28-L29 -> 509945.52 | ... U30: =T30+U16-U28-U29 -> 1521970.2
A31: AUM retained thanks to Pause & Reflect | B31: VND mn | D31: =D21-D30 -> 0 | E31: =E21-E30 -> 0 | F31: =F21-F30 -> 187.80132 | G31: =G21-G30 -> 585.78241 | H31: =H21-H30 -> 1284.8697 | I31: =I21-I30 -> 2728.8313 | J31: =J21-J30 -> 4952.3113 | K31: =K21-K30 -> 7447.4244 | ... U31: =U21-U30 -> 62809.597
A32: P&L to Infina (incremental)
A33: Revenue on savings AUM | B33: VND mn | C33: =SUM(D33:U33) -> 5288.1256 | D33: =D25*(1-D22)*Assumptions!$E$24/12 -> 2.0416667 | E33: =E25*(1-E22)*Assumptions!$E$24/12 -> 8.90575 | F33: =F25*(1-F22)*Assumptions!$E$24/12 -> 22.014215 | G33: =G25*(1-G22)*Assumptions!$E$24/12 -> 42.585664 | H33: =H25*(1-H22)*Assumptions!$E$24/12 -> 69.23605 | I33: =I25*(1-I22)*Assumptions!$E$24/12 -> 102.28244 | J33: =J25*(1-J22)*Assumptions!$E$24/12 -> 140.23516 | K33: =K25*(1-K22)*Assumptions!$E$24/12 -> 181.72602 | ... U33: =U25*(1-U22)*Assumptions!$E$24/12 -> 717.91949
A34: Revenue on fund AUM | B34: VND mn | C34: =SUM(D34:U34) -> 1745.3123 | D34: =D25*D22*Assumptions!$E$25/12 -> 0 | E34: =E25*E22*Assumptions!$E$25/12 -> 0 | F34: =F25*F22*Assumptions!$E$25/12 -> 0 | G34: =G25*G22*Assumptions!$E$25/12 -> 0 | H34: =H25*H22*Assumptions!$E$25/12 -> 3.4106429 | I34: =I25*I22*Assumptions!$E$25/12 -> 10.436984 | J34: =J25*J22*Assumptions!$E$25/12 -> 22.259549 | K34: =K25*K22*Assumptions!$E$25/12 -> 39.939784 | ... U34: =U25*U22*Assumptions!$E$25/12 -> 256.39982
A35: Gross revenue on Habitlock AUM | B35: VND mn | C35: =SUM(D35:U35) -> 7033.438 | D35: =D33+D34 -> 2.0416667 | E35: =E33+E34 -> 8.90575 | F35: =F33+F34 -> 22.014215 | G35: =G33+G34 -> 42.585664 | H35: =H33+H34 -> 72.646693 | I35: =I33+I34 -> 112.71942 | J35: =J33+J34 -> 162.49471 | K35: =K33+K34 -> 221.6658 | ... U35: =U33+U34 -> 974.31931
A36: Incremental revenue (after incrementality) | B36: VND mn | C36: =SUM(D36:U36) -> 6330.0942 | D36: =D35*Assumptions!$E$26 -> 1.8375 | E36: =E35*Assumptions!$E$26 -> 8.015175 | F36: =F35*Assumptions!$E$26 -> 19.812794 | G36: =G35*Assumptions!$E$26 -> 38.327097 | H36: =H35*Assumptions!$E$26 -> 65.382024 | I36: =I35*Assumptions!$E$26 -> 101.44748 | J36: =J35*Assumptions!$E$26 -> 146.24524 | K36: =K35*Assumptions!$E$26 -> 199.49922 | ... U36: =U35*Assumptions!$E$26 -> 876.88738
A37: Weighted average bonus rate (annual, savings AUM) | B37: %/yr | D37: =IF(D11>0,SUM(D71:D88)/D11,0) -> 0 | E37: =IF(E11>0,SUM(E71:E88)/E11,0) -> 0 | F37: =IF(F11>0,SUM(F71:F88)/F11,0) -> 0 | G37: =IF(G11>0,SUM(G71:G88)/G11,0) -> 0.0004 | H37: =IF(H11>0,SUM(H71:H88)/H11,0) -> 0.00067069758 | I37: =IF(I11>0,SUM(I71:I88)/I11,0) -> 0.00088010497 | J37: =IF(J11>0,SUM(J71:J88)/J11,0) -> 0.0012266152 | K37: =IF(K11>0,SUM(K71:K88)/K11,0) -> 0.0013606248 | ... U37: =IF(U11>0,SUM(U71:U88)/U11,0) -> 0.0019923606
A38: Bonus interest cost (paid on ALL Habitlock savings AUM) | B38: VND mn | C38: =SUM(D38:U38) -> 1315.3696 | D38: =D25*(1-D22)*D37/12 -> 0 | E38: =E25*(1-E22)*E37/12 -> 0 | F38: =F25*(1-F22)*F37/12 -> 0 | G38: =G25*(1-G22)*G37/12 -> 2.4334665 | H38: =H25*(1-H22)*H37/12 -> 6.6337788 | I38: =I25*(1-I22)*I37/12 -> 12.859898 | J38: =J25*(1-J22)*J37/12 -> 24.573512 | K38: =K25*(1-K22)*K37/12 -> 35.32299 | ... U38: =U25*(1-U22)*U37/12 -> 204.33636
A39: Acquisition spend | B39: VND mn | C39: =SUM(D39:U39) -> 33600 | D39: =D10*Assumptions!$E$16/Assumptions!$E$7 -> 700 | E39: =E10*Assumptions!$E$16/Assumptions!$E$7 -> 1050 | F39: =F10*Assumptions!$E$16/Assumptions!$E$7 -> 1400 | G39: =G10*Assumptions!$E$16/Assumptions!$E$7 -> 1750 | H39: =H10*Assumptions!$E$16/Assumptions!$E$7 -> 2100 | I39: =I10*Assumptions!$E$16/Assumptions!$E$7 -> 2450 | J39: =J10*Assumptions!$E$16/Assumptions!$E$7 -> 2450 | K39: =K10*Assumptions!$E$16/Assumptions!$E$7 -> 2450 | ... U39: =U10*Assumptions!$E$16/Assumptions!$E$7 -> 1400
A40: Build cost | B40: VND mn | C40: =SUM(D40:U40) -> 1500 | D40: =IF(D4<=Assumptions!$E$40,Assumptions!$E$39/Assumptions!$E$40/Assumptions!$E$7,0) -> 500 | E40: =IF(E4<=Assumptions!$E$40,Assumptions!$E$39/Assumptions!$E$40/Assumptions!$E$7,0) -> 500 | F40: =IF(F4<=Assumptions!$E$40,Assumptions!$E$39/Assumptions!$E$40/Assumptions!$E$7,0) -> 500 | G40: =IF(G4<=Assumptions!$E$40,Assumptions!$E$39/Assumptions!$E$40/Assumptions!$E$7,0) -> 0 | H40: =IF(H4<=Assumptions!$E$40,Assumptions!$E$39/Assumptions!$E$40/Assumptions!$E$7,0) -> 0 | I40: =IF(I4<=Assumptions!$E$40,Assumptions!$E$39/Assumptions!$E$40/Assumptions!$E$7,0) -> 0 | J40: =IF(J4<=Assumptions!$E$40,Assumptions!$E$39/Assumptions!$E$40/Assumptions!$E$7,0) -> 0 | K40: =IF(K4<=Assumptions!$E$40,Assumptions!$E$39/Assumptions!$E$40/Assumptions!$E$7,0) -> 0 | ... U40: =IF(U4<=Assumptions!$E$40,Assumptions!$E$39/Assumptions!$E$40/Assumptions!$E$7,0) -> 0
A41: Run cost | B41: VND mn | C41: =SUM(D41:U41) -> 2160 | D41: =Assumptions!$E$41/Assumptions!$E$7 -> 120 | E41: =Assumptions!$E$41/Assumptions!$E$7 -> 120 | F41: =Assumptions!$E$41/Assumptions!$E$7 -> 120 | G41: =Assumptions!$E$41/Assumptions!$E$7 -> 120 | H41: =Assumptions!$E$41/Assumptions!$E$7 -> 120 | I41: =Assumptions!$E$41/Assumptions!$E$7 -> 120 | J41: =Assumptions!$E$41/Assumptions!$E$7 -> 120 | K41: =Assumptions!$E$41/Assumptions!$E$7 -> 120 | ... U41: =Assumptions!$E$41/Assumptions!$E$7 -> 120
A42: Net contribution | B42: VND mn | C42: =SUM(D42:U42) -> -32245.275 | D42: =D36-D38-D39-D40-D41 -> -1318.1625 | E42: =E36-E38-E39-E40-E41 -> -1661.9848 | F42: =F36-F38-F39-F40-F41 -> -2000.1872 | G42: =G36-G38-G39-G40-G41 -> -1834.1064 | H42: =H36-H38-H39-H40-H41 -> -2161.2518 | I42: =I36-I38-I39-I40-I41 -> -2481.4124 | J42: =J36-J38-J39-J40-J41 -> -2448.3283 | K42: =K36-K38-K39-K40-K41 -> -2405.8238 | ... U42: =U36-U38-U39-U40-U41 -> -847.44897
A43: Cumulative net contribution | B43: VND mn | D43: =D42 -> -1318.1625 | E43: =D43+E42 -> -2980.1473 | F43: =E43+F42 -> -4980.3345 | G43: =F43+G42 -> -6814.4409 | H43: =G43+H42 -> -8975.6927 | I43: =H43+I42 -> -11457.105 | J43: =I43+J42 -> -13905.433 | K43: =J43+K42 -> -16311.257 | L43: =K43+L42 -> -18666.907 | ... U43: =T43+U42 -> -32245.275
A44: Flag: cumulative net >= 0 | B44: flag | D44: =IF(D43>=0,1,0) -> 0 | E44: =IF(E43>=0,1,0) -> 0 | F44: =IF(F43>=0,1,0) -> 0 | G44: =IF(G43>=0,1,0) -> 0 | H44: =IF(H43>=0,1,0) -> 0 | I44: =IF(I43>=0,1,0) -> 0 | J44: =IF(J43>=0,1,0) -> 0 | K44: =IF(K43>=0,1,0) -> 0 | ... U44: =IF(U43>=0,1,0) -> 0
A45: Flag: monthly net >= 0 | B45: flag | D45: =IF(D42>=0,1,0) -> 0 | E45: =IF(E42>=0,1,0) -> 0 | F45: =IF(F42>=0,1,0) -> 0 | G45: =IF(G42>=0,1,0) -> 0 | H45: =IF(H42>=0,1,0) -> 0 | I45: =IF(I42>=0,1,0) -> 0 | J45: =IF(J42>=0,1,0) -> 0 | K45: =IF(K42>=0,1,0) -> 0 | ... U45: =IF(U42>=0,1,0) -> 0
A47: Cohort matrix: active users by acquisition cohort (rows) and month (columns)
A48: Cohort | B48: Cohort # | D48: M1 | E48: M2 | F48: M3 | G48: M4 | H48: M5 | I48: M6 | J48: M7 | K48: M8 | L48: M9 | M48: M10 | N48: M11 | O48: M12 | P48: M13 | Q48: M14 | R48: M15 | S48: M16 | T48: M17 | U48: M18
A49: Cohort M1 | B49: 1 | D49: =IF(D$4<$B49,0,INDEX($D$10:$U$10,$B49)*(1-Assumptions!$E$18)^(D$4-$B49)) -> 8750 | E49: =IF(E$4<$B49,0,INDEX($D$10:$U$10,$B49)*(1-Assumptions!$E$18)^(E$4-$B49)) -> 8312.5 | F49: =IF(F$4<$B49,0,INDEX($D$10:$U$10,$B49)*(1-Assumptions!$E$18)^(F$4-$B49)) -> 7896.875 | G49: =IF(G$4<$B49,0,INDEX($D$10:$U$10,$B49)*(1-Assumptions!$E$18)^(G$4-$B49)) -> 7502.0312 | H49: =IF(H$4<$B49,0,INDEX($D$10:$U$10,$B49)*(1-Assumptions!$E$18)^(H$4-$B49)) -> 7126.9297 | I49: =IF(I$4<$B49,0,INDEX($D$10:$U$10,$B49)*(1-Assumptions!$E$18)^(I$4-$B49)) -> 6770.5832 | J49: =IF(J$4<$B49,0,INDEX($D$10:$U$10,$B49)*(1-Assumptions!$E$18)^(J$4-$B49)) -> 6432.054 | K49: =IF(K$4<$B49,0,INDEX($D$10:$U$10,$B49)*(1-Assumptions!$E$18)^(K$4-$B49)) -> 6110.4513 | ... U49: =IF(U$4<$B49,0,INDEX($D$10:$U$10,$B49)*(1-Assumptions!$E$18)^(U$4-$B49)) -> 3658.5529
A50: Cohort M2 | B50: 2 | D50: =IF(D$4<$B50,0,INDEX($D$10:$U$10,$B50)*(1-Assumptions!$E$18)^(D$4-$B50)) -> 0 | E50: =IF(E$4<$B50,0,INDEX($D$10:$U$10,$B50)*(1-Assumptions!$E$18)^(E$4-$B50)) -> 13125 | F50: =IF(F$4<$B50,0,INDEX($D$10:$U$10,$B50)*(1-Assumptions!$E$18)^(F$4-$B50)) -> 12468.75 | G50: =IF(G$4<$B50,0,INDEX($D$10:$U$10,$B50)*(1-Assumptions!$E$18)^(G$4-$B50)) -> 11845.312 | H50: =IF(H$4<$B50,0,INDEX($D$10:$U$10,$B50)*(1-Assumptions!$E$18)^(H$4-$B50)) -> 11253.047 | I50: =IF(I$4<$B50,0,INDEX($D$10:$U$10,$B50)*(1-Assumptions!$E$18)^(I$4-$B50)) -> 10690.395 | J50: =IF(J$4<$B50,0,INDEX($D$10:$U$10,$B50)*(1-Assumptions!$E$18)^(J$4-$B50)) -> 10155.875 | K50: =IF(K$4<$B50,0,INDEX($D$10:$U$10,$B50)*(1-Assumptions!$E$18)^(K$4-$B50)) -> 9648.0811 | ... U50: =IF(U$4<$B50,0,INDEX($D$10:$U$10,$B50)*(1-Assumptions!$E$18)^(U$4-$B50)) -> 5776.6625
A51: Cohort M3 | B51: 3 | D51: =IF(D$4<$B51,0,INDEX($D$10:$U$10,$B51)*(1-Assumptions!$E$18)^(D$4-$B51)) -> 0 | E51: =IF(E$4<$B51,0,INDEX($D$10:$U$10,$B51)*(1-Assumptions!$E$18)^(E$4-$B51)) -> 0 | F51: =IF(F$4<$B51,0,INDEX($D$10:$U$10,$B51)*(1-Assumptions!$E$18)^(F$4-$B51)) -> 17500 | G51: =IF(G$4<$B51,0,INDEX($D$10:$U$10,$B51)*(1-Assumptions!$E$18)^(G$4-$B51)) -> 16625 | H51: =IF(H$4<$B51,0,INDEX($D$10:$U$10,$B51)*(1-Assumptions!$E$18)^(H$4-$B51)) -> 15793.75 | I51: =IF(I$4<$B51,0,INDEX($D$10:$U$10,$B51)*(1-Assumptions!$E$18)^(I$4-$B51)) -> 15004.062 | J51: =IF(J$4<$B51,0,INDEX($D$10:$U$10,$B51)*(1-Assumptions!$E$18)^(J$4-$B51)) -> 14253.859 | K51: =IF(K$4<$B51,0,INDEX($D$10:$U$10,$B51)*(1-Assumptions!$E$18)^(K$4-$B51)) -> 13541.166 | ... U51: =IF(U$4<$B51,0,INDEX($D$10:$U$10,$B51)*(1-Assumptions!$E$18)^(U$4-$B51)) -> 8107.5965
A52: Cohort M4 | B52: 4 | D52: =IF(D$4<$B52,0,INDEX($D$10:$U$10,$B52)*(1-Assumptions!$E$18)^(D$4-$B52)) -> 0 | E52: =IF(E$4<$B52,0,INDEX($D$10:$U$10,$B52)*(1-Assumptions!$E$18)^(E$4-$B52)) -> 0 | F52: =IF(F$4<$B52,0,INDEX($D$10:$U$10,$B52)*(1-Assumptions!$E$18)^(F$4-$B52)) -> 0 | G52: =IF(G$4<$B52,0,INDEX($D$10:$U$10,$B52)*(1-Assumptions!$E$18)^(G$4-$B52)) -> 21875 | H52: =IF(H$4<$B52,0,INDEX($D$10:$U$10,$B52)*(1-Assumptions!$E$18)^(H$4-$B52)) -> 20781.25 | I52: =IF(I$4<$B52,0,INDEX($D$10:$U$10,$B52)*(1-Assumptions!$E$18)^(I$4-$B52)) -> 19742.188 | J52: =IF(J$4<$B52,0,INDEX($D$10:$U$10,$B52)*(1-Assumptions!$E$18)^(J$4-$B52)) -> 18755.078 | K52: =IF(K$4<$B52,0,INDEX($D$10:$U$10,$B52)*(1-Assumptions!$E$18)^(K$4-$B52)) -> 17817.324 | ... U52: =IF(U$4<$B52,0,INDEX($D$10:$U$10,$B52)*(1-Assumptions!$E$18)^(U$4-$B52)) -> 10667.89
A53: Cohort M5 | B53: 5 | D53: =IF(D$4<$B53,0,INDEX($D$10:$U$10,$B53)*(1-Assumptions!$E$18)^(D$4-$B53)) -> 0 | E53: =IF(E$4<$B53,0,INDEX($D$10:$U$10,$B53)*(1-Assumptions!$E$18)^(E$4-$B53)) -> 0 | F53: =IF(F$4<$B53,0,INDEX($D$10:$U$10,$B53)*(1-Assumptions!$E$18)^(F$4-$B53)) -> 0 | G53: =IF(G$4<$B53,0,INDEX($D$10:$U$10,$B53)*(1-Assumptions!$E$18)^(G$4-$B53)) -> 0 | H53: =IF(H$4<$B53,0,INDEX($D$10:$U$10,$B53)*(1-Assumptions!$E$18)^(H$4-$B53)) -> 26250 | I53: =IF(I$4<$B53,0,INDEX($D$10:$U$10,$B53)*(1-Assumptions!$E$18)^(I$4-$B53)) -> 24937.5 | J53: =IF(J$4<$B53,0,INDEX($D$10:$U$10,$B53)*(1-Assumptions!$E$18)^(J$4-$B53)) -> 23690.625 | K53: =IF(K$4<$B53,0,INDEX($D$10:$U$10,$B53)*(1-Assumptions!$E$18)^(K$4-$B53)) -> 22506.094 | ... U53: =IF(U$4<$B53,0,INDEX($D$10:$U$10,$B53)*(1-Assumptions!$E$18)^(U$4-$B53)) -> 13475.23
A54: Cohort M6 | B54: 6 | D54: =IF(D$4<$B54,0,INDEX($D$10:$U$10,$B54)*(1-Assumptions!$E$18)^(D$4-$B54)) -> 0 | E54: =IF(E$4<$B54,0,INDEX($D$10:$U$10,$B54)*(1-Assumptions!$E$18)^(E$4-$B54)) -> 0 | F54: =IF(F$4<$B54,0,INDEX($D$10:$U$10,$B54)*(1-Assumptions!$E$18)^(F$4-$B54)) -> 0 | G54: =IF(G$4<$B54,0,INDEX($D$10:$U$10,$B54)*(1-Assumptions!$E$18)^(G$4-$B54)) -> 0 | H54: =IF(H$4<$B54,0,INDEX($D$10:$U$10,$B54)*(1-Assumptions!$E$18)^(H$4-$B54)) -> 0 | I54: =IF(I$4<$B54,0,INDEX($D$10:$U$10,$B54)*(1-Assumptions!$E$18)^(I$4-$B54)) -> 30625 | J54: =IF(J$4<$B54,0,INDEX($D$10:$U$10,$B54)*(1-Assumptions!$E$18)^(J$4-$B54)) -> 29093.75 | K54: =IF(K$4<$B54,0,INDEX($D$10:$U$10,$B54)*(1-Assumptions!$E$18)^(K$4-$B54)) -> 27639.062 | ... U54: =IF(U$4<$B54,0,INDEX($D$10:$U$10,$B54)*(1-Assumptions!$E$18)^(U$4-$B54)) -> 16548.528
A55: Cohort M7 | B55: 7 | D55: =IF(D$4<$B55,0,INDEX($D$10:$U$10,$B55)*(1-Assumptions!$E$18)^(D$4-$B55)) -> 0 | E55: =IF(E$4<$B55,0,INDEX($D$10:$U$10,$B55)*(1-Assumptions!$E$18)^(E$4-$B55)) -> 0 | F55: =IF(F$4<$B55,0,INDEX($D$10:$U$10,$B55)*(1-Assumptions!$E$18)^(F$4-$B55)) -> 0 | G55: =IF(G$4<$B55,0,INDEX($D$10:$U$10,$B55)*(1-Assumptions!$E$18)^(G$4-$B55)) -> 0 | H55: =IF(H$4<$B55,0,INDEX($D$10:$U$10,$B55)*(1-Assumptions!$E$18)^(H$4-$B55)) -> 0 | I55: =IF(I$4<$B55,0,INDEX($D$10:$U$10,$B55)*(1-Assumptions!$E$18)^(I$4-$B55)) -> 0 | J55: =IF(J$4<$B55,0,INDEX($D$10:$U$10,$B55)*(1-Assumptions!$E$18)^(J$4-$B55)) -> 30625 | K55: =IF(K$4<$B55,0,INDEX($D$10:$U$10,$B55)*(1-Assumptions!$E$18)^(K$4-$B55)) -> 29093.75 | ... U55: =IF(U$4<$B55,0,INDEX($D$10:$U$10,$B55)*(1-Assumptions!$E$18)^(U$4-$B55)) -> 17419.503
A56: Cohort M8 | B56: 8 | D56: =IF(D$4<$B56,0,INDEX($D$10:$U$10,$B56)*(1-Assumptions!$E$18)^(D$4-$B56)) -> 0 | E56: =IF(E$4<$B56,0,INDEX($D$10:$U$10,$B56)*(1-Assumptions!$E$18)^(E$4-$B56)) -> 0 | F56: =IF(F$4<$B56,0,INDEX($D$10:$U$10,$B56)*(1-Assumptions!$E$18)^(F$4-$B56)) -> 0 | G56: =IF(G$4<$B56,0,INDEX($D$10:$U$10,$B56)*(1-Assumptions!$E$18)^(G$4-$B56)) -> 0 | H56: =IF(H$4<$B56,0,INDEX($D$10:$U$10,$B56)*(1-Assumptions!$E$18)^(H$4-$B56)) -> 0 | I56: =IF(I$4<$B56,0,INDEX($D$10:$U$10,$B56)*(1-Assumptions!$E$18)^(I$4-$B56)) -> 0 | J56: =IF(J$4<$B56,0,INDEX($D$10:$U$10,$B56)*(1-Assumptions!$E$18)^(J$4-$B56)) -> 0 | K56: =IF(K$4<$B56,0,INDEX($D$10:$U$10,$B56)*(1-Assumptions!$E$18)^(K$4-$B56)) -> 30625 | ... U56: =IF(U$4<$B56,0,INDEX($D$10:$U$10,$B56)*(1-Assumptions!$E$18)^(U$4-$B56)) -> 18336.319
A57: Cohort M9 | B57: 9 | D57: =IF(D$4<$B57,0,INDEX($D$10:$U$10,$B57)*(1-Assumptions!$E$18)^(D$4-$B57)) -> 0 | E57: =IF(E$4<$B57,0,INDEX($D$10:$U$10,$B57)*(1-Assumptions!$E$18)^(E$4-$B57)) -> 0 | F57: =IF(F$4<$B57,0,INDEX($D$10:$U$10,$B57)*(1-Assumptions!$E$18)^(F$4-$B57)) -> 0 | G57: =IF(G$4<$B57,0,INDEX($D$10:$U$10,$B57)*(1-Assumptions!$E$18)^(G$4-$B57)) -> 0 | H57: =IF(H$4<$B57,0,INDEX($D$10:$U$10,$B57)*(1-Assumptions!$E$18)^(H$4-$B57)) -> 0 | I57: =IF(I$4<$B57,0,INDEX($D$10:$U$10,$B57)*(1-Assumptions!$E$18)^(I$4-$B57)) -> 0 | J57: =IF(J$4<$B57,0,INDEX($D$10:$U$10,$B57)*(1-Assumptions!$E$18)^(J$4-$B57)) -> 0 | K57: =IF(K$4<$B57,0,INDEX($D$10:$U$10,$B57)*(1-Assumptions!$E$18)^(K$4-$B57)) -> 0 | ... U57: =IF(U$4<$B57,0,INDEX($D$10:$U$10,$B57)*(1-Assumptions!$E$18)^(U$4-$B57)) -> 19301.388
A58: Cohort M10 | B58: 10 | D58: =IF(D$4<$B58,0,INDEX($D$10:$U$10,$B58)*(1-Assumptions!$E$18)^(D$4-$B58)) -> 0 | E58: =IF(E$4<$B58,0,INDEX($D$10:$U$10,$B58)*(1-Assumptions!$E$18)^(E$4-$B58)) -> 0 | F58: =IF(F$4<$B58,0,INDEX($D$10:$U$10,$B58)*(1-Assumptions!$E$18)^(F$4-$B58)) -> 0 | G58: =IF(G$4<$B58,0,INDEX($D$10:$U$10,$B58)*(1-Assumptions!$E$18)^(G$4-$B58)) -> 0 | H58: =IF(H$4<$B58,0,INDEX($D$10:$U$10,$B58)*(1-Assumptions!$E$18)^(H$4-$B58)) -> 0 | I58: =IF(I$4<$B58,0,INDEX($D$10:$U$10,$B58)*(1-Assumptions!$E$18)^(I$4-$B58)) -> 0 | J58: =IF(J$4<$B58,0,INDEX($D$10:$U$10,$B58)*(1-Assumptions!$E$18)^(J$4-$B58)) -> 0 | K58: =IF(K$4<$B58,0,INDEX($D$10:$U$10,$B58)*(1-Assumptions!$E$18)^(K$4-$B58)) -> 0 | ... U58: =IF(U$4<$B58,0,INDEX($D$10:$U$10,$B58)*(1-Assumptions!$E$18)^(U$4-$B58)) -> 20317.251
A59: Cohort M11 | B59: 11 | D59: =IF(D$4<$B59,0,INDEX($D$10:$U$10,$B59)*(1-Assumptions!$E$18)^(D$4-$B59)) -> 0 | E59: =IF(E$4<$B59,0,INDEX($D$10:$U$10,$B59)*(1-Assumptions!$E$18)^(E$4-$B59)) -> 0 | F59: =IF(F$4<$B59,0,INDEX($D$10:$U$10,$B59)*(1-Assumptions!$E$18)^(F$4-$B59)) -> 0 | G59: =IF(G$4<$B59,0,INDEX($D$10:$U$10,$B59)*(1-Assumptions!$E$18)^(G$4-$B59)) -> 0 | H59: =IF(H$4<$B59,0,INDEX($D$10:$U$10,$B59)*(1-Assumptions!$E$18)^(H$4-$B59)) -> 0 | I59: =IF(I$4<$B59,0,INDEX($D$10:$U$10,$B59)*(1-Assumptions!$E$18)^(I$4-$B59)) -> 0 | J59: =IF(J$4<$B59,0,INDEX($D$10:$U$10,$B59)*(1-Assumptions!$E$18)^(J$4-$B59)) -> 0 | K59: =IF(K$4<$B59,0,INDEX($D$10:$U$10,$B59)*(1-Assumptions!$E$18)^(K$4-$B59)) -> 0 | ... U59: =IF(U$4<$B59,0,INDEX($D$10:$U$10,$B59)*(1-Assumptions!$E$18)^(U$4-$B59)) -> 18331.354
A60: Cohort M12 | B60: 12 | D60: =IF(D$4<$B60,0,INDEX($D$10:$U$10,$B60)*(1-Assumptions!$E$18)^(D$4-$B60)) -> 0 | E60: =IF(E$4<$B60,0,INDEX($D$10:$U$10,$B60)*(1-Assumptions!$E$18)^(E$4-$B60)) -> 0 | F60: =IF(F$4<$B60,0,INDEX($D$10:$U$10,$B60)*(1-Assumptions!$E$18)^(F$4-$B60)) -> 0 | G60: =IF(G$4<$B60,0,INDEX($D$10:$U$10,$B60)*(1-Assumptions!$E$18)^(G$4-$B60)) -> 0 | H60: =IF(H$4<$B60,0,INDEX($D$10:$U$10,$B60)*(1-Assumptions!$E$18)^(H$4-$B60)) -> 0 | I60: =IF(I$4<$B60,0,INDEX($D$10:$U$10,$B60)*(1-Assumptions!$E$18)^(I$4-$B60)) -> 0 | J60: =IF(J$4<$B60,0,INDEX($D$10:$U$10,$B60)*(1-Assumptions!$E$18)^(J$4-$B60)) -> 0 | K60: =IF(K$4<$B60,0,INDEX($D$10:$U$10,$B60)*(1-Assumptions!$E$18)^(K$4-$B60)) -> 0 | ... U60: =IF(U$4<$B60,0,INDEX($D$10:$U$10,$B60)*(1-Assumptions!$E$18)^(U$4-$B60)) -> 19296.162
... A66: Cohort M18 | B66: 18 | D66: =IF(D$4<$B66,0,INDEX($D$10:$U$10,$B66)*(1-Assumptions!$E$18)^(D$4-$B66)) -> 0 | E66: =IF(E$4<$B66,0,INDEX($D$10:$U$10,$B66)*(1-Assumptions!$E$18)^(E$4-$B66)) -> 0 | F66: =IF(F$4<$B66,0,INDEX($D$10:$U$10,$B66)*(1-Assumptions!$E$18)^(F$4-$B66)) -> 0 | G66: =IF(G$4<$B66,0,INDEX($D$10:$U$10,$B66)*(1-Assumptions!$E$18)^(G$4-$B66)) -> 0 | H66: =IF(H$4<$B66,0,INDEX($D$10:$U$10,$B66)*(1-Assumptions!$E$18)^(H$4-$B66)) -> 0 | I66: =IF(I$4<$B66,0,INDEX($D$10:$U$10,$B66)*(1-Assumptions!$E$18)^(I$4-$B66)) -> 0 | J66: =IF(J$4<$B66,0,INDEX($D$10:$U$10,$B66)*(1-Assumptions!$E$18)^(J$4-$B66)) -> 0 | K66: =IF(K$4<$B66,0,INDEX($D$10:$U$10,$B66)*(1-Assumptions!$E$18)^(K$4-$B66)) -> 0 | ... U66: =IF(U$4<$B66,0,INDEX($D$10:$U$10,$B66)*(1-Assumptions!$E$18)^(U$4-$B66)) -> 17500
A69: Cohort matrix: active users x bonus rate (feeds weighted average bonus rate)
A70: Cohort | B70: Cohort # | D70: M1 | E70: M2 | F70: M3 | G70: M4 | H70: M5 | I70: M6 | J70: M7 | K70: M8 | L70: M9 | M70: M10 | N70: M11 | O70: M12 | P70: M13 | Q70: M14 | R70: M15 | S70: M16 | T70: M17 | U70: M18
A71: Cohort M1 | B71: 1 | D71: =IF(OR(D$4<Assumptions!$E$32,D$4<$B71),0,D49*IF(D$4>=Assumptions!$E$33,INDEX($D$94:$D$111,D$4-MAX($B71,Assumptions!$E$32)+1),INDEX($C$94:$C$111,D$4-MAX($B71,Assumptions!$E$32)+1))) -> 0 | E71: =IF(OR(E$4<Assumptions!$E$32,E$4<$B71),0,E49*IF(E$4>=Assumptions!$E$33,INDEX($D$94:$D$111,E$4-MAX($B71,Assumptions!$E$32)+1),INDEX($C$94:$C$111,E$4-MAX($B71,Assumptions!$E$32)+1))) -> 0 | F71: =IF(OR(F$4<Assumptions!$E$32,F$4<$B71),0,F49*IF(F$4>=Assumptions!$E$33,INDEX($D$94:$D$111,F$4-MAX($B71,Assumptions!$E$32)+1),INDEX($C$94:$C$111,F$4-MAX($B71,Assumptions!$E$32)+1))) -> 0 | G71: =IF(OR(G$4<Assumptions!$E$32,G$4<$B71),0,G49*IF(G$4>=Assumptions!$E$33,INDEX($D$94:$D$111,G$4-MAX($B71,Assumptions!$E$32)+1),INDEX($C$94:$C$111,G$4-MAX($B71,Assumptions!$E$32)+1))) -> 3.0008125 | H71: =IF(OR(H$4<Assumptions!$E$32,H$4<$B71),0,H49*IF(H$4>=Assumptions!$E$33,INDEX($D$94:$D$111,H$4-MAX($B71,Assumptions!$E$32)+1),INDEX($C$94:$C$111,H$4-MAX($B71,Assumptions!$E$32)+1))) -> 5.7015437 | I71: =IF(OR(I$4<Assumptions!$E$32,I$4<$B71),0,I49*IF(I$4>=Assumptions!$E$33,INDEX($D$94:$D$111,I$4-MAX($B71,Assumptions!$E$32)+1),INDEX($C$94:$C$111,I$4-MAX($B71,Assumptions!$E$32)+1))) -> 8.1246998 | J71: =IF(OR(J$4<Assumptions!$E$32,J$4<$B71),0,J49*IF(J$4>=Assumptions!$E$33,INDEX($D$94:$D$111,J$4-MAX($B71,Assumptions!$E$32)+1),INDEX($C$94:$C$111,J$4-MAX($B71,Assumptions!$E$32)+1))) -> 12.864108 | K71: =IF(OR(K$4<Assumptions!$E$32,K$4<$B71),0,K49*IF(K$4>=Assumptions!$E$33,INDEX($D$94:$D$111,K$4-MAX($B71,Assumptions!$E$32)+1),INDEX($C$94:$C$111,K$4-MAX($B71,Assumptions!$E$32)+1))) -> 12.954157 | ... U71: =IF(OR(U$4<Assumptions!$E$32,U$4<$B71),0,U49*IF(U$4>=Assumptions!$E$33,INDEX($D$94:$D$111,U$4-MAX($B71,Assumptions!$E$32)+1),INDEX($C$94:$C$111,U$4-MAX($B71,Assumptions!$E$32)+1))) -> 8.6341849
A72: Cohort M2 | B72: 2 | D72: =IF(OR(D$4<Assumptions!$E$32,D$4<$B72),0,D50*IF(D$4>=Assumptions!$E$33,INDEX($D$94:$D$111,D$4-MAX($B72,Assumptions!$E$32)+1),INDEX($C$94:$C$111,D$4-MAX($B72,Assumptions!$E$32)+1))) -> 0 | E72: =IF(OR(E$4<Assumptions!$E$32,E$4<$B72),0,E50*IF(E$4>=Assumptions!$E$33,INDEX($D$94:$D$111,E$4-MAX($B72,Assumptions!$E$32)+1),INDEX($C$94:$C$111,E$4-MAX($B72,Assumptions!$E$32)+1))) -> 0 | F72: =IF(OR(F$4<Assumptions!$E$32,F$4<$B72),0,F50*IF(F$4>=Assumptions!$E$33,INDEX($D$94:$D$111,F$4-MAX($B72,Assumptions!$E$32)+1),INDEX($C$94:$C$111,F$4-MAX($B72,Assumptions!$E$32)+1))) -> 0 | G72: =IF(OR(G$4<Assumptions!$E$32,G$4<$B72),0,G50*IF(G$4>=Assumptions!$E$33,INDEX($D$94:$D$111,G$4-MAX($B72,Assumptions!$E$32)+1),INDEX($C$94:$C$111,G$4-MAX($B72,Assumptions!$E$32)+1))) -> 4.738125 | H72: =IF(OR(H$4<Assumptions!$E$32,H$4<$B72),0,H50*IF(H$4>=Assumptions!$E$33,INDEX($D$94:$D$111,H$4-MAX($B72,Assumptions!$E$32)+1),INDEX($C$94:$C$111,H$4-MAX($B72,Assumptions!$E$32)+1))) -> 9.0024375 | I72: =IF(OR(I$4<Assumptions!$E$32,I$4<$B72),0,I50*IF(I$4>=Assumptions!$E$33,INDEX($D$94:$D$111,I$4-MAX($B72,Assumptions!$E$32)+1),INDEX($C$94:$C$111,I$4-MAX($B72,Assumptions!$E$32)+1))) -> 12.828473 | J72: =IF(OR(J$4<Assumptions!$E$32,J$4<$B72),0,J50*IF(J$4>=Assumptions!$E$33,INDEX($D$94:$D$111,J$4-MAX($B72,Assumptions!$E$32)+1),INDEX($C$94:$C$111,J$4-MAX($B72,Assumptions!$E$32)+1))) -> 20.31175 | K72: =IF(OR(K$4<Assumptions!$E$32,K$4<$B72),0,K50*IF(K$4>=Assumptions!$E$33,INDEX($D$94:$D$111,K$4-MAX($B72,Assumptions!$E$32)+1),INDEX($C$94:$C$111,K$4-MAX($B72,Assumptions!$E$32)+1))) -> 20.453932 | ... U72: =IF(OR(U$4<Assumptions!$E$32,U$4<$B72),0,U50*IF(U$4>=Assumptions!$E$33,INDEX($D$94:$D$111,U$4-MAX($B72,Assumptions!$E$32)+1),INDEX($C$94:$C$111,U$4-MAX($B72,Assumptions!$E$32)+1))) -> 13.632924
A73: Cohort M3 | B73: 3 | D73: =IF(OR(D$4<Assumptions!$E$32,D$4<$B73),0,D51*IF(D$4>=Assumptions!$E$33,INDEX($D$94:$D$111,D$4-MAX($B73,Assumptions!$E$32)+1),INDEX($C$94:$C$111,D$4-MAX($B73,Assumptions!$E$32)+1))) -> 0 | E73: =IF(OR(E$4<Assumptions!$E$32,E$4<$B73),0,E51*IF(E$4>=Assumptions!$E$33,INDEX($D$94:$D$111,E$4-MAX($B73,Assumptions!$E$32)+1),INDEX($C$94:$C$111,E$4-MAX($B73,Assumptions!$E$32)+1))) -> 0 | F73: =IF(OR(F$4<Assumptions!$E$32,F$4<$B73),0,F51*IF(F$4>=Assumptions!$E$33,INDEX($D$94:$D$111,F$4-MAX($B73,Assumptions!$E$32)+1),INDEX($C$94:$C$111,F$4-MAX($B73,Assumptions!$E$32)+1))) -> 0 | G73: =IF(OR(G$4<Assumptions!$E$32,G$4<$B73),0,G51*IF(G$4>=Assumptions!$E$33,INDEX($D$94:$D$111,G$4-MAX($B73,Assumptions!$E$32)+1),INDEX($C$94:$C$111,G$4-MAX($B73,Assumptions!$E$32)+1))) -> 6.65 | H73: =IF(OR(H$4<Assumptions!$E$32,H$4<$B73),0,H51*IF(H$4>=Assumptions!$E$33,INDEX($D$94:$D$111,H$4-MAX($B73,Assumptions!$E$32)+1),INDEX($C$94:$C$111,H$4-MAX($B73,Assumptions!$E$32)+1))) -> 12.635 | I73: =IF(OR(I$4<Assumptions!$E$32,I$4<$B73),0,I51*IF(I$4>=Assumptions!$E$33,INDEX($D$94:$D$111,I$4-MAX($B73,Assumptions!$E$32)+1),INDEX($C$94:$C$111,I$4-MAX($B73,Assumptions!$E$32)+1))) -> 18.004875 | J73: =IF(OR(J$4<Assumptions!$E$32,J$4<$B73),0,J51*IF(J$4>=Assumptions!$E$33,INDEX($D$94:$D$111,J$4-MAX($B73,Assumptions!$E$32)+1),INDEX($C$94:$C$111,J$4-MAX($B73,Assumptions!$E$32)+1))) -> 28.507719 | K73: =IF(OR(K$4<Assumptions!$E$32,K$4<$B73),0,K51*IF(K$4>=Assumptions!$E$33,INDEX($D$94:$D$111,K$4-MAX($B73,Assumptions!$E$32)+1),INDEX($C$94:$C$111,K$4-MAX($B73,Assumptions!$E$32)+1))) -> 28.707273 | ... U73: =IF(OR(U$4<Assumptions!$E$32,U$4<$B73),0,U51*IF(U$4>=Assumptions!$E$33,INDEX($D$94:$D$111,U$4-MAX($B73,Assumptions!$E$32)+1),INDEX($C$94:$C$111,U$4-MAX($B73,Assumptions!$E$32)+1))) -> 19.133928
A74: Cohort M4 | B74: 4 | D74: =IF(OR(D$4<Assumptions!$E$32,D$4<$B74),0,D52*IF(D$4>=Assumptions!$E$33,INDEX($D$94:$D$111,D$4-MAX($B74,Assumptions!$E$32)+1),INDEX($C$94:$C$111,D$4-MAX($B74,Assumptions!$E$32)+1))) -> 0 | E74: =IF(OR(E$4<Assumptions!$E$32,E$4<$B74),0,E52*IF(E$4>=Assumptions!$E$33,INDEX($D$94:$D$111,E$4-MAX($B74,Assumptions!$E$32)+1),INDEX($C$94:$C$111,E$4-MAX($B74,Assumptions!$E$32)+1))) -> 0 | F74: =IF(OR(F$4<Assumptions!$E$32,F$4<$B74),0,F52*IF(F$4>=Assumptions!$E$33,INDEX($D$94:$D$111,F$4-MAX($B74,Assumptions!$E$32)+1),INDEX($C$94:$C$111,F$4-MAX($B74,Assumptions!$E$32)+1))) -> 0 | G74: =IF(OR(G$4<Assumptions!$E$32,G$4<$B74),0,G52*IF(G$4>=Assumptions!$E$33,INDEX($D$94:$D$111,G$4-MAX($B74,Assumptions!$E$32)+1),INDEX($C$94:$C$111,G$4-MAX($B74,Assumptions!$E$32)+1))) -> 8.75 | H74: =IF(OR(H$4<Assumptions!$E$32,H$4<$B74),0,H52*IF(H$4>=Assumptions!$E$33,INDEX($D$94:$D$111,H$4-MAX($B74,Assumptions!$E$32)+1),INDEX($C$94:$C$111,H$4-MAX($B74,Assumptions!$E$32)+1))) -> 16.625 | I74: =IF(OR(I$4<Assumptions!$E$32,I$4<$B74),0,I52*IF(I$4>=Assumptions!$E$33,INDEX($D$94:$D$111,I$4-MAX($B74,Assumptions!$E$32)+1),INDEX($C$94:$C$111,I$4-MAX($B74,Assumptions!$E$32)+1))) -> 23.690625 | J74: =IF(OR(J$4<Assumptions!$E$32,J$4<$B74),0,J52*IF(J$4>=Assumptions!$E$33,INDEX($D$94:$D$111,J$4-MAX($B74,Assumptions!$E$32)+1),INDEX($C$94:$C$111,J$4-MAX($B74,Assumptions!$E$32)+1))) -> 37.510156 | K74: =IF(OR(K$4<Assumptions!$E$32,K$4<$B74),0,K52*IF(K$4>=Assumptions!$E$33,INDEX($D$94:$D$111,K$4-MAX($B74,Assumptions!$E$32)+1),INDEX($C$94:$C$111,K$4-MAX($B74,Assumptions!$E$32)+1))) -> 37.772727 | ... U74: =IF(OR(U$4<Assumptions!$E$32,U$4<$B74),0,U52*IF(U$4>=Assumptions!$E$33,INDEX($D$94:$D$111,U$4-MAX($B74,Assumptions!$E$32)+1),INDEX($C$94:$C$111,U$4-MAX($B74,Assumptions!$E$32)+1))) -> 25.176221
A75: Cohort M5 | B75: 5 | D75: =IF(OR(D$4<Assumptions!$E$32,D$4<$B75),0,D53*IF(D$4>=Assumptions!$E$33,INDEX($D$94:$D$111,D$4-MAX($B75,Assumptions!$E$32)+1),INDEX($C$94:$C$111,D$4-MAX($B75,Assumptions!$E$32)+1))) -> 0 | E75: =IF(OR(E$4<Assumptions!$E$32,E$4<$B75),0,E53*IF(E$4>=Assumptions!$E$33,INDEX($D$94:$D$111,E$4-MAX($B75,Assumptions!$E$32)+1),INDEX($C$94:$C$111,E$4-MAX($B75,Assumptions!$E$32)+1))) -> 0 | F75: =IF(OR(F$4<Assumptions!$E$32,F$4<$B75),0,F53*IF(F$4>=Assumptions!$E$33,INDEX($D$94:$D$111,F$4-MAX($B75,Assumptions!$E$32)+1),INDEX($C$94:$C$111,F$4-MAX($B75,Assumptions!$E$32)+1))) -> 0 | G75: =IF(OR(G$4<Assumptions!$E$32,G$4<$B75),0,G53*IF(G$4>=Assumptions!$E$33,INDEX($D$94:$D$111,G$4-MAX($B75,Assumptions!$E$32)+1),INDEX($C$94:$C$111,G$4-MAX($B75,Assumptions!$E$32)+1))) -> 0 | H75: =IF(OR(H$4<Assumptions!$E$32,H$4<$B75),0,H53*IF(H$4>=Assumptions!$E$33,INDEX($D$94:$D$111,H$4-MAX($B75,Assumptions!$E$32)+1),INDEX($C$94:$C$111,H$4-MAX($B75,Assumptions!$E$32)+1))) -> 10.5 | I75: =IF(OR(I$4<Assumptions!$E$32,I$4<$B75),0,I53*IF(I$4>=Assumptions!$E$33,INDEX($D$94:$D$111,I$4-MAX($B75,Assumptions!$E$32)+1),INDEX($C$94:$C$111,I$4-MAX($B75,Assumptions!$E$32)+1))) -> 19.95 | J75: =IF(OR(J$4<Assumptions!$E$32,J$4<$B75),0,J53*IF(J$4>=Assumptions!$E$33,INDEX($D$94:$D$111,J$4-MAX($B75,Assumptions!$E$32)+1),INDEX($C$94:$C$111,J$4-MAX($B75,Assumptions!$E$32)+1))) -> 28.42875 | K75: =IF(OR(K$4<Assumptions!$E$32,K$4<$B75),0,K53*IF(K$4>=Assumptions!$E$33,INDEX($D$94:$D$111,K$4-MAX($B75,Assumptions!$E$32)+1),INDEX($C$94:$C$111,K$4-MAX($B75,Assumptions!$E$32)+1))) -> 45.012188 | ... U75: =IF(OR(U$4<Assumptions!$E$32,U$4<$B75),0,U53*IF(U$4>=Assumptions!$E$33,INDEX($D$94:$D$111,U$4-MAX($B75,Assumptions!$E$32)+1),INDEX($C$94:$C$111,U$4-MAX($B75,Assumptions!$E$32)+1))) -> 31.801542
A76: Cohort M6 | B76: 6 | D76: =IF(OR(D$4<Assumptions!$E$32,D$4<$B76),0,D54*IF(D$4>=Assumptions!$E$33,INDEX($D$94:$D$111,D$4-MAX($B76,Assumptions!$E$32)+1),INDEX($C$94:$C$111,D$4-MAX($B76,Assumptions!$E$32)+1))) -> 0 | E76: =IF(OR(E$4<Assumptions!$E$32,E$4<$B76),0,E54*IF(E$4>=Assumptions!$E$33,INDEX($D$94:$D$111,E$4-MAX($B76,Assumptions!$E$32)+1),INDEX($C$94:$C$111,E$4-MAX($B76,Assumptions!$E$32)+1))) -> 0 | F76: =IF(OR(F$4<Assumptions!$E$32,F$4<$B76),0,F54*IF(F$4>=Assumptions!$E$33,INDEX($D$94:$D$111,F$4-MAX($B76,Assumptions!$E$32)+1),INDEX($C$94:$C$111,F$4-MAX($B76,Assumptions!$E$32)+1))) -> 0 | G76: =IF(OR(G$4<Assumptions!$E$32,G$4<$B76),0,G54*IF(G$4>=Assumptions!$E$33,INDEX($D$94:$D$111,G$4-MAX($B76,Assumptions!$E$32)+1),INDEX($C$94:$C$111,G$4-MAX($B76,Assumptions!$E$32)+1))) -> 0 | H76: =IF(OR(H$4<Assumptions!$E$32,H$4<$B76),0,H54*IF(H$4>=Assumptions!$E$33,INDEX($D$94:$D$111,H$4-MAX($B76,Assumptions!$E$32)+1),INDEX($C$94:$C$111,H$4-MAX($B76,Assumptions!$E$32)+1))) -> 0 | I76: =IF(OR(I$4<Assumptions!$E$32,I$4<$B76),0,I54*IF(I$4>=Assumptions!$E$33,INDEX($D$94:$D$111,I$4-MAX($B76,Assumptions!$E$32)+1),INDEX($C$94:$C$111,I$4-MAX($B76,Assumptions!$E$32)+1))) -> 12.25 | J76: =IF(OR(J$4<Assumptions!$E$32,J$4<$B76),0,J54*IF(J$4>=Assumptions!$E$33,INDEX($D$94:$D$111,J$4-MAX($B76,Assumptions!$E$32)+1),INDEX($C$94:$C$111,J$4-MAX($B76,Assumptions!$E$32)+1))) -> 23.275 | K76: =IF(OR(K$4<Assumptions!$E$32,K$4<$B76),0,K54*IF(K$4>=Assumptions!$E$33,INDEX($D$94:$D$111,K$4-MAX($B76,Assumptions!$E$32)+1),INDEX($C$94:$C$111,K$4-MAX($B76,Assumptions!$E$32)+1))) -> 33.166875 | ... U76: =IF(OR(U$4<Assumptions!$E$32,U$4<$B76),0,U54*IF(U$4>=Assumptions!$E$33,INDEX($D$94:$D$111,U$4-MAX($B76,Assumptions!$E$32)+1),INDEX($C$94:$C$111,U$4-MAX($B76,Assumptions!$E$32)+1))) -> 39.054525
A77: Cohort M7 | B77: 7 | D77: =IF(OR(D$4<Assumptions!$E$32,D$4<$B77),0,D55*IF(D$4>=Assumptions!$E$33,INDEX($D$94:$D$111,D$4-MAX($B77,Assumptions!$E$32)+1),INDEX($C$94:$C$111,D$4-MAX($B77,Assumptions!$E$32)+1))) -> 0 | E77: =IF(OR(E$4<Assumptions!$E$32,E$4<$B77),0,E55*IF(E$4>=Assumptions!$E$33,INDEX($D$94:$D$111,E$4-MAX($B77,Assumptions!$E$32)+1),INDEX($C$94:$C$111,E$4-MAX($B77,Assumptions!$E$32)+1))) -> 0 | F77: =IF(OR(F$4<Assumptions!$E$32,F$4<$B77),0,F55*IF(F$4>=Assumptions!$E$33,INDEX($D$94:$D$111,F$4-MAX($B77,Assumptions!$E$32)+1),INDEX($C$94:$C$111,F$4-MAX($B77,Assumptions!$E$32)+1))) -> 0 | G77: =IF(OR(G$4<Assumptions!$E$32,G$4<$B77),0,G55*IF(G$4>=Assumptions!$E$33,INDEX($D$94:$D$111,G$4-MAX($B77,Assumptions!$E$32)+1),INDEX($C$94:$C$111,G$4-MAX($B77,Assumptions!$E$32)+1))) -> 0 | H77: =IF(OR(H$4<Assumptions!$E$32,H$4<$B77),0,H55*IF(H$4>=Assumptions!$E$33,INDEX($D$94:$D$111,H$4-MAX($B77,Assumptions!$E$32)+1),INDEX($C$94:$C$111,H$4-MAX($B77,Assumptions!$E$32)+1))) -> 0 | I77: =IF(OR(I$4<Assumptions!$E$32,I$4<$B77),0,I55*IF(I$4>=Assumptions!$E$33,INDEX($D$94:$D$111,I$4-MAX($B77,Assumptions!$E$32)+1),INDEX($C$94:$C$111,I$4-MAX($B77,Assumptions!$E$32)+1))) -> 0 | J77: =IF(OR(J$4<Assumptions!$E$32,J$4<$B77),0,J55*IF(J$4>=Assumptions!$E$33,INDEX($D$94:$D$111,J$4-MAX($B77,Assumptions!$E$32)+1),INDEX($C$94:$C$111,J$4-MAX($B77,Assumptions!$E$32)+1))) -> 12.25 | K77: =IF(OR(K$4<Assumptions!$E$32,K$4<$B77),0,K55*IF(K$4>=Assumptions!$E$33,INDEX($D$94:$D$111,K$4-MAX($B77,Assumptions!$E$32)+1),INDEX($C$94:$C$111,K$4-MAX($B77,Assumptions!$E$32)+1))) -> 23.275 | ... U77: =IF(OR(U$4<Assumptions!$E$32,U$4<$B77),0,U55*IF(U$4>=Assumptions!$E$33,INDEX($D$94:$D$111,U$4-MAX($B77,Assumptions!$E$32)+1),INDEX($C$94:$C$111,U$4-MAX($B77,Assumptions!$E$32)+1))) -> 41.110027
A78: Cohort M8 | B78: 8 | D78: =IF(OR(D$4<Assumptions!$E$32,D$4<$B78),0,D56*IF(D$4>=Assumptions!$E$33,INDEX($D$94:$D$111,D$4-MAX($B78,Assumptions!$E$32)+1),INDEX($C$94:$C$111,D$4-MAX($B78,Assumptions!$E$32)+1))) -> 0 | E78: =IF(OR(E$4<Assumptions!$E$32,E$4<$B78),0,E56*IF(E$4>=Assumptions!$E$33,INDEX($D$94:$D$111,E$4-MAX($B78,Assumptions!$E$32)+1),INDEX($C$94:$C$111,E$4-MAX($B78,Assumptions!$E$32)+1))) -> 0 | F78: =IF(OR(F$4<Assumptions!$E$32,F$4<$B78),0,F56*IF(F$4>=Assumptions!$E$33,INDEX($D$94:$D$111,F$4-MAX($B78,Assumptions!$E$32)+1),INDEX($C$94:$C$111,F$4-MAX($B78,Assumptions!$E$32)+1))) -> 0 | G78: =IF(OR(G$4<Assumptions!$E$32,G$4<$B78),0,G56*IF(G$4>=Assumptions!$E$33,INDEX($D$94:$D$111,G$4-MAX($B78,Assumptions!$E$32)+1),INDEX($C$94:$C$111,G$4-MAX($B78,Assumptions!$E$32)+1))) -> 0 | H78: =IF(OR(H$4<Assumptions!$E$32,H$4<$B78),0,H56*IF(H$4>=Assumptions!$E$33,INDEX($D$94:$D$111,H$4-MAX($B78,Assumptions!$E$32)+1),INDEX($C$94:$C$111,H$4-MAX($B78,Assumptions!$E$32)+1))) -> 0 | I78: =IF(OR(I$4<Assumptions!$E$32,I$4<$B78),0,I56*IF(I$4>=Assumptions!$E$33,INDEX($D$94:$D$111,I$4-MAX($B78,Assumptions!$E$32)+1),INDEX($C$94:$C$111,I$4-MAX($B78,Assumptions!$E$32)+1))) -> 0 | J78: =IF(OR(J$4<Assumptions!$E$32,J$4<$B78),0,J56*IF(J$4>=Assumptions!$E$33,INDEX($D$94:$D$111,J$4-MAX($B78,Assumptions!$E$32)+1),INDEX($C$94:$C$111,J$4-MAX($B78,Assumptions!$E$32)+1))) -> 0 | K78: =IF(OR(K$4<Assumptions!$E$32,K$4<$B78),0,K56*IF(K$4>=Assumptions!$E$33,INDEX($D$94:$D$111,K$4-MAX($B78,Assumptions!$E$32)+1),INDEX($C$94:$C$111,K$4-MAX($B78,Assumptions!$E$32)+1))) -> 12.25 | ... U78: =IF(OR(U$4<Assumptions!$E$32,U$4<$B78),0,U56*IF(U$4>=Assumptions!$E$33,INDEX($D$94:$D$111,U$4-MAX($B78,Assumptions!$E$32)+1),INDEX($C$94:$C$111,U$4-MAX($B78,Assumptions!$E$32)+1))) -> 43.273712
A79: Cohort M9 | B79: 9 | D79: =IF(OR(D$4<Assumptions!$E$32,D$4<$B79),0,D57*IF(D$4>=Assumptions!$E$33,INDEX($D$94:$D$111,D$4-MAX($B79,Assumptions!$E$32)+1),INDEX($C$94:$C$111,D$4-MAX($B79,Assumptions!$E$32)+1))) -> 0 | E79: =IF(OR(E$4<Assumptions!$E$32,E$4<$B79),0,E57*IF(E$4>=Assumptions!$E$33,INDEX($D$94:$D$111,E$4-MAX($B79,Assumptions!$E$32)+1),INDEX($C$94:$C$111,E$4-MAX($B79,Assumptions!$E$32)+1))) -> 0 | F79: =IF(OR(F$4<Assumptions!$E$32,F$4<$B79),0,F57*IF(F$4>=Assumptions!$E$33,INDEX($D$94:$D$111,F$4-MAX($B79,Assumptions!$E$32)+1),INDEX($C$94:$C$111,F$4-MAX($B79,Assumptions!$E$32)+1))) -> 0 | G79: =IF(OR(G$4<Assumptions!$E$32,G$4<$B79),0,G57*IF(G$4>=Assumptions!$E$33,INDEX($D$94:$D$111,G$4-MAX($B79,Assumptions!$E$32)+1),INDEX($C$94:$C$111,G$4-MAX($B79,Assumptions!$E$32)+1))) -> 0 | H79: =IF(OR(H$4<Assumptions!$E$32,H$4<$B79),0,H57*IF(H$4>=Assumptions!$E$33,INDEX($D$94:$D$111,H$4-MAX($B79,Assumptions!$E$32)+1),INDEX($C$94:$C$111,H$4-MAX($B79,Assumptions!$E$32)+1))) -> 0 | I79: =IF(OR(I$4<Assumptions!$E$32,I$4<$B79),0,I57*IF(I$4>=Assumptions!$E$33,INDEX($D$94:$D$111,I$4-MAX($B79,Assumptions!$E$32)+1),INDEX($C$94:$C$111,I$4-MAX($B79,Assumptions!$E$32)+1))) -> 0 | J79: =IF(OR(J$4<Assumptions!$E$32,J$4<$B79),0,J57*IF(J$4>=Assumptions!$E$33,INDEX($D$94:$D$111,J$4-MAX($B79,Assumptions!$E$32)+1),INDEX($C$94:$C$111,J$4-MAX($B79,Assumptions!$E$32)+1))) -> 0 | K79: =IF(OR(K$4<Assumptions!$E$32,K$4<$B79),0,K57*IF(K$4>=Assumptions!$E$33,INDEX($D$94:$D$111,K$4-MAX($B79,Assumptions!$E$32)+1),INDEX($C$94:$C$111,K$4-MAX($B79,Assumptions!$E$32)+1))) -> 0 | ... U79: =IF(OR(U$4<Assumptions!$E$32,U$4<$B79),0,U57*IF(U$4>=Assumptions!$E$33,INDEX($D$94:$D$111,U$4-MAX($B79,Assumptions!$E$32)+1),INDEX($C$94:$C$111,U$4-MAX($B79,Assumptions!$E$32)+1))) -> 45.551276
A80: Cohort M10 | B80: 10 | D80: =IF(OR(D$4<Assumptions!$E$32,D$4<$B80),0,D58*IF(D$4>=Assumptions!$E$33,INDEX($D$94:$D$111,D$4-MAX($B80,Assumptions!$E$32)+1),INDEX($C$94:$C$111,D$4-MAX($B80,Assumptions!$E$32)+1))) -> 0 | E80: =IF(OR(E$4<Assumptions!$E$32,E$4<$B80),0,E58*IF(E$4>=Assumptions!$E$33,INDEX($D$94:$D$111,E$4-MAX($B80,Assumptions!$E$32)+1),INDEX($C$94:$C$111,E$4-MAX($B80,Assumptions!$E$32)+1))) -> 0 | F80: =IF(OR(F$4<Assumptions!$E$32,F$4<$B80),0,F58*IF(F$4>=Assumptions!$E$33,INDEX($D$94:$D$111,F$4-MAX($B80,Assumptions!$E$32)+1),INDEX($C$94:$C$111,F$4-MAX($B80,Assumptions!$E$32)+1))) -> 0 | G80: =IF(OR(G$4<Assumptions!$E$32,G$4<$B80),0,G58*IF(G$4>=Assumptions!$E$33,INDEX($D$94:$D$111,G$4-MAX($B80,Assumptions!$E$32)+1),INDEX($C$94:$C$111,G$4-MAX($B80,Assumptions!$E$32)+1))) -> 0 | H80: =IF(OR(H$4<Assumptions!$E$32,H$4<$B80),0,H58*IF(H$4>=Assumptions!$E$33,INDEX($D$94:$D$111,H$4-MAX($B80,Assumptions!$E$32)+1),INDEX($C$94:$C$111,H$4-MAX($B80,Assumptions!$E$32)+1))) -> 0 | I80: =IF(OR(I$4<Assumptions!$E$32,I$4<$B80),0,I58*IF(I$4>=Assumptions!$E$33,INDEX($D$94:$D$111,I$4-MAX($B80,Assumptions!$E$32)+1),INDEX($C$94:$C$111,I$4-MAX($B80,Assumptions!$E$32)+1))) -> 0 | J80: =IF(OR(J$4<Assumptions!$E$32,J$4<$B80),0,J58*IF(J$4>=Assumptions!$E$33,INDEX($D$94:$D$111,J$4-MAX($B80,Assumptions!$E$32)+1),INDEX($C$94:$C$111,J$4-MAX($B80,Assumptions!$E$32)+1))) -> 0 | K80: =IF(OR(K$4<Assumptions!$E$32,K$4<$B80),0,K58*IF(K$4>=Assumptions!$E$33,INDEX($D$94:$D$111,K$4-MAX($B80,Assumptions!$E$32)+1),INDEX($C$94:$C$111,K$4-MAX($B80,Assumptions!$E$32)+1))) -> 0 | ... U80: =IF(OR(U$4<Assumptions!$E$32,U$4<$B80),0,U58*IF(U$4>=Assumptions!$E$33,INDEX($D$94:$D$111,U$4-MAX($B80,Assumptions!$E$32)+1),INDEX($C$94:$C$111,U$4-MAX($B80,Assumptions!$E$32)+1))) -> 47.948712
A81: Cohort M11 | B81: 11 | D81: =IF(OR(D$4<Assumptions!$E$32,D$4<$B81),0,D59*IF(D$4>=Assumptions!$E$33,INDEX($D$94:$D$111,D$4-MAX($B81,Assumptions!$E$32)+1),INDEX($C$94:$C$111,D$4-MAX($B81,Assumptions!$E$32)+1))) -> 0 | E81: =IF(OR(E$4<Assumptions!$E$32,E$4<$B81),0,E59*IF(E$4>=Assumptions!$E$33,INDEX($D$94:$D$111,E$4-MAX($B81,Assumptions!$E$32)+1),INDEX($C$94:$C$111,E$4-MAX($B81,Assumptions!$E$32)+1))) -> 0 | F81: =IF(OR(F$4<Assumptions!$E$32,F$4<$B81),0,F59*IF(F$4>=Assumptions!$E$33,INDEX($D$94:$D$111,F$4-MAX($B81,Assumptions!$E$32)+1),INDEX($C$94:$C$111,F$4-MAX($B81,Assumptions!$E$32)+1))) -> 0 | G81: =IF(OR(G$4<Assumptions!$E$32,G$4<$B81),0,G59*IF(G$4>=Assumptions!$E$33,INDEX($D$94:$D$111,G$4-MAX($B81,Assumptions!$E$32)+1),INDEX($C$94:$C$111,G$4-MAX($B81,Assumptions!$E$32)+1))) -> 0 | H81: =IF(OR(H$4<Assumptions!$E$32,H$4<$B81),0,H59*IF(H$4>=Assumptions!$E$33,INDEX($D$94:$D$111,H$4-MAX($B81,Assumptions!$E$32)+1),INDEX($C$94:$C$111,H$4-MAX($B81,Assumptions!$E$32)+1))) -> 0 | I81: =IF(OR(I$4<Assumptions!$E$32,I$4<$B81),0,I59*IF(I$4>=Assumptions!$E$33,INDEX($D$94:$D$111,I$4-MAX($B81,Assumptions!$E$32)+1),INDEX($C$94:$C$111,I$4-MAX($B81,Assumptions!$E$32)+1))) -> 0 | J81: =IF(OR(J$4<Assumptions!$E$32,J$4<$B81),0,J59*IF(J$4>=Assumptions!$E$33,INDEX($D$94:$D$111,J$4-MAX($B81,Assumptions!$E$32)+1),INDEX($C$94:$C$111,J$4-MAX($B81,Assumptions!$E$32)+1))) -> 0 | K81: =IF(OR(K$4<Assumptions!$E$32,K$4<$B81),0,K59*IF(K$4>=Assumptions!$E$33,INDEX($D$94:$D$111,K$4-MAX($B81,Assumptions!$E$32)+1),INDEX($C$94:$C$111,K$4-MAX($B81,Assumptions!$E$32)+1))) -> 0 | ... U81: =IF(OR(U$4<Assumptions!$E$32,U$4<$B81),0,U59*IF(U$4>=Assumptions!$E$33,INDEX($D$94:$D$111,U$4-MAX($B81,Assumptions!$E$32)+1),INDEX($C$94:$C$111,U$4-MAX($B81,Assumptions!$E$32)+1))) -> 43.261995
A82: Cohort M12 | B82: 12 | D82: =IF(OR(D$4<Assumptions!$E$32,D$4<$B82),0,D60*IF(D$4>=Assumptions!$E$33,INDEX($D$94:$D$111,D$4-MAX($B82,Assumptions!$E$32)+1),INDEX($C$94:$C$111,D$4-MAX($B82,Assumptions!$E$32)+1))) -> 0 | E82: =IF(OR(E$4<Assumptions!$E$32,E$4<$B82),0,E60*IF(E$4>=Assumptions!$E$33,INDEX($D$94:$D$111,E$4-MAX($B82,Assumptions!$E$32)+1),INDEX($C$94:$C$111,E$4-MAX($B82,Assumptions!$E$32)+1))) -> 0 | F82: =IF(OR(F$4<Assumptions!$E$32,F$4<$B82),0,F60*IF(F$4>=Assumptions!$E$33,INDEX($D$94:$D$111,F$4-MAX($B82,Assumptions!$E$32)+1),INDEX($C$94:$C$111,F$4-MAX($B82,Assumptions!$E$32)+1))) -> 0 | G82: =IF(OR(G$4<Assumptions!$E$32,G$4<$B82),0,G60*IF(G$4>=Assumptions!$E$33,INDEX($D$94:$D$111,G$4-MAX($B82,Assumptions!$E$32)+1),INDEX($C$94:$C$111,G$4-MAX($B82,Assumptions!$E$32)+1))) -> 0 | H82: =IF(OR(H$4<Assumptions!$E$32,H$4<$B82),0,H60*IF(H$4>=Assumptions!$E$33,INDEX($D$94:$D$111,H$4-MAX($B82,Assumptions!$E$32)+1),INDEX($C$94:$C$111,H$4-MAX($B82,Assumptions!$E$32)+1))) -> 0 | I82: =IF(OR(I$4<Assumptions!$E$32,I$4<$B82),0,I60*IF(I$4>=Assumptions!$E$33,INDEX($D$94:$D$111,I$4-MAX($B82,Assumptions!$E$32)+1),INDEX($C$94:$C$111,I$4-MAX($B82,Assumptions!$E$32)+1))) -> 0 | J82: =IF(OR(J$4<Assumptions!$E$32,J$4<$B82),0,J60*IF(J$4>=Assumptions!$E$33,INDEX($D$94:$D$111,J$4-MAX($B82,Assumptions!$E$32)+1),INDEX($C$94:$C$111,J$4-MAX($B82,Assumptions!$E$32)+1))) -> 0 | K82: =IF(OR(K$4<Assumptions!$E$32,K$4<$B82),0,K60*IF(K$4>=Assumptions!$E$33,INDEX($D$94:$D$111,K$4-MAX($B82,Assumptions!$E$32)+1),INDEX($C$94:$C$111,K$4-MAX($B82,Assumptions!$E$32)+1))) -> 0 | ... U82: =IF(OR(U$4<Assumptions!$E$32,U$4<$B82),0,U60*IF(U$4>=Assumptions!$E$33,INDEX($D$94:$D$111,U$4-MAX($B82,Assumptions!$E$32)+1),INDEX($C$94:$C$111,U$4-MAX($B82,Assumptions!$E$32)+1))) -> 40.907864
... A88: Cohort M18 | B88: 18 | D88: =IF(OR(D$4<Assumptions!$E$32,D$4<$B88),0,D66*IF(D$4>=Assumptions!$E$33,INDEX($D$94:$D$111,D$4-MAX($B88,Assumptions!$E$32)+1),INDEX($C$94:$C$111,D$4-MAX($B88,Assumptions!$E$32)+1))) -> 0 | E88: =IF(OR(E$4<Assumptions!$E$32,E$4<$B88),0,E66*IF(E$4>=Assumptions!$E$33,INDEX($D$94:$D$111,E$4-MAX($B88,Assumptions!$E$32)+1),INDEX($C$94:$C$111,E$4-MAX($B88,Assumptions!$E$32)+1))) -> 0 | F88: =IF(OR(F$4<Assumptions!$E$32,F$4<$B88),0,F66*IF(F$4>=Assumptions!$E$33,INDEX($D$94:$D$111,F$4-MAX($B88,Assumptions!$E$32)+1),INDEX($C$94:$C$111,F$4-MAX($B88,Assumptions!$E$32)+1))) -> 0 | G88: =IF(OR(G$4<Assumptions!$E$32,G$4<$B88),0,G66*IF(G$4>=Assumptions!$E$33,INDEX($D$94:$D$111,G$4-MAX($B88,Assumptions!$E$32)+1),INDEX($C$94:$C$111,G$4-MAX($B88,Assumptions!$E$32)+1))) -> 0 | H88: =IF(OR(H$4<Assumptions!$E$32,H$4<$B88),0,H66*IF(H$4>=Assumptions!$E$33,INDEX($D$94:$D$111,H$4-MAX($B88,Assumptions!$E$32)+1),INDEX($C$94:$C$111,H$4-MAX($B88,Assumptions!$E$32)+1))) -> 0 | I88: =IF(OR(I$4<Assumptions!$E$32,I$4<$B88),0,I66*IF(I$4>=Assumptions!$E$33,INDEX($D$94:$D$111,I$4-MAX($B88,Assumptions!$E$32)+1),INDEX($C$94:$C$111,I$4-MAX($B88,Assumptions!$E$32)+1))) -> 0 | J88: =IF(OR(J$4<Assumptions!$E$32,J$4<$B88),0,J66*IF(J$4>=Assumptions!$E$33,INDEX($D$94:$D$111,J$4-MAX($B88,Assumptions!$E$32)+1),INDEX($C$94:$C$111,J$4-MAX($B88,Assumptions!$E$32)+1))) -> 0 | K88: =IF(OR(K$4<Assumptions!$E$32,K$4<$B88),0,K66*IF(K$4>=Assumptions!$E$33,INDEX($D$94:$D$111,K$4-MAX($B88,Assumptions!$E$32)+1),INDEX($C$94:$C$111,K$4-MAX($B88,Assumptions!$E$32)+1))) -> 0 | ... U88: =IF(OR(U$4<Assumptions!$E$32,U$4<$B88),0,U66*IF(U$4>=Assumptions!$E$33,INDEX($D$94:$D$111,U$4-MAX($B88,Assumptions!$E$32)+1),INDEX($C$94:$C$111,U$4-MAX($B88,Assumptions!$E$32)+1))) -> 7
A92: Bonus curve by badge age (months since max(cohort start, badge launch) + 1)
A93: Badge age | B93: Age # | C93: Rate before AI launch | D93: Rate after AI launch
A94: Age 1 | B94: 1 | C94: =Assumptions!$E$36*IF($B94<=3,INDEX(Assumptions!$C$48:$C$53,$B94),INDEX(Assumptions!$C$48:$C$53,4)) -> 0.0004 | D94: =Assumptions!$E$36*IF($B94<=3,INDEX(Assumptions!$C$48:$C$53,$B94),IF($B94<5,INDEX(Assumptions!$C$48:$C$53,4),IF($B94<8,(1-Assumptions!$E$37)*INDEX(Assumptions!$C$48:$C$53,4)+Assumptions!$E$37*INDEX(Assumptions!$C$48:$C$53,5),(1-Assumptions!$E$37)*INDEX(Assumptions!$C$48:$C$53,4)+Assumptions!$E$37*INDEX(Assumptions!$C$48:$C$53,6)))) -> 0.0004
A95: Age 2 | B95: 2 | C95: =Assumptions!$E$36*IF($B95<=3,INDEX(Assumptions!$C$48:$C$53,$B95),INDEX(Assumptions!$C$48:$C$53,4)) -> 0.0008 | D95: =Assumptions!$E$36*IF($B95<=3,INDEX(Assumptions!$C$48:$C$53,$B95),IF($B95<5,INDEX(Assumptions!$C$48:$C$53,4),IF($B95<8,(1-Assumptions!$E$37)*INDEX(Assumptions!$C$48:$C$53,4)+Assumptions!$E$37*INDEX(Assumptions!$C$48:$C$53,5),(1-Assumptions!$E$37)*INDEX(Assumptions!$C$48:$C$53,4)+Assumptions!$E$37*INDEX(Assumptions!$C$48:$C$53,6)))) -> 0.0008
A96: Age 3 | B96: 3 | C96: =Assumptions!$E$36*IF($B96<=3,INDEX(Assumptions!$C$48:$C$53,$B96),INDEX(Assumptions!$C$48:$C$53,4)) -> 0.0012 | D96: =Assumptions!$E$36*IF($B96<=3,INDEX(Assumptions!$C$48:$C$53,$B96),IF($B96<5,INDEX(Assumptions!$C$48:$C$53,4),IF($B96<8,(1-Assumptions!$E$37)*INDEX(Assumptions!$C$48:$C$53,4)+Assumptions!$E$37*INDEX(Assumptions!$C$48:$C$53,5),(1-Assumptions!$E$37)*INDEX(Assumptions!$C$48:$C$53,4)+Assumptions!$E$37*INDEX(Assumptions!$C$48:$C$53,6)))) -> 0.0012
A97: Age 4 | B97: 4 | C97: =Assumptions!$E$36*IF($B97<=3,INDEX(Assumptions!$C$48:$C$53,$B97),INDEX(Assumptions!$C$48:$C$53,4)) -> 0.002 | D97: =Assumptions!$E$36*IF($B97<=3,INDEX(Assumptions!$C$48:$C$53,$B97),IF($B97<5,INDEX(Assumptions!$C$48:$C$53,4),IF($B97<8,(1-Assumptions!$E$37)*INDEX(Assumptions!$C$48:$C$53,4)+Assumptions!$E$37*INDEX(Assumptions!$C$48:$C$53,5),(1-Assumptions!$E$37)*INDEX(Assumptions!$C$48:$C$53,4)+Assumptions!$E$37*INDEX(Assumptions!$C$48:$C$53,6)))) -> 0.002
A98: Age 5 | B98: 5 | C98: =Assumptions!$E$36*IF($B98<=3,INDEX(Assumptions!$C$48:$C$53,$B98),INDEX(Assumptions!$C$48:$C$53,4)) -> 0.002 | D98: =Assumptions!$E$36*IF($B98<=3,INDEX(Assumptions!$C$48:$C$53,$B98),IF($B98<5,INDEX(Assumptions!$C$48:$C$53,4),IF($B98<8,(1-Assumptions!$E$37)*INDEX(Assumptions!$C$48:$C$53,4)+Assumptions!$E$37*INDEX(Assumptions!$C$48:$C$53,5),(1-Assumptions!$E$37)*INDEX(Assumptions!$C$48:$C$53,4)+Assumptions!$E$37*INDEX(Assumptions!$C$48:$C$53,6)))) -> 0.00212
A99: Age 6 | B99: 6 | C99: =Assumptions!$E$36*IF($B99<=3,INDEX(Assumptions!$C$48:$C$53,$B99),INDEX(Assumptions!$C$48:$C$53,4)) -> 0.002 | D99: =Assumptions!$E$36*IF($B99<=3,INDEX(Assumptions!$C$48:$C$53,$B99),IF($B99<5,INDEX(Assumptions!$C$48:$C$53,4),IF($B99<8,(1-Assumptions!$E$37)*INDEX(Assumptions!$C$48:$C$53,4)+Assumptions!$E$37*INDEX(Assumptions!$C$48:$C$53,5),(1-Assumptions!$E$37)*INDEX(Assumptions!$C$48:$C$53,4)+Assumptions!$E$37*INDEX(Assumptions!$C$48:$C$53,6)))) -> 0.00212
A100: Age 7 | B100: 7 | C100: =Assumptions!$E$36*IF($B100<=3,INDEX(Assumptions!$C$48:$C$53,$B100),INDEX(Assumptions!$C$48:$C$53,4)) -> 0.002 | D100: =Assumptions!$E$36*IF($B100<=3,INDEX(Assumptions!$C$48:$C$53,$B100),IF($B100<5,INDEX(Assumptions!$C$48:$C$53,4),IF($B100<8,(1-Assumptions!$E$37)*INDEX(Assumptions!$C$48:$C$53,4)+Assumptions!$E$37*INDEX(Assumptions!$C$48:$C$53,5),(1-Assumptions!$E$37)*INDEX(Assumptions!$C$48:$C$53,4)+Assumptions!$E$37*INDEX(Assumptions!$C$48:$C$53,6)))) -> 0.00212
A101: Age 8 | B101: 8 | C101: =Assumptions!$E$36*IF($B101<=3,INDEX(Assumptions!$C$48:$C$53,$B101),INDEX(Assumptions!$C$48:$C$53,4)) -> 0.002 | D101: =Assumptions!$E$36*IF($B101<=3,INDEX(Assumptions!$C$48:$C$53,$B101),IF($B101<5,INDEX(Assumptions!$C$48:$C$53,4),IF($B101<8,(1-Assumptions!$E$37)*INDEX(Assumptions!$C$48:$C$53,4)+Assumptions!$E$37*INDEX(Assumptions!$C$48:$C$53,5),(1-Assumptions!$E$37)*INDEX(Assumptions!$C$48:$C$53,4)+Assumptions!$E$37*INDEX(Assumptions!$C$48:$C$53,6)))) -> 0.00236
